Workbook
Name mkt_brokers: Assumptions!$C$6
Name mkt_brokers_high: Assumptions!$C$7
Name mkt_carriers: Assumptions!$C$8
Name mkt_carriers_ds: Assumptions!$C$9
Name mkt_overlap: Assumptions!$C$10
Name mkt_case: Assumptions!$C$11
Name addressable: Assumptions!$C$12
Name pen_low: Assumptions!$C$13
Name pen_base: Assumptions!$C$14
Name pen_high: Assumptions!$C$15
Name ramp_exp: Assumptions!$C$16
Name start_tenants: Assumptions!$C$17
Name churn_m: Assumptions!$C$18
Name p_platform: Assumptions!$C$21
Name p_dialer: Assumptions!$C$22
Name incl_min: Assumptions!$C$23
Name over_mult: Assumptions!$C$24
Name bill_over: Assumptions!$C$25
Name p_sms: Assumptions!$C$26
Name incl_seg: Assumptions!$C$27
Name sms_setup: Assumptions!$C$28
Name p_comp: Assumptions!$C$29
Name p_ai: Assumptions!$C$30
Name p_onboard: Assumptions!$C$31
Name bundle_disc: Assumptions!$C$32
Name att_dialer: Assumptions!$C$33
Name att_sms: Assumptions!$C$34
Name att_comp: Assumptions!$C$35
Name att_ai: Assumptions!$C$36
Name zoho_margin: Assumptions!$C$37
Name target_gm: Assumptions!$C$38
Name seats: Assumptions!$C$41
Name nums_per_seat: Assumptions!$C$42
Name nums_shared: Assumptions!$C$43
Name leads_per_seat: Assumptions!$C$44
Name d_leads: Assumptions!$C$45
Name workdays: Assumptions!$C$48
Name att_day: Assumptions!$C$49
Name sh_person: Assumptions!$C$50
Name sh_vm: Assumptions!$C$51
Name sh_unans: Assumptions!$C$52
Name min_person: Assumptions!$C$53
Name min_vm: Assumptions!$C$54
Name min_ring: Assumptions!$C$55
Name in_day: Assumptions!$C$56
Name in_ans: Assumptions!$C$57
Name min_in: Assumptions!$C$58
Name min_in_unans: Assumptions!$C$59
Name rec_out: Assumptions!$C$60
Name rec_in: Assumptions!$C$61
Name retention: Assumptions!$C$62
Name amd_on: Assumptions!$C$63
Name band: Assumptions!$C$64
Name d_attempts: Assumptions!$C$65
Name d_out_min: Assumptions!$C$66
Name d_in_calls: Assumptions!$C$67
Name d_in_min: Assumptions!$C$68
Name d_browser_min: Assumptions!$C$69
Name d_rec_min: Assumptions!$C$70
Name d_calls: Assumptions!$C$71

Sheet Assumptions
A1: HaulOS pricing model: assumptions
A2: Blue is an input. Black is a formula. Every input carries a source and a confidence. ASSUMPTION means nobody has measured it.
A4: Key | B4: Input | C4: Value | D4: Unit | E4: Source | F4: Confidence | G4: Note
A5: Market
A6: mkt_brokers | B6: Active household-goods broker authorities | C6: 901 | D6: firms | E6: FMCSA dataset 6eyk-hxee on data.transportation.gov, counted 2026-10-04: broker_stat='A' AND hhg_chk='Y' | F6: Med | G6: The count is exact. What the household-goods flag means is not fully confirmed.
A7: mkt_brokers_high | B7: Broker count, high case | C7: 1256 | D7: firms | E7: FMCSA 2024 notice, as given in the brief; not re-read | F7: Med
A8: mkt_carriers | B8: Household-goods carriers | C8: 4000 | D8: firms | E8: Figure given in the brief ("roughly 4,000", older) | F8: Low | G8: The dataset counts 8,596 active carrier authorities with the flag: see the next row.
A9: mkt_carriers_ds | B9: Carrier count, dataset upper bound | C9: 8596 | D9: firms | E9: FMCSA dataset 6eyk-hxee on data.transportation.gov, counted 2026-10-04: hhg_chk='Y' AND (common_stat='A' OR contract_stat='A') | F9: Low | G9: An authority that covers household goods, not proof the firm moves households.
A10: mkt_overlap | B10: Firms that are both broker and carrier | C10: 237 | D10: firms | E10: FMCSA dataset 6eyk-hxee on data.transportation.gov, counted 2026-10-04 | F10: Med
A11: mkt_case | B11: Market case: 1 brokers, 2 brokers high, 3 brokers + carriers, 4 brokers + carriers (dataset) | C11: 1 | D11: switch | E11: Choice | F11: ASSUMPTION
A12: addressable | B12: Addressable firms, selected case | C12: =CHOOSE($C$11,$C$6,$C$7,$C$6+$C$8-$C$10,$C$6+$C$9-$C$10) | D12: firms | E12: Formula
A13: pen_low | B13: Share of addressable firms at month 24, low | C13: 0.02 | D13: % | E13: Starting hypothesis in the brief | F13: ASSUMPTION
A14: pen_base | B14: Share of addressable firms at month 24, base | C14: 0.05 | D14: % | E14: Starting hypothesis in the brief | F14: ASSUMPTION
A15: pen_high | B15: Share of addressable firms at month 24, high | C15: 0.1 | D15: % | E15: Starting hypothesis in the brief | F15: ASSUMPTION
A16: ramp_exp | B16: Ramp shape | C16: 1.5 | D16: exponent | E16: Nothing measured | F16: ASSUMPTION | G16: 1 is a straight line to month 24. Higher starts slower.
A17: start_tenants | B17: Tenants today | C17: 1 | D17: tenants | E17: The first client is live | F17: High
A18: churn_m | B18: Tenants lost per month | C18: 0.015 | D18: % | E18: Nothing measured | F18: ASSUMPTION | G18: Only changes how many new tenants are needed, and so the one-time fees.
A20: Prices
A21: p_platform | B21: Platform fee | C21: 349 | D21: $ / tenant / month | E21: Starting hypothesis in the brief (test $299 to $499) | F21: ASSUMPTION
A22: p_dialer | B22: Dialer add-on | C22: 79 | D22: $ / seat / month | E22: Starting hypothesis in the brief | F22: ASSUMPTION
A23: incl_min | B23: Minutes included with a dialer seat | C23: 1200 | D23: minutes / seat / month | E23: Starting hypothesis in the brief | F23: ASSUMPTION | G23: Counted as phone minutes, outbound plus inbound.
A24: over_mult | B24: Overage price as a multiple of cost | C24: 2.5 | D24: x | E24: Starting hypothesis in the brief | F24: ASSUMPTION
A25: bill_over | B25: Overage is charged: 1 yes, 0 no | C25: 1 | D25: switch | E25: Choice | F25: ASSUMPTION
A26: p_sms | B26: SMS add-on | C26: 49 | D26: $ / tenant / month | E26: Starting hypothesis in the brief | F26: ASSUMPTION
A27: incl_seg | B27: Segments included with the SMS add-on | C27: 1000 | D27: segments / month | E27: Starting hypothesis in the brief | F27: ASSUMPTION | G27: Outbound segments.
A28: sms_setup | B28: SMS setup fee | C28: 399 | D28: $ one-time | E28: Starting hypothesis in the brief | F28: ASSUMPTION
A29: p_comp | B29: Compliance module | C29: 79 | D29: $ / tenant / month | E29: Starting hypothesis in the brief | F29: ASSUMPTION
A30: p_ai | B30: AI SMS add-on | C30: 249 | D30: $ / tenant / month | E30: Starting hypothesis in the brief (a test price) | F30: ASSUMPTION
A31: p_onboard | B31: Platform setup fee | C31: 0 | D31: $ one-time | E31: Not in the brief | F31: ASSUMPTION | G31: Set above zero to model a setup fee.
A32: bundle_disc | B32: Discount on a bundle | C32: 0 | D32: % | E32: Not in the brief | F32: ASSUMPTION
A33: att_dialer | B33: Tenants that take the dialer | C33: 0.6 | D33: % | E33: Starting hypothesis in the brief | F33: ASSUMPTION
A34: att_sms | B34: Tenants that take SMS | C34: 0.5 | D34: % | E34: Starting hypothesis in the brief | F34: ASSUMPTION
A35: att_comp | B35: Tenants that take compliance | C35: 0.4 | D35: % | E35: Starting hypothesis in the brief | F35: ASSUMPTION
A36: att_ai | B36: Tenants that take AI SMS | C36: 0.2 | D36: % | E36: Starting hypothesis in the brief | F36: ASSUMPTION
A37: zoho_margin | B37: Kore margin on Zoho licenses | C37: 0 | D37: % | E37: Partner application in progress. Zoho publishes no reseller margin | F37: ASSUMPTION | G37: One third-party page says 15% to 25% (Low confidence).
A38: target_gm | B38: Gross-margin target | C38: 0.7 | D38: % | E38: Nothing measured | F38: ASSUMPTION | G38: Used only for the breakeven lines.
A40: Tenant shape
A41: seats | B41: Seats per tenant | C41: 4 | D41: seats | E41: Starting hypothesis in the brief | F41: ASSUMPTION | G41: The first client has 2 Zoho Voice users (seen 2026-09-30).
A42: nums_per_seat | B42: Phone numbers per seat | C42: 1 | D42: numbers | E42: Nothing measured | F42: ASSUMPTION | G42: A direct line per rep.
A43: nums_shared | B43: Shared phone numbers per tenant | C43: 1 | D43: numbers | E43: Nothing measured | F43: ASSUMPTION | G43: The main line.
A44: leads_per_seat | B44: New leads per seat per month | C44: 100 | D44: leads | E44: Nothing measured | F44: ASSUMPTION
A45: d_leads | B45: New leads per tenant per month | C45: =$C$41*$C$44 | D45: leads | E45: Formula
A47: Calling: what a seat does
A48: workdays | B48: Working days a month | C48: 21 | D48: days | E48: Nothing measured | F48: ASSUMPTION
A49: att_day | B49: Outbound dial attempts per seat per day | C49: 60 | D49: attempts | E49: Nothing measured | F49: ASSUMPTION | G49: The biggest unknown in the model.
A50: sh_person | B50: Attempts answered by a person | C50: 0.2 | D50: % | E50: Nothing measured | F50: ASSUMPTION
A51: sh_vm | B51: Attempts answered by voicemail | C51: 0.35 | D51: % | E51: Nothing measured | F51: ASSUMPTION
A52: sh_unans | B52: Attempts not answered | C52: =1-$C$50-$C$51 | D52: % | E52: Formula
A53: min_person | B53: Billed minutes when a person answers | C53: 4 | D53: minutes | E53: Nothing measured | F53: ASSUMPTION | G53: Each call is rounded up to a whole minute.
A54: min_vm | B54: Billed minutes when voicemail answers | C54: 1 | D54: minutes | E54: Nothing measured | F54: ASSUMPTION
A55: min_ring | B55: Browser-leg minutes billed on an unanswered attempt | C55: 1 | D55: minutes | E55: Code: no answerOnBridge on the dial (src/routes/voice.js) | F55: ASSUMPTION | G55: UNVERIFIED against a bill. Set to 0 if ring time turns out to be free.
A56: in_day | B56: Inbound calls per seat per day | C56: 8 | D56: calls | E56: Nothing measured | F56: ASSUMPTION
A57: in_ans | B57: Inbound calls answered | C57: 0.8 | D57: % | E57: Nothing measured | F57: ASSUMPTION
A58: min_in | B58: Billed minutes per answered inbound call | C58: 4 | D58: minutes | E58: Nothing measured | F58: ASSUMPTION
A59: min_in_unans | B59: Billed inbound minutes on an unanswered inbound call | C59: 1 | D59: minutes | E59: Code: no answerOnBridge (src/routes/inbound.js) | F59: ASSUMPTION | G59: UNVERIFIED against a bill.
A60: rec_out | B60: Outbound calls are recorded: 1 yes, 0 no | C60: 1 | D60: switch | E60: Code: record-from-answer on every outbound call (src/routes/voice.js:21) | F60: High
A61: rec_in | B61: Inbound calls are recorded: 1 yes, 0 no | C61: 0 | D61: switch | E61: Code: no record on the inbound dial (src/routes/inbound.js:21) | F61: High
A62: retention | B62: Months a recording is kept | C62: 12 | D62: months | E62: Nothing measured | F62: ASSUMPTION | G62: The code never deletes a recording. 12 assumes a retention rule is added.
A63: amd_on | B63: Answering machine detection: 1 on, 0 off | C63: 0 | D63: switch | E63: Code: not used anywhere in src/ | F63: High | G63: The planned auto dialer would turn this on.
A64: band | B64: Low and high band when there are under 3 months of data | C64: 0.5 | D64: % | E64: Rule in the brief | F64: High
A65: d_attempts | B65: Outbound attempts per seat per month | C65: =$C$48*$C$49 | D65: calls | E65: Formula
A66: d_out_min | B66: Billed minutes, PSTN outbound, per seat | C66: =$C$65*($C$50*$C$53+$C$51*$C$54) | D66: minutes | E66: Formula
A67: d_in_calls | B67: Inbound calls per seat per month | C67: =$C$48*$C$56 | D67: calls | E67: Formula
A68: d_in_min | B68: Billed minutes, PSTN inbound, per seat | C68: =$C$67*($C$57*$C$58+(1-$C$57)*$C$59) | D68: minutes | E68: Formula
A69: d_browser_min | B69: Billed minutes, browser leg, per seat | C69: =$C$66+$C$65*$C$52*$C$55+$C$67*$C$57*$C$58 | D69: minutes | E69: Formula
A70: d_rec_min | B70: Recorded minutes per seat | C70: =$C$66*$C$60+$C$67*$C$57*$C$58*$C$61 | D70: minutes | E70: Formula
A71: d_calls | B71: Calls per seat per month | C71: =$C$65+$C$67 | D71: calls | E71: Formula
A72: d_amd | B72: Answering-machine-detection calls per seat | C72: =$C$65*$C$63 | D72: calls | E72: Formula
A74: Texting: what a seat sends
A75: texts_per_lead | B75: Automated texts per lead | C75: 6 | D75: texts | E75: Nothing measured | F75: ASSUMPTION
A76: seg_per_text | B76: Segments per automated text | C76: 1.6 | D76: segments | E76: Nothing measured | F76: ASSUMPTION | G76: A text with a signature line usually runs past 160 characters.
A77: manual_day | B77: Texts an agent types per day | C77: 10 | D77: texts | E77: Nothing measured | F77: ASSUMPTION
A78: seg_manual | B78: Segments per typed text | C78: 1.3 | D78: segments | E78: Nothing measured | F78: ASSUMPTION
A79: reply_rate | B79: Leads that reply | C79: 0.25 | D79: % | E79: Nothing measured | F79: ASSUMPTION
A80: in_per_reply | B80: Inbound messages per replying lead | C80: 2 | D80: messages | E80: Nothing measured | F80: ASSUMPTION
A81: d_seg_out | B81: Outbound segments per seat per month | C81: =$C$44*$C$75*$C$76+$C$48*$C$77*$C$78 | D81: segments | E81: Formula
A82: d_seg_in | B82: Inbound segments per seat per month | C82: =$C$44*$C$79*$C$80 | D82: segments | E82: Formula
A84: AI SMS: what a tenant uses
A85: ai_turns | B85: AI replies per conversation | C85: 4 | D85: turns | E85: Nothing measured | F85: ASSUMPTION
A86: tok_in | B86: Input tokens per AI reply | C86: 3500 | D86: tokens | E86: Nothing measured | F86: ASSUMPTION | G86: Instructions plus the thread so far.
A87: tok_out | B87: Output tokens per AI reply | C87: 300 | D87: tokens | E87: Nothing measured | F87: ASSUMPTION
A88: ai_seg_out | B88: Segments per AI text | C88: 1.6 | D88: segments | E88: Nothing measured | F88: ASSUMPTION
A89: ai_seg_in | B89: Segments per reply | C89: 1 | D89: segments | E89: Nothing measured | F89: ASSUMPTION
A90: d_ai_convos | B90: AI conversations per tenant per month | C90: =$C$45*$C$79 | D90: conversations | E90: Formula
A92: Twilio Programmable Voice, US
A93: tw_out | B93: Outbound to a US number | C93: 0.014 | D93: $ / minute | E93: twilio.com/en-us/voice/pricing/us, read 2026-10-04 (page dated August 2026) | F93: High
A94: tw_in | B94: Inbound on a local number | C94: 0.0085 | D94: $ / minute | E94: twilio.com/en-us/voice/pricing/us, read 2026-10-04 (page dated August 2026) | F94: High
A95: tw_client | B95: Browser (Voice SDK) leg | C95: 0.004 | D95: $ / minute | E95: twilio.com/en-us/voice/pricing/us, read 2026-10-04 (page dated August 2026) | F95: High | G95: Billed on top of the phone leg. Each leg rounds up to a minute.
A96: tw_rec | B96: Call recording | C96: 0.0025 | D96: $ / minute | E96: twilio.com/en-us/voice/pricing/us, read 2026-10-04 (page dated August 2026) | F96: High
A97: tw_store | B97: Recording storage | C97: 0.0005 | D97: $ / minute / month | E97: twilio.com/en-us/voice/pricing/us, read 2026-10-04 (page dated August 2026) | F97: High | G97: No free allotment is stated on the page.
A98: tw_num | B98: Local number | C98: 1.15 | D98: $ / month | E98: twilio.com/en-us/voice/pricing/us, read 2026-10-04 (page dated August 2026) | F98: High
A99: tw_amd | B99: Answering machine detection | C99: 0.0075 | D99: $ / call | E99: twilio.com/en-us/voice/pricing/us, read 2026-10-04 (page dated August 2026) | F99: High
A101: Twilio Messaging and 10DLC, US
A102: tw_sms_out | B102: Outbound SMS | C102: 0.0083 | D102: $ / segment | E102: twilio.com/en-us/sms/pricing/us, read 2026-10-04 (page dated September 2026) | F102: High | G102: One flat rate. No volume tiers are published.
A103: tw_sms_in | B103: Inbound SMS | C103: 0.0083 | D103: $ / segment | E103: twilio.com/en-us/sms/pricing/us, read 2026-10-04 (page dated September 2026) | F103: High
A104: tw_car_out | B104: Carrier fee, outbound, blended | C104: 0.0044 | D104: $ / segment | E104: twilio.com/en-us/sms/pricing/us, read 2026-10-04 (page dated September 2026) | F104: Med | G104: Rates are published: AT&T $0.0035, T-Mobile $0.0045, Verizon $0.005, US Cellular $0.005, others $0.0042. The blend is an ASSUMPTION (Verizon 35%, T-Mobile 33%, AT&T 28%, others 4%).
A105: tw_car_in | B105: Carrier fee, inbound, blended | C105: 0.0018 | D105: $ / segment | E105: twilio.com/en-us/sms/pricing/us, read 2026-10-04 (page dated September 2026) | F105: Med | G105: AT&T $0.0035, T-Mobile and US Cellular $0.0025, none listed for Verizon. Same blend.
A106: tw_brand | B106: 10DLC brand registration | C106: 4.5 | D106: $ one-time | E106: Twilio help article 1260803965530 (A2P 10DLC fees), read 2026-10-04 | F106: High | G106: Low-volume standard brand. A standard brand is $46.
A107: tw_vet | B107: 10DLC campaign vetting | C107: 15 | D107: $ one-time | E107: Twilio help article 1260803965530 (A2P 10DLC fees), read 2026-10-04 | F107: High
A108: tw_camp_mo | B108: 10DLC campaign fee | C108: 1.5 | D108: $ / month | E108: Twilio help article 1260803965530 (A2P 10DLC fees), read 2026-10-04 | F108: High | G108: Low-volume mixed campaign, capped at 2,000 segments a day to T-Mobile. A standard campaign is $10.
...

Sheet UsageActuals
A1: Usage actuals
A2: From inputs/usage-actuals.json, pulled 2026-10-05T02:27:33Z, window 2026-07-01 to 2026-10-04. A blank cell is a null: not retrieved, not zero.
A4: Include = 1 counts the row in the per-seat figures. Development, sandbox and part-months start at 0. Set a ramp-up month to 0 to leave it out.
E5: voice | F5: voice | G5: voice | H5: voice | I5: voice | J5: voice | K5: voice | L5: voice | M5: voice | N5: voice | O5: voice | P5: voice | Q5: voice | R5: voice | S5: sms | T5: sms | U5: sms | V5: sms | W5: sms | X5: sms | Y5: sms | Z5: sms | AA5: zoho_crm | AB5: zoho_crm | AC5: zoho_crm | AD5: zoho_crm | AE5: zoho_crm | AF5: zoho_crm | AG5: zoho_marketing | AI5: derived | AJ5: derived | AK5: derived | AL5: derived | AM5: derived | AN5: derived | AO5: derived | AP5: derived | AQ5: derived
A6: Tenant | B6: Environment | C6: Month | D6: Include | E6: calls_out | F6: calls_in | G6: connected_calls | H6: avg_duration_sec | I6: median_duration_sec | J6: billed_min_total | K6: billed_min_pstn_out | L6: billed_min_pstn_in | M6: billed_min_browser_leg | N6: recorded_min | O6: voicemail_drops | P6: amd_calls | Q6: active_agents | R6: peak_concurrent | S6: msgs_out | T6: msgs_in | U6: segments_out | V6: segments_in | W6: delivery_rate | X6: opt_outs | Y6: filtered_errors | Z6: carrier_fee_usd | AA6: licensed_users | AB6: edition | AC6: api_credits_per_day_avg | AD6: api_credits_per_day_peak | AE6: api_credit_limit | AF6: call_records_created | AG6: sends | AI6: Billed minutes, PSTN outbound, per seat / month | AJ6: Billed minutes, PSTN inbound, per seat / month | AK6: Billed minutes, browser leg, per seat / month | AL6: Recorded minutes, per seat / month | AM6: Calls, out plus in, per seat / month | AN6: Answering-machine-detection calls, per seat / month | AO6: Outbound SMS segments, per seat / month | AP6: Inbound SMS segments, per seat / month | AQ6: AI conversations, per tenant / month
A7: kore | B7: dev | C7: 2026-07 | D7: 0 | AI7: =IF(AND($D7=1,ISNUMBER(K7),ISNUMBER(Q7)),IF(Q7>0,(K7)/Q7,""),"") | AJ7: =IF(AND($D7=1,ISNUMBER(L7),ISNUMBER(Q7)),IF(Q7>0,(L7)/Q7,""),"") | AK7: =IF(AND($D7=1,ISNUMBER(M7),ISNUMBER(Q7)),IF(Q7>0,(M7)/Q7,""),"") | AL7: =IF(AND($D7=1,ISNUMBER(N7),ISNUMBER(Q7)),IF(Q7>0,(N7)/Q7,""),"") | AM7: =IF(AND($D7=1,ISNUMBER(E7),ISNUMBER(F7),ISNUMBER(Q7)),IF(Q7>0,(E7+F7)/Q7,""),"") | AN7: =IF(AND($D7=1,ISNUMBER(P7),ISNUMBER(Q7)),IF(Q7>0,(P7)/Q7,""),"") | AO7: =IF(AND($D7=1,ISNUMBER(U7),ISNUMBER(Q7)),IF(Q7>0,(U7)/Q7,""),"") | AP7: =IF(AND($D7=1,ISNUMBER(V7),ISNUMBER(Q7)),IF(Q7>0,(V7)/Q7,""),"")
A8: kore | B8: dev | C8: 2026-08 | D8: 0 | AI8: =IF(AND($D8=1,ISNUMBER(K8),ISNUMBER(Q8)),IF(Q8>0,(K8)/Q8,""),"") | AJ8: =IF(AND($D8=1,ISNUMBER(L8),ISNUMBER(Q8)),IF(Q8>0,(L8)/Q8,""),"") | AK8: =IF(AND($D8=1,ISNUMBER(M8),ISNUMBER(Q8)),IF(Q8>0,(M8)/Q8,""),"") | AL8: =IF(AND($D8=1,ISNUMBER(N8),ISNUMBER(Q8)),IF(Q8>0,(N8)/Q8,""),"") | AM8: =IF(AND($D8=1,ISNUMBER(E8),ISNUMBER(F8),ISNUMBER(Q8)),IF(Q8>0,(E8+F8)/Q8,""),"") | AN8: =IF(AND($D8=1,ISNUMBER(P8),ISNUMBER(Q8)),IF(Q8>0,(P8)/Q8,""),"") | AO8: =IF(AND($D8=1,ISNUMBER(U8),ISNUMBER(Q8)),IF(Q8>0,(U8)/Q8,""),"") | AP8: =IF(AND($D8=1,ISNUMBER(V8),ISNUMBER(Q8)),IF(Q8>0,(V8)/Q8,""),"")
A9: kore | B9: dev | C9: 2026-09 | D9: 0 | AI9: =IF(AND($D9=1,ISNUMBER(K9),ISNUMBER(Q9)),IF(Q9>0,(K9)/Q9,""),"") | AJ9: =IF(AND($D9=1,ISNUMBER(L9),ISNUMBER(Q9)),IF(Q9>0,(L9)/Q9,""),"") | AK9: =IF(AND($D9=1,ISNUMBER(M9),ISNUMBER(Q9)),IF(Q9>0,(M9)/Q9,""),"") | AL9: =IF(AND($D9=1,ISNUMBER(N9),ISNUMBER(Q9)),IF(Q9>0,(N9)/Q9,""),"") | AM9: =IF(AND($D9=1,ISNUMBER(E9),ISNUMBER(F9),ISNUMBER(Q9)),IF(Q9>0,(E9+F9)/Q9,""),"") | AN9: =IF(AND($D9=1,ISNUMBER(P9),ISNUMBER(Q9)),IF(Q9>0,(P9)/Q9,""),"") | AO9: =IF(AND($D9=1,ISNUMBER(U9),ISNUMBER(Q9)),IF(Q9>0,(U9)/Q9,""),"") | AP9: =IF(AND($D9=1,ISNUMBER(V9),ISNUMBER(Q9)),IF(Q9>0,(V9)/Q9,""),"")
A10: kore | B10: dev | C10: 2026-10 | D10: 0 | AI10: =IF(AND($D10=1,ISNUMBER(K10),ISNUMBER(Q10)),IF(Q10>0,(K10)/Q10,""),"") | AJ10: =IF(AND($D10=1,ISNUMBER(L10),ISNUMBER(Q10)),IF(Q10>0,(L10)/Q10,""),"") | AK10: =IF(AND($D10=1,ISNUMBER(M10),ISNUMBER(Q10)),IF(Q10>0,(M10)/Q10,""),"") | AL10: =IF(AND($D10=1,ISNUMBER(N10),ISNUMBER(Q10)),IF(Q10>0,(N10)/Q10,""),"") | AM10: =IF(AND($D10=1,ISNUMBER(E10),ISNUMBER(F10),ISNUMBER(Q10)),IF(Q10>0,(E10+F10)/Q10,""),"") | AN10: =IF(AND($D10=1,ISNUMBER(P10),ISNUMBER(Q10)),IF(Q10>0,(P10)/Q10,""),"") | AO10: =IF(AND($D10=1,ISNUMBER(U10),ISNUMBER(Q10)),IF(Q10>0,(U10)/Q10,""),"") | AP10: =IF(AND($D10=1,ISNUMBER(V10),ISNUMBER(Q10)),IF(Q10>0,(V10)/Q10,""),"")
A11: kore-sandbox | B11: sandbox | C11: 2026-07 | D11: 0 | AI11: =IF(AND($D11=1,ISNUMBER(K11),ISNUMBER(Q11)),IF(Q11>0,(K11)/Q11,""),"") | AJ11: =IF(AND($D11=1,ISNUMBER(L11),ISNUMBER(Q11)),IF(Q11>0,(L11)/Q11,""),"") | AK11: =IF(AND($D11=1,ISNUMBER(M11),ISNUMBER(Q11)),IF(Q11>0,(M11)/Q11,""),"") | AL11: =IF(AND($D11=1,ISNUMBER(N11),ISNUMBER(Q11)),IF(Q11>0,(N11)/Q11,""),"") | AM11: =IF(AND($D11=1,ISNUMBER(E11),ISNUMBER(F11),ISNUMBER(Q11)),IF(Q11>0,(E11+F11)/Q11,""),"") | AN11: =IF(AND($D11=1,ISNUMBER(P11),ISNUMBER(Q11)),IF(Q11>0,(P11)/Q11,""),"") | AO11: =IF(AND($D11=1,ISNUMBER(U11),ISNUMBER(Q11)),IF(Q11>0,(U11)/Q11,""),"") | AP11: =IF(AND($D11=1,ISNUMBER(V11),ISNUMBER(Q11)),IF(Q11>0,(V11)/Q11,""),"")
A12: kore-sandbox | B12: sandbox | C12: 2026-08 | D12: 0 | AI12: =IF(AND($D12=1,ISNUMBER(K12),ISNUMBER(Q12)),IF(Q12>0,(K12)/Q12,""),"") | AJ12: =IF(AND($D12=1,ISNUMBER(L12),ISNUMBER(Q12)),IF(Q12>0,(L12)/Q12,""),"") | AK12: =IF(AND($D12=1,ISNUMBER(M12),ISNUMBER(Q12)),IF(Q12>0,(M12)/Q12,""),"") | AL12: =IF(AND($D12=1,ISNUMBER(N12),ISNUMBER(Q12)),IF(Q12>0,(N12)/Q12,""),"") | AM12: =IF(AND($D12=1,ISNUMBER(E12),ISNUMBER(F12),ISNUMBER(Q12)),IF(Q12>0,(E12+F12)/Q12,""),"") | AN12: =IF(AND($D12=1,ISNUMBER(P12),ISNUMBER(Q12)),IF(Q12>0,(P12)/Q12,""),"") | AO12: =IF(AND($D12=1,ISNUMBER(U12),ISNUMBER(Q12)),IF(Q12>0,(U12)/Q12,""),"") | AP12: =IF(AND($D12=1,ISNUMBER(V12),ISNUMBER(Q12)),IF(Q12>0,(V12)/Q12,""),"")
A13: kore-sandbox | B13: sandbox | C13: 2026-09 | D13: 0 | AI13: =IF(AND($D13=1,ISNUMBER(K13),ISNUMBER(Q13)),IF(Q13>0,(K13)/Q13,""),"") | AJ13: =IF(AND($D13=1,ISNUMBER(L13),ISNUMBER(Q13)),IF(Q13>0,(L13)/Q13,""),"") | AK13: =IF(AND($D13=1,ISNUMBER(M13),ISNUMBER(Q13)),IF(Q13>0,(M13)/Q13,""),"") | AL13: =IF(AND($D13=1,ISNUMBER(N13),ISNUMBER(Q13)),IF(Q13>0,(N13)/Q13,""),"") | AM13: =IF(AND($D13=1,ISNUMBER(E13),ISNUMBER(F13),ISNUMBER(Q13)),IF(Q13>0,(E13+F13)/Q13,""),"") | AN13: =IF(AND($D13=1,ISNUMBER(P13),ISNUMBER(Q13)),IF(Q13>0,(P13)/Q13,""),"") | AO13: =IF(AND($D13=1,ISNUMBER(U13),ISNUMBER(Q13)),IF(Q13>0,(U13)/Q13,""),"") | AP13: =IF(AND($D13=1,ISNUMBER(V13),ISNUMBER(Q13)),IF(Q13>0,(V13)/Q13,""),"")
A14: kore-sandbox | B14: sandbox | C14: 2026-10 | D14: 0 | AI14: =IF(AND($D14=1,ISNUMBER(K14),ISNUMBER(Q14)),IF(Q14>0,(K14)/Q14,""),"") | AJ14: =IF(AND($D14=1,ISNUMBER(L14),ISNUMBER(Q14)),IF(Q14>0,(L14)/Q14,""),"") | AK14: =IF(AND($D14=1,ISNUMBER(M14),ISNUMBER(Q14)),IF(Q14>0,(M14)/Q14,""),"") | AL14: =IF(AND($D14=1,ISNUMBER(N14),ISNUMBER(Q14)),IF(Q14>0,(N14)/Q14,""),"") | AM14: =IF(AND($D14=1,ISNUMBER(E14),ISNUMBER(F14),ISNUMBER(Q14)),IF(Q14>0,(E14+F14)/Q14,""),"") | AN14: =IF(AND($D14=1,ISNUMBER(P14),ISNUMBER(Q14)),IF(Q14>0,(P14)/Q14,""),"") | AO14: =IF(AND($D14=1,ISNUMBER(U14),ISNUMBER(Q14)),IF(Q14>0,(U14)/Q14,""),"") | AP14: =IF(AND($D14=1,ISNUMBER(V14),ISNUMBER(Q14)),IF(Q14>0,(V14)/Q14,""),"")
A15: the-moving-group | B15: prod | C15: 2026-07 | D15: 1 | AI15: =IF(AND($D15=1,ISNUMBER(K15),ISNUMBER(Q15)),IF(Q15>0,(K15)/Q15,""),"") | AJ15: =IF(AND($D15=1,ISNUMBER(L15),ISNUMBER(Q15)),IF(Q15>0,(L15)/Q15,""),"") | AK15: =IF(AND($D15=1,ISNUMBER(M15),ISNUMBER(Q15)),IF(Q15>0,(M15)/Q15,""),"") | AL15: =IF(AND($D15=1,ISNUMBER(N15),ISNUMBER(Q15)),IF(Q15>0,(N15)/Q15,""),"") | AM15: =IF(AND($D15=1,ISNUMBER(E15),ISNUMBER(F15),ISNUMBER(Q15)),IF(Q15>0,(E15+F15)/Q15,""),"") | AN15: =IF(AND($D15=1,ISNUMBER(P15),ISNUMBER(Q15)),IF(Q15>0,(P15)/Q15,""),"") | AO15: =IF(AND($D15=1,ISNUMBER(U15),ISNUMBER(Q15)),IF(Q15>0,(U15)/Q15,""),"") | AP15: =IF(AND($D15=1,ISNUMBER(V15),ISNUMBER(Q15)),IF(Q15>0,(V15)/Q15,""),"")
A16: the-moving-group | B16: prod | C16: 2026-08 | D16: 1 | AI16: =IF(AND($D16=1,ISNUMBER(K16),ISNUMBER(Q16)),IF(Q16>0,(K16)/Q16,""),"") | AJ16: =IF(AND($D16=1,ISNUMBER(L16),ISNUMBER(Q16)),IF(Q16>0,(L16)/Q16,""),"") | AK16: =IF(AND($D16=1,ISNUMBER(M16),ISNUMBER(Q16)),IF(Q16>0,(M16)/Q16,""),"") | AL16: =IF(AND($D16=1,ISNUMBER(N16),ISNUMBER(Q16)),IF(Q16>0,(N16)/Q16,""),"") | AM16: =IF(AND($D16=1,ISNUMBER(E16),ISNUMBER(F16),ISNUMBER(Q16)),IF(Q16>0,(E16+F16)/Q16,""),"") | AN16: =IF(AND($D16=1,ISNUMBER(P16),ISNUMBER(Q16)),IF(Q16>0,(P16)/Q16,""),"") | AO16: =IF(AND($D16=1,ISNUMBER(U16),ISNUMBER(Q16)),IF(Q16>0,(U16)/Q16,""),"") | AP16: =IF(AND($D16=1,ISNUMBER(V16),ISNUMBER(Q16)),IF(Q16>0,(V16)/Q16,""),"")
A17: the-moving-group | B17: prod | C17: 2026-09 | D17: 1 | AI17: =IF(AND($D17=1,ISNUMBER(K17),ISNUMBER(Q17)),IF(Q17>0,(K17)/Q17,""),"") | AJ17: =IF(AND($D17=1,ISNUMBER(L17),ISNUMBER(Q17)),IF(Q17>0,(L17)/Q17,""),"") | AK17: =IF(AND($D17=1,ISNUMBER(M17),ISNUMBER(Q17)),IF(Q17>0,(M17)/Q17,""),"") | AL17: =IF(AND($D17=1,ISNUMBER(N17),ISNUMBER(Q17)),IF(Q17>0,(N17)/Q17,""),"") | AM17: =IF(AND($D17=1,ISNUMBER(E17),ISNUMBER(F17),ISNUMBER(Q17)),IF(Q17>0,(E17+F17)/Q17,""),"") | AN17: =IF(AND($D17=1,ISNUMBER(P17),ISNUMBER(Q17)),IF(Q17>0,(P17)/Q17,""),"") | AO17: =IF(AND($D17=1,ISNUMBER(U17),ISNUMBER(Q17)),IF(Q17>0,(U17)/Q17,""),"") | AP17: =IF(AND($D17=1,ISNUMBER(V17),ISNUMBER(Q17)),IF(Q17>0,(V17)/Q17,""),"")
A18: the-moving-group | B18: prod | C18: 2026-10 | D18: 0 | AI18: =IF(AND($D18=1,ISNUMBER(K18),ISNUMBER(Q18)),IF(Q18>0,(K18)/Q18,""),"") | AJ18: =IF(AND($D18=1,ISNUMBER(L18),ISNUMBER(Q18)),IF(Q18>0,(L18)/Q18,""),"") | AK18: =IF(AND($D18=1,ISNUMBER(M18),ISNUMBER(Q18)),IF(Q18>0,(M18)/Q18,""),"") | AL18: =IF(AND($D18=1,ISNUMBER(N18),ISNUMBER(Q18)),IF(Q18>0,(N18)/Q18,""),"") | AM18: =IF(AND($D18=1,ISNUMBER(E18),ISNUMBER(F18),ISNUMBER(Q18)),IF(Q18>0,(E18+F18)/Q18,""),"") | AN18: =IF(AND($D18=1,ISNUMBER(P18),ISNUMBER(Q18)),IF(Q18>0,(P18)/Q18,""),"") | AO18: =IF(AND($D18=1,ISNUMBER(U18),ISNUMBER(Q18)),IF(Q18>0,(U18)/Q18,""),"") | AP18: =IF(AND($D18=1,ISNUMBER(V18),ISNUMBER(Q18)),IF(Q18>0,(V18)/Q18,""),"")
A21: Usage profile: measured where there is data, assumed where there is not
A22: Metric | B22: Unit | C22: n (months) | D22: Mean | E22: Median | F22: P25 | G22: P90 | H22: Assumption | I22: Low used | J22: Base used | K22: High used | L22: Basis
A23: Billed minutes, PSTN outbound | B23: per seat / month | C23: =COUNT($AI$7:$AI$18) | D23: =IF(C23=0,"",AVERAGE($AI$7:$AI$18)) | E23: =IF(C23=0,"",MEDIAN($AI$7:$AI$18)) | F23: =IF(C23=0,"",PERCENTILE($AI$7:$AI$18,0.25)) | G23: =IF(C23=0,"",PERCENTILE($AI$7:$AI$18,0.9)) | H23: =Assumptions!$C$66 | I23: =IF(C23>=3,F23,J23*(1-Assumptions!$C$64)) | J23: =IF(C23=0,H23,D23) | K23: =IF(C23>=3,G23,J23*(1+Assumptions!$C$64)) | L23: =IF(C23=0,"ASSUMPTION",IF(C23<3,"Actual mean, banded","Actual P25 / mean / P90"))
A24: Billed minutes, PSTN inbound | B24: per seat / month | C24: =COUNT($AJ$7:$AJ$18) | D24: =IF(C24=0,"",AVERAGE($AJ$7:$AJ$18)) | E24: =IF(C24=0,"",MEDIAN($AJ$7:$AJ$18)) | F24: =IF(C24=0,"",PERCENTILE($AJ$7:$AJ$18,0.25)) | G24: =IF(C24=0,"",PERCENTILE($AJ$7:$AJ$18,0.9)) | H24: =Assumptions!$C$68 | I24: =IF(C24>=3,F24,J24*(1-Assumptions!$C$64)) | J24: =IF(C24=0,H24,D24) | K24: =IF(C24>=3,G24,J24*(1+Assumptions!$C$64)) | L24: =IF(C24=0,"ASSUMPTION",IF(C24<3,"Actual mean, banded","Actual P25 / mean / P90"))
A25: Billed minutes, browser leg | B25: per seat / month | C25: =COUNT($AK$7:$AK$18) | D25: =IF(C25=0,"",AVERAGE($AK$7:$AK$18)) | E25: =IF(C25=0,"",MEDIAN($AK$7:$AK$18)) | F25: =IF(C25=0,"",PERCENTILE($AK$7:$AK$18,0.25)) | G25: =IF(C25=0,"",PERCENTILE($AK$7:$AK$18,0.9)) | H25: =Assumptions!$C$69 | I25: =IF(C25>=3,F25,J25*(1-Assumptions!$C$64)) | J25: =IF(C25=0,H25,D25) | K25: =IF(C25>=3,G25,J25*(1+Assumptions!$C$64)) | L25: =IF(C25=0,"ASSUMPTION",IF(C25<3,"Actual mean, banded","Actual P25 / mean / P90"))
A26: Recorded minutes | B26: per seat / month | C26: =COUNT($AL$7:$AL$18) | D26: =IF(C26=0,"",AVERAGE($AL$7:$AL$18)) | E26: =IF(C26=0,"",MEDIAN($AL$7:$AL$18)) | F26: =IF(C26=0,"",PERCENTILE($AL$7:$AL$18,0.25)) | G26: =IF(C26=0,"",PERCENTILE($AL$7:$AL$18,0.9)) | H26: =Assumptions!$C$70 | I26: =IF(C26>=3,F26,J26*(1-Assumptions!$C$64)) | J26: =IF(C26=0,H26,D26) | K26: =IF(C26>=3,G26,J26*(1+Assumptions!$C$64)) | L26: =IF(C26=0,"ASSUMPTION",IF(C26<3,"Actual mean, banded","Actual P25 / mean / P90"))
A27: Calls, out plus in | B27: per seat / month | C27: =COUNT($AM$7:$AM$18) | D27: =IF(C27=0,"",AVERAGE($AM$7:$AM$18)) | E27: =IF(C27=0,"",MEDIAN($AM$7:$AM$18)) | F27: =IF(C27=0,"",PERCENTILE($AM$7:$AM$18,0.25)) | G27: =IF(C27=0,"",PERCENTILE($AM$7:$AM$18,0.9)) | H27: =Assumptions!$C$71 | I27: =IF(C27>=3,F27,J27*(1-Assumptions!$C$64)) | J27: =IF(C27=0,H27,D27) | K27: =IF(C27>=3,G27,J27*(1+Assumptions!$C$64)) | L27: =IF(C27=0,"ASSUMPTION",IF(C27<3,"Actual mean, banded","Actual P25 / mean / P90"))
A28: Answering-machine-detection calls | B28: per seat / month | C28: =COUNT($AN$7:$AN$18) | D28: =IF(C28=0,"",AVERAGE($AN$7:$AN$18)) | E28: =IF(C28=0,"",MEDIAN($AN$7:$AN$18)) | F28: =IF(C28=0,"",PERCENTILE($AN$7:$AN$18,0.25)) | G28: =IF(C28=0,"",PERCENTILE($AN$7:$AN$18,0.9)) | H28: =Assumptions!$C$72 | I28: =IF(C28>=3,F28,J28*(1-Assumptions!$C$64)) | J28: =IF(C28=0,H28,D28) | K28: =IF(C28>=3,G28,J28*(1+Assumptions!$C$64)) | L28: =IF(C28=0,"ASSUMPTION",IF(C28<3,"Actual mean, banded","Actual P25 / mean / P90"))
A29: Outbound SMS segments | B29: per seat / month | C29: =COUNT($AO$7:$AO$18) | D29: =IF(C29=0,"",AVERAGE($AO$7:$AO$18)) | E29: =IF(C29=0,"",MEDIAN($AO$7:$AO$18)) | F29: =IF(C29=0,"",PERCENTILE($AO$7:$AO$18,0.25)) | G29: =IF(C29=0,"",PERCENTILE($AO$7:$AO$18,0.9)) | H29: =Assumptions!$C$81 | I29: =IF(C29>=3,F29,J29*(1-Assumptions!$C$64)) | J29: =IF(C29=0,H29,D29) | K29: =IF(C29>=3,G29,J29*(1+Assumptions!$C$64)) | L29: =IF(C29=0,"ASSUMPTION",IF(C29<3,"Actual mean, banded","Actual P25 / mean / P90"))
A30: Inbound SMS segments | B30: per seat / month | C30: =COUNT($AP$7:$AP$18) | D30: =IF(C30=0,"",AVERAGE($AP$7:$AP$18)) | E30: =IF(C30=0,"",MEDIAN($AP$7:$AP$18)) | F30: =IF(C30=0,"",PERCENTILE($AP$7:$AP$18,0.25)) | G30: =IF(C30=0,"",PERCENTILE($AP$7:$AP$18,0.9)) | H30: =Assumptions!$C$82 | I30: =IF(C30>=3,F30,J30*(1-Assumptions!$C$64)) | J30: =IF(C30=0,H30,D30) | K30: =IF(C30>=3,G30,J30*(1+Assumptions!$C$64)) | L30: =IF(C30=0,"ASSUMPTION",IF(C30<3,"Actual mean, banded","Actual P25 / mean / P90"))
A31: AI conversations | B31: per tenant / month | C31: 0 | H31: =Assumptions!$C$90 | I31: =IF(C31>=3,F31,J31*(1-Assumptions!$C$64)) | J31: =IF(C31=0,H31,D31) | K31: =IF(C31>=3,G31,J31*(1+Assumptions!$C$64)) | L31: =IF(C31=0,"ASSUMPTION",IF(C31<3,"Actual mean, banded","Actual P25 / mean / P90"))
A34: Notes carried in the file
A35: NO USAGE IS IN THIS FILE YET. Every metric is null. Nothing here is estimated. See pull-log.md.
A36: Shape: the sendblue block from the brief is removed. SendBlue is not in use: there is no SendBlue code, setting or dependency in any HaulOS repository or in the client site.
A37: 2026-10 is month-to-date (2026-10-01 to 2026-10-04).
A38: The Moving Group production: a second, read-only pass on 2026-10-04 did return monthly aggregates from the client site's Twilio account, Zoho CRM, the Zoho Voice call and text logs and the site database. They are NOT in this file: the session was not permitted to write them into the repository. They are held outside it until that is approved.
A39: Twilio (HaulOS account): UNAVAILABLE. No tool in the session is signed in to it. The two saved Twilio CLI profiles were identified by their TwiML application list only; neither has an application pointing at the HaulOS dialer backend, so neither was queried further. The desktop Twilio connector is bound to another project's account and has no usage endpoints. billed_costs_by_category is empty for the same reason.
A40: Zoho CRM (Kore org and sandbox): UNAVAILABLE. The HaulOS Zoho configuration tool holds settings-scope tokens (fields, layouts, pipeline, roles, profiles, views, workflows) and has no read path for org, users or records.
A41: Zoho Marketing Automation: UNAVAILABLE. Not in use; no tool.
A42: 10DLC brand and campaign status and fees for the HaulOS account: not retrievable (Twilio unavailable).
A43: PRIOR OBSERVATION, not from this pull (2026-09-30 probe of The Moving Group's Zoho Voice): 2 Zoho Voice users, 3 lines (2 that text, 1 calls only). Request-board card 63 (2026-09-03) records the plan as the Solo tier.
A44: PRIOR OBSERVATION, not from this pull (2026-10-01 capacity study of the client website): Zoho CRM API allowance 53,000 credits a day for The Moving Group's org; Zoho Voice documents 20 requests a minute; the client's own Twilio account held 7 numbers.
A45: PRIOR OBSERVATION, not from this pull (2026-10-01 capacity study): the Netlify team that hosts the client website is on the credit-based Pro plan ($20 for 3,000 credits) and was using about 9,000 credits a month (about $60), about 80% of it database compute kept awake by every-minute schedules; five sites share the credit pool.
A46: Dev and ramp-up warning: the first client is still deploying. When this file is filled, treat kore/dev and kore-sandbox as test traffic and 2026-07 to 2026-09 as ramp-up for the-moving-group.

Sheet UnitEconomics
A1: Unit economics
A2: Cost of each tool in use at low, base and high usage. Low and high are P25 and P90 of the actuals, or plus or minus the band on base when there are under three months.
A4: Line | B4: Unit | C4: Low | D4: Base | E4: High | F4: Note
A5: Usage, per dialer seat per month
A6: Billed minutes, PSTN outbound | B6: minutes | C6: =UsageActuals!$I$23 | D6: =UsageActuals!$J$23 | E6: =UsageActuals!$K$23
A7: Billed minutes, PSTN inbound | B7: minutes | C7: =UsageActuals!$I$24 | D7: =UsageActuals!$J$24 | E7: =UsageActuals!$K$24
A8: Billed minutes, browser leg | B8: minutes | C8: =UsageActuals!$I$25 | D8: =UsageActuals!$J$25 | E8: =UsageActuals!$K$25
A9: Recorded minutes | B9: minutes | C9: =UsageActuals!$I$26 | D9: =UsageActuals!$J$26 | E9: =UsageActuals!$K$26
A10: Calls | B10: calls | C10: =UsageActuals!$I$27 | D10: =UsageActuals!$J$27 | E10: =UsageActuals!$K$27
A11: Answering-machine-detection calls | B11: calls | C11: =UsageActuals!$I$28 | D11: =UsageActuals!$J$28 | E11: =UsageActuals!$K$28
A12: Phone minutes a customer would count | B12: minutes | C12: =C6+C7 | D12: =D6+D7 | E12: =E6+E7 | F12: Outbound plus inbound. This is what an included-minutes allowance is measured in.
A14: Usage, per tenant per month
A15: Outbound SMS segments | B15: segments | C15: =UsageActuals!$I$29*Assumptions!$C$41 | D15: =UsageActuals!$J$29*Assumptions!$C$41 | E15: =UsageActuals!$K$29*Assumptions!$C$41 | F15: Per seat, times the seats.
A16: Inbound SMS segments | B16: segments | C16: =UsageActuals!$I$30*Assumptions!$C$41 | D16: =UsageActuals!$J$30*Assumptions!$C$41 | E16: =UsageActuals!$K$30*Assumptions!$C$41
A17: AI conversations | B17: conversations | C17: =UsageActuals!$I$31 | D17: =UsageActuals!$J$31 | E17: =UsageActuals!$K$31
A19: Twilio Programmable Voice: cost per dialer seat per month
A20: PSTN outbound | B20: $ | C20: =C6*Assumptions!$C$93 | D20: =D6*Assumptions!$C$93 | E20: =E6*Assumptions!$C$93
A21: PSTN inbound | B21: $ | C21: =C7*Assumptions!$C$94 | D21: =D7*Assumptions!$C$94 | E21: =E7*Assumptions!$C$94
A22: Browser leg | B22: $ | C22: =C8*Assumptions!$C$95 | D22: =D8*Assumptions!$C$95 | E22: =E8*Assumptions!$C$95
A23: Recording | B23: $ | C23: =C9*Assumptions!$C$96 | D23: =D9*Assumptions!$C$96 | E23: =E9*Assumptions!$C$96
A24: Recording storage, steady state | B24: $ | C24: =C9*Assumptions!$C$97*Assumptions!$C$62 | D24: =D9*Assumptions!$C$97*Assumptions!$C$62 | E24: =E9*Assumptions!$C$97*Assumptions!$C$62 | F24: Each month of recordings is stored for the retention period. With no retention rule this keeps growing.
A25: Answering machine detection | B25: $ | C25: =C11*Assumptions!$C$99 | D25: =D11*Assumptions!$C$99 | E25: =E11*Assumptions!$C$99
A26: Voice usage per seat | B26: $ | C26: =C20+C21+C22+C23+C24+C25 | D26: =D20+D21+D22+D23+D24+D25 | E26: =E20+E21+E22+E23+E24+E25
A27: Cost per phone minute | B27: $ / minute | C27: =IF(C12>0,C26/C12,0) | D27: =IF(D12>0,D26/D12,0) | E27: =IF(E12>0,E26/E12,0)
A28: Phone numbers per tenant | B28: $ | C28: =(Assumptions!$C$41*Assumptions!$C$42+Assumptions!$C$43)*Assumptions!$C$98 | D28: =(Assumptions!$C$41*Assumptions!$C$42+Assumptions!$C$43)*Assumptions!$C$98 | E28: =(Assumptions!$C$41*Assumptions!$C$42+Assumptions!$C$43)*Assumptions!$C$98
A29: Voice per tenant | B29: $ | C29: =Assumptions!$C$41*C26+C28 | D29: =Assumptions!$C$41*D26+D28 | E29: =Assumptions!$C$41*E26+E28
A30: Voice per seat, numbers included | B30: $ | C30: =C29/Assumptions!$C$41 | D30: =D29/Assumptions!$C$41 | E30: =E29/Assumptions!$C$41
A31: Overage price per phone minute | B31: $ / minute | C31: =ROUNDUP(Assumptions!$C$24*$D$27,3) | D31: =ROUNDUP(Assumptions!$C$24*$D$27,3) | E31: =ROUNDUP(Assumptions!$C$24*$D$27,3) | F31: One price for every tenant, set from the base cost.
A33: Twilio Messaging and 10DLC: cost per tenant per month
A34: Outbound segments, carrier fee included | B34: $ | C34: =C15*(Assumptions!$C$102+Assumptions!$C$104) | D34: =D15*(Assumptions!$C$102+Assumptions!$C$104) | E34: =E15*(Assumptions!$C$102+Assumptions!$C$104)
A35: Inbound segments, carrier fee included | B35: $ | C35: =C16*(Assumptions!$C$103+Assumptions!$C$105) | D35: =D16*(Assumptions!$C$103+Assumptions!$C$105) | E35: =E16*(Assumptions!$C$103+Assumptions!$C$105)
A36: Campaign fee and texting number | B36: $ | C36: =Assumptions!$C$108+Assumptions!$C$109*Assumptions!$C$98 | D36: =Assumptions!$C$108+Assumptions!$C$109*Assumptions!$C$98 | E36: =Assumptions!$C$108+Assumptions!$C$109*Assumptions!$C$98
A37: Texting per tenant | B37: $ | C37: =C34+C35+C36 | D37: =D34+D35+D36 | E37: =E34+E35+E36
A38: Cost per outbound segment | B38: $ / segment | C38: =Assumptions!$C$102+Assumptions!$C$104 | D38: =Assumptions!$C$102+Assumptions!$C$104 | E38: =Assumptions!$C$102+Assumptions!$C$104
A39: Overage price per segment | B39: $ / segment | C39: =ROUNDUP(Assumptions!$C$24*C38,3) | D39: =ROUNDUP(Assumptions!$C$24*D38,3) | E39: =ROUNDUP(Assumptions!$C$24*E38,3)
A40: One-time: brand and campaign registration | B40: $ | C40: =Assumptions!$C$106+Assumptions!$C$107 | D40: =Assumptions!$C$106+Assumptions!$C$107 | E40: =Assumptions!$C$106+Assumptions!$C$107
A42: Zoho CRM: the tenant pays Zoho
A43: List price per seat | B43: $ | C43: =Assumptions!$C$116 | D43: =Assumptions!$C$116 | E43: =Assumptions!$C$116
A44: List price per tenant | B44: $ | C44: =Assumptions!$C$116*Assumptions!$C$41 | D44: =Assumptions!$C$116*Assumptions!$C$41 | E44: =Assumptions!$C$116*Assumptions!$C$41
A45: Kore margin per tenant | B45: $ | C45: =Assumptions!$C$37*Assumptions!$C$116*Assumptions!$C$41 | D45: =Assumptions!$C$37*Assumptions!$C$116*Assumptions!$C$41 | E45: =Assumptions!$C$37*Assumptions!$C$116*Assumptions!$C$41
A46: API credits a day used by call logging | B46: credits | C46: =Assumptions!$C$41*C10/Assumptions!$C$48*Assumptions!$C$122 | D46: =Assumptions!$C$41*D10/Assumptions!$C$48*Assumptions!$C$122 | E46: =Assumptions!$C$41*E10/Assumptions!$C$48*Assumptions!$C$122
A47: API credits a day allowed | B47: credits | C47: =Assumptions!$C$121 | D47: =Assumptions!$C$121 | E47: =Assumptions!$C$121
A48: Share of the allowance used | B48: % | C48: =C46/C47 | D48: =D46/D47 | E48: =E46/E47 | F48: A ceiling, not a dollar cost.
A50: Zoho Voice: the tenant pays Zoho
A51: List price per seat | B51: $ | C51: =Assumptions!$C$123 | D51: =Assumptions!$C$123 | E51: =Assumptions!$C$123
A52: List price per tenant | B52: $ | C52: =Assumptions!$C$123*Assumptions!$C$41 | D52: =Assumptions!$C$123*Assumptions!$C$41 | E52: =Assumptions!$C$123*Assumptions!$C$41
A53: With the auto dialer, per tenant (planned) | B53: $ | C53: =(Assumptions!$C$123+Assumptions!$C$125)*Assumptions!$C$41 | D53: =(Assumptions!$C$123+Assumptions!$C$125)*Assumptions!$C$41 | E53: =(Assumptions!$C$123+Assumptions!$C$125)*Assumptions!$C$41 | F53: ASSUMPTION: no auto dialer price is published.
A55: Zoho Marketing Automation (planned): cost per tenant if texting ran through it
A56: Plan, number, campaign and texts | B56: $ | C56: =Assumptions!$C$126+Assumptions!$C$128+C15*Assumptions!$C$127 | D56: =Assumptions!$C$126+Assumptions!$C$128+D15*Assumptions!$C$127 | E56: =Assumptions!$C$126+Assumptions!$C$128+E15*Assumptions!$C$127 | F56: Counts one text per segment.
A58: AI SMS: cost per tenant per month
A59: Texts the AI sends and receives, on Twilio | B59: $ | C59: =C17*Assumptions!$C$85*(Assumptions!$C$88*(Assumptions!$C$102+Assumptions!$C$104)+Assumptions!$C$89*(Assumptions!$C$103+Assumptions!$C$105)) | D59: =D17*Assumptions!$C$85*(Assumptions!$C$88*(Assumptions!$C$102+Assumptions!$C$104)+Assumptions!$C$89*(Assumptions!$C$103+Assumptions!$C$105)) | E59: =E17*Assumptions!$C$85*(Assumptions!$C$88*(Assumptions!$C$102+Assumptions!$C$104)+Assumptions!$C$89*(Assumptions!$C$103+Assumptions!$C$105)) | F59: No per-line fee: the AI texts ride the same Twilio messaging as the SMS add-on.
A60: AI model tokens | B60: $ | C60: =C17*Assumptions!$C$85*(Assumptions!$C$86*Assumptions!$C$131+Assumptions!$C$87*Assumptions!$C$132)/1000000 | D60: =D17*Assumptions!$C$85*(Assumptions!$C$86*Assumptions!$C$131+Assumptions!$C$87*Assumptions!$C$132)/1000000 | E60: =E17*Assumptions!$C$85*(Assumptions!$C$86*Assumptions!$C$131+Assumptions!$C$87*Assumptions!$C$132)/1000000
A61: AI SMS per tenant | B61: $ | C61: =C59+C60 | D61: =D59+D60 | E61: =E59+E60
A63: Platform: hosting, client site, lead lines and GitHub, per tenant at today's tenant count
A64: Backend hosting | B64: $ | C64: =IF(Assumptions!$C$155=1,(Assumptions!$C$135*Assumptions!$C$140+Hosting!$C$5*Assumptions!$C$140+MAX(0,ROUNDUP(Assumptions!$C$17/Assumptions!$C$141,0)-1)*Hosting!$C$5),IF(Assumptions!$C$155=2,(MAX(Assumptions!$C$145,ROUNDUP(Assumptions!$C$17/Assumptions!$C$146,0))*Assumptions!$C$144+Assumptions!$C$17*Hosting!$C$6),IF(Assumptions!$C$17>=Assumptions!$C$156,(MAX(Assumptions!$C$145,ROUNDUP(Assumptions!$C$17/Assumptions!$C$146,0))*Assumptions!$C$144+Assumptions!$C$17*Hosting!$C$6),(Assumptions!$C$135*Assumptions!$C$140+Hosting!$C$5*Assumptions!$C$140+MAX(0,ROUNDUP(Assumptions!$C$17/Assumptions!$C$141,0)-1)*Hosting!$C$5))))/Assumptions!$C$17 | D64: =IF(Assumptions!$C$155=1,(Assumptions!$C$135*Assumptions!$C$140+Hosting!$C$5*Assumptions!$C$140+MAX(0,ROUNDUP(Assumptions!$C$17/Assumptions!$C$141,0)-1)*Hosting!$C$5),IF(Assumptions!$C$155=2,(MAX(Assumptions!$C$145,ROUNDUP(Assumptions!$C$17/Assumptions!$C$146,0))*Assumptions!$C$144+Assumptions!$C$17*Hosting!$C$6),IF(Assumptions!$C$17>=Assumptions!$C$156,(MAX(Assumptions!$C$145,ROUNDUP(Assumptions!$C$17/Assumptions!$C$146,0))*Assumptions!$C$144+Assumptions!$C$17*Hosting!$C$6),(Assumptions!$C$135*Assumptions!$C$140+Hosting!$C$5*Assumptions!$C$140+MAX(0,ROUNDUP(Assumptions!$C$17/Assumptions!$C$141,0)-1)*Hosting!$C$5))))/Assumptions!$C$17 | E64: =IF(Assumptions!$C$155=1,(Assumptions!$C$135*Assumptions!$C$140+Hosting!$C$5*Assumptions!$C$140+MAX(0,ROUNDUP(Assumptions!$C$17/Assumptions!$C$141,0)-1)*Hosting!$C$5),IF(Assumptions!$C$155=2,(MAX(Assumptions!$C$145,ROUNDUP(Assumptions!$C$17/Assumptions!$C$146,0))*Assumptions!$C$144+Assumptions!$C$17*Hosting!$C$6),IF(Assumptions!$C$17>=Assumptions!$C$156,(MAX(Assumptions!$C$145,ROUNDUP(Assumptions!$C$17/Assumptions!$C$146,0))*Assumptions!$C$144+Assumptions!$C$17*Hosting!$C$6),(Assumptions!$C$135*Assumptions!$C$140+Hosting!$C$5*Assumptions!$C$140+MAX(0,ROUNDUP(Assumptions!$C$17/Assumptions!$C$141,0)-1)*Hosting!$C$5))))/Assumptions!$C$17 | F64: Falls quickly as tenants are added: see the Hosting sheet.
A65: Client site (Netlify) | B65: $ | C65: =Assumptions!$C$159*(Assumptions!$C$160+MAX(0,Assumptions!$C$17*Assumptions!$C$163-Assumptions!$C$161)*Assumptions!$C$162)/Assumptions!$C$17 | D65: =Assumptions!$C$159*(Assumptions!$C$160+MAX(0,Assumptions!$C$17*Assumptions!$C$163-Assumptions!$C$161)*Assumptions!$C$162)/Assumptions!$C$17 | E65: =Assumptions!$C$159*(Assumptions!$C$160+MAX(0,Assumptions!$C$17*Assumptions!$C$163-Assumptions!$C$161)*Assumptions!$C$162)/Assumptions!$C$17 | F65: Does not fall: each tenant site uses its own credits.
A66: GitHub | B66: $ | C66: =Assumptions!$C$164*Assumptions!$C$165/Assumptions!$C$17 | D66: =Assumptions!$C$164*Assumptions!$C$165/Assumptions!$C$17 | E66: =Assumptions!$C$164*Assumptions!$C$165/Assumptions!$C$17
A67: Lead lines on Twilio | B67: $ | C67: =Assumptions!$C$168+Assumptions!$C$169 | D67: =Assumptions!$C$168+Assumptions!$C$169 | E67: =Assumptions!$C$168+Assumptions!$C$169 | F67: From the first client's bill. Scales with a tenant's lead calls, not with tenant count.
A68: Platform per tenant | B68: $ | C68: =C64+C65+C66+C67 | D68: =D64+D65+D66+D67 | E68: =E64+E65+E66+E67
A70: Cost to serve by product, per tenant that takes it, per month
A71: Platform | B71: $ | C71: =C68 | D71: =D68 | E71: =E68
A72: Dialer | B72: $ | C72: =C29 | D72: =D29 | E72: =E29
A73: SMS | B73: $ | C73: =C37 | D73: =D37 | E73: =E37
A74: Compliance | B74: $ | C74: =Assumptions!$C$172 | D74: =Assumptions!$C$172 | E74: =Assumptions!$C$172
A75: AI SMS | B75: $ | C75: =C61 | D75: =D61 | E75: =E61

Sheet VoiceSKUs
A1: Voice: Zoho Voice (A) against the custom Twilio dialer (B)
A2: A costs Kore nothing and earns the reseller margin. B is priced by Kore and carries the Twilio bill.
A4: Line | B4: Unit | C4: Low | D4: Base | E4: High | F4: Note
A5: A. Zoho Voice, per seat per month
A6: What the tenant pays Zoho | B6: $ | C6: =Assumptions!$C$123 | D6: =Assumptions!$C$123 | E6: =Assumptions!$C$123 | F6: Enterprise Telephony Basic, with unlimited US and Canada calling.
A7: What Kore earns | B7: $ | C7: =Assumptions!$C$37*Assumptions!$C$123 | D7: =Assumptions!$C$37*Assumptions!$C$123 | E7: =Assumptions!$C$37*Assumptions!$C$123 | F7: Reseller margin. 0% today.
A8: What Kore pays | B8: $ | C8: =0 | D8: =0 | E8: =0
A9: Kore gross profit per seat | B9: $ | C9: =C7-C8 | D9: =D7-D8 | E9: =E7-E8
A10: Tenant price with the auto dialer (planned) | B10: $ | C10: =Assumptions!$C$123+Assumptions!$C$125 | D10: =Assumptions!$C$123+Assumptions!$C$125 | E10: =Assumptions!$C$123+Assumptions!$C$125 | F10: ASSUMPTION: no auto dialer price is published.
A12: B. Custom Twilio dialer, per seat per month
A13: Price | B13: $ | C13: =Assumptions!$C$22 | D13: =Assumptions!$C$22 | E13: =Assumptions!$C$22
A14: Minutes included | B14: minutes | C14: =Assumptions!$C$23 | D14: =Assumptions!$C$23 | E14: =Assumptions!$C$23
A15: Phone minutes used | B15: minutes | C15: =UnitEconomics!$C$12 | D15: =UnitEconomics!$D$12 | E15: =UnitEconomics!$E$12
A16: Cost, numbers included | B16: $ | C16: =UnitEconomics!$C$30 | D16: =UnitEconomics!$D$30 | E16: =UnitEconomics!$E$30
A17: Gross profit, no overage charged | B17: $ | C17: =C13-C16 | D17: =D13-D16 | E17: =E13-E16
A18: Gross margin, no overage charged | B18: % | C18: =C17/C13 | D18: =D17/D13 | E18: =E17/E13
A19: Minutes over the allowance | B19: minutes | C19: =MAX(0,C15-C14) | D19: =MAX(0,D15-D14) | E19: =MAX(0,E15-E14)
A20: Overage price | B20: $ / minute | C20: =UnitEconomics!$C$31 | D20: =UnitEconomics!$D$31 | E20: =UnitEconomics!$E$31
A21: Overage revenue | B21: $ | C21: =Assumptions!$C$25*C19*C20 | D21: =Assumptions!$C$25*D19*D20 | E21: =Assumptions!$C$25*E19*E20
A22: Revenue with overage | B22: $ | C22: =C13+C21 | D22: =D13+D21 | E22: =E13+E21
A23: Gross profit with overage | B23: $ | C23: =C22-C16 | D23: =D22-D16 | E23: =E22-E16
A24: Gross margin with overage | B24: % | C24: =C23/C22 | D24: =D23/D22 | E24: =E23/E22
A26: B against A
A27: What the tenant pays extra for B, per seat | B27: $ | C27: =C13-C6 | D27: =D13-D6 | E27: =E13-E6 | F27: Before overage. A has no minute cap.
A28: The same, against A with the auto dialer | B28: $ | C28: =C13-C10 | D28: =D13-D10 | E28: =E13-E10
A29: What Kore earns extra from B, per seat | B29: $ | C29: =C23-C9 | D29: =D23-D9 | E29: =E23-E9
A31: Breakeven
A32: Minutes a seat can use before the flat price loses money | B32: minutes | C32: =(Assumptions!$C$22-((Assumptions!$C$41*Assumptions!$C$42+Assumptions!$C$43)*Assumptions!$C$98/Assumptions!$C$41))/UnitEconomics!$C$27 | D32: =(Assumptions!$C$22-((Assumptions!$C$41*Assumptions!$C$42+Assumptions!$C$43)*Assumptions!$C$98/Assumptions!$C$41))/UnitEconomics!$D$27 | E32: =(Assumptions!$C$22-((Assumptions!$C$41*Assumptions!$C$42+Assumptions!$C$43)*Assumptions!$C$98/Assumptions!$C$41))/UnitEconomics!$E$27 | F32: With no overage charged.
A33: Minutes a seat can use and still hit the margin target | B33: minutes | C33: =(Assumptions!$C$22*(1-Assumptions!$C$38)-((Assumptions!$C$41*Assumptions!$C$42+Assumptions!$C$43)*Assumptions!$C$98/Assumptions!$C$41))/UnitEconomics!$C$27 | D33: =(Assumptions!$C$22*(1-Assumptions!$C$38)-((Assumptions!$C$41*Assumptions!$C$42+Assumptions!$C$43)*Assumptions!$C$98/Assumptions!$C$41))/UnitEconomics!$D$27 | E33: =(Assumptions!$C$22*(1-Assumptions!$C$38)-((Assumptions!$C$41*Assumptions!$C$42+Assumptions!$C$43)*Assumptions!$C$98/Assumptions!$C$41))/UnitEconomics!$E$27
A34: Minutes at which B earns Kore no more than reselling A | B34: minutes | C34: =(Assumptions!$C$22-Assumptions!$C$37*Assumptions!$C$123-((Assumptions!$C$41*Assumptions!$C$42+Assumptions!$C$43)*Assumptions!$C$98/Assumptions!$C$41))/UnitEconomics!$C$27 | D34: =(Assumptions!$C$22-Assumptions!$C$37*Assumptions!$C$123-((Assumptions!$C$41*Assumptions!$C$42+Assumptions!$C$43)*Assumptions!$C$98/Assumptions!$C$41))/UnitEconomics!$D$27 | E34: =(Assumptions!$C$22-Assumptions!$C$37*Assumptions!$C$123-((Assumptions!$C$41*Assumptions!$C$42+Assumptions!$C$43)*Assumptions!$C$98/Assumptions!$C$41))/UnitEconomics!$E$27
A35: Fixed monthly cost of running the dialer | B35: $ | C35: =UnitEconomics!$C$64*Assumptions!$C$17 | D35: =UnitEconomics!$D$64*Assumptions!$C$17 | E35: =UnitEconomics!$E$64*Assumptions!$C$17 | F35: Backend hosting today.
A36: Seats needed to cover that fixed cost | B36: seats | C36: =IF(C29>0,C35/C29,"never") | D36: =IF(D29>0,D35/D29,"never") | E36: =IF(E29>0,E35/E29,"never")
A38: Margin by minutes used (base cost per minute)
A39: Phone minutes per seat | B39: Cost per seat | C39: Margin, flat price | D39: Overage revenue | E39: Margin with overage
A40: 500 | B40: =A40*UnitEconomics!$D$27+((Assumptions!$C$41*Assumptions!$C$42+Assumptions!$C$43)*Assumptions!$C$98/Assumptions!$C$41) | C40: =(Assumptions!$C$22-B40)/Assumptions!$C$22 | D40: =Assumptions!$C$25*MAX(0,A40-Assumptions!$C$23)*UnitEconomics!$D$31 | E40: =(Assumptions!$C$22+D40-B40)/(Assumptions!$C$22+D40)
A41: 800 | B41: =A41*UnitEconomics!$D$27+((Assumptions!$C$41*Assumptions!$C$42+Assumptions!$C$43)*Assumptions!$C$98/Assumptions!$C$41) | C41: =(Assumptions!$C$22-B41)/Assumptions!$C$22 | D41: =Assumptions!$C$25*MAX(0,A41-Assumptions!$C$23)*UnitEconomics!$D$31 | E41: =(Assumptions!$C$22+D41-B41)/(Assumptions!$C$22+D41)
A42: 1000 | B42: =A42*UnitEconomics!$D$27+((Assumptions!$C$41*Assumptions!$C$42+Assumptions!$C$43)*Assumptions!$C$98/Assumptions!$C$41) | C42: =(Assumptions!$C$22-B42)/Assumptions!$C$22 | D42: =Assumptions!$C$25*MAX(0,A42-Assumptions!$C$23)*UnitEconomics!$D$31 | E42: =(Assumptions!$C$22+D42-B42)/(Assumptions!$C$22+D42)
A43: 1200 | B43: =A43*UnitEconomics!$D$27+((Assumptions!$C$41*Assumptions!$C$42+Assumptions!$C$43)*Assumptions!$C$98/Assumptions!$C$41) | C43: =(Assumptions!$C$22-B43)/Assumptions!$C$22 | D43: =Assumptions!$C$25*MAX(0,A43-Assumptions!$C$23)*UnitEconomics!$D$31 | E43: =(Assumptions!$C$22+D43-B43)/(Assumptions!$C$22+D43)
A44: 1500 | B44: =A44*UnitEconomics!$D$27+((Assumptions!$C$41*Assumptions!$C$42+Assumptions!$C$43)*Assumptions!$C$98/Assumptions!$C$41) | C44: =(Assumptions!$C$22-B44)/Assumptions!$C$22 | D44: =Assumptions!$C$25*MAX(0,A44-Assumptions!$C$23)*UnitEconomics!$D$31 | E44: =(Assumptions!$C$22+D44-B44)/(Assumptions!$C$22+D44)
A45: 2000 | B45: =A45*UnitEconomics!$D$27+((Assumptions!$C$41*Assumptions!$C$42+Assumptions!$C$43)*Assumptions!$C$98/Assumptions!$C$41) | C45: =(Assumptions!$C$22-B45)/Assumptions!$C$22 | D45: =Assumptions!$C$25*MAX(0,A45-Assumptions!$C$23)*UnitEconomics!$D$31 | E45: =(Assumptions!$C$22+D45-B45)/(Assumptions!$C$22+D45)
A46: 2500 | B46: =A46*UnitEconomics!$D$27+((Assumptions!$C$41*Assumptions!$C$42+Assumptions!$C$43)*Assumptions!$C$98/Assumptions!$C$41) | C46: =(Assumptions!$C$22-B46)/Assumptions!$C$22 | D46: =Assumptions!$C$25*MAX(0,A46-Assumptions!$C$23)*UnitEconomics!$D$31 | E46: =(Assumptions!$C$22+D46-B46)/(Assumptions!$C$22+D46)
A47: 3000 | B47: =A47*UnitEconomics!$D$27+((Assumptions!$C$41*Assumptions!$C$42+Assumptions!$C$43)*Assumptions!$C$98/Assumptions!$C$41) | C47: =(Assumptions!$C$22-B47)/Assumptions!$C$22 | D47: =Assumptions!$C$25*MAX(0,A47-Assumptions!$C$23)*UnitEconomics!$D$31 | E47: =(Assumptions!$C$22+D47-B47)/(Assumptions!$C$22+D47)
A48: 4000 | B48: =A48*UnitEconomics!$D$27+((Assumptions!$C$41*Assumptions!$C$42+Assumptions!$C$43)*Assumptions!$C$98/Assumptions!$C$41) | C48: =(Assumptions!$C$22-B48)/Assumptions!$C$22 | D48: =Assumptions!$C$25*MAX(0,A48-Assumptions!$C$23)*UnitEconomics!$D$31 | E48: =(Assumptions!$C$22+D48-B48)/(Assumptions!$C$22+D48)

Sheet Tiers
A1: Tiers: platform fee and add-ons
A2: Revenue and cost per tenant, blended by attach rate. Costs are the base case from UnitEconomics. Gross margin here is tool cost only: no support, sales or payment fees.
A4: Item | B4: Price | C4: Unit | D4: Units per tenant | E4: Attach rate | F4: Revenue per tenant that takes it | G4: Blended revenue per tenant | H4: Cost per tenant that takes it | I4: Blended cost per tenant | J4: Gross profit per tenant that takes it | K4: Gross margin
A5: Platform | B5: =Assumptions!$C$21 | C5: $ / tenant | D5: =1 | E5: =1 | F5: =B5*D5 | G5: =F5*E5 | H5: =UnitEconomics!$D$71 | I5: =H5*E5 | J5: =F5-H5 | K5: =IF(F5>0,J5/F5,0)
A6: Dialer | B6: =Assumptions!$C$22 | C6: $ / seat | D6: =Assumptions!$C$41 | E6: =Assumptions!$C$33 | F6: =B6*D6 | G6: =F6*E6 | H6: =UnitEconomics!$D$72 | I6: =H6*E6 | J6: =F6-H6 | K6: =IF(F6>0,J6/F6,0)
A7: Dialer overage | B7: =UnitEconomics!$D$31 | C7: $ / minute | D7: =Assumptions!$C$41*MAX(0,UnitEconomics!$D$12-Assumptions!$C$23) | E7: =Assumptions!$C$33*Assumptions!$C$25 | F7: =B7*D7 | G7: =F7*E7 | H7: =0 | I7: =H7*E7 | J7: =F7-H7 | K7: =IF(F7>0,J7/F7,0)
A8: SMS | B8: =Assumptions!$C$26 | C8: $ / tenant | D8: =1 | E8: =Assumptions!$C$34 | F8: =B8*D8 | G8: =F8*E8 | H8: =UnitEconomics!$D$73 | I8: =H8*E8 | J8: =F8-H8 | K8: =IF(F8>0,J8/F8,0)
A9: SMS overage | B9: =UnitEconomics!$D$39 | C9: $ / segment | D9: =MAX(0,UnitEconomics!$D$15-Assumptions!$C$27) | E9: =Assumptions!$C$34*Assumptions!$C$25 | F9: =B9*D9 | G9: =F9*E9 | H9: =0 | I9: =H9*E9 | J9: =F9-H9 | K9: =IF(F9>0,J9/F9,0)
A10: Compliance | B10: =Assumptions!$C$29 | C10: $ / tenant | D10: =1 | E10: =Assumptions!$C$35 | F10: =B10*D10 | G10: =F10*E10 | H10: =UnitEconomics!$D$74 | I10: =H10*E10 | J10: =F10-H10 | K10: =IF(F10>0,J10/F10,0)
A11: AI SMS | B11: =Assumptions!$C$30 | C11: $ / tenant | D11: =1 | E11: =Assumptions!$C$36 | F11: =B11*D11 | G11: =F11*E11 | H11: =UnitEconomics!$D$75 | I11: =H11*E11 | J11: =F11-H11 | K11: =IF(F11>0,J11/F11,0)
A12: Zoho resale margin | B12: =Assumptions!$C$37*(Assumptions!$C$116*Assumptions!$C$41+Assumptions!$C$123*Assumptions!$C$41*(1-Assumptions!$C$33)) | C12: $ / tenant | D12: =1 | E12: =1 | F12: =B12*D12 | G12: =F12*E12 | H12: =0 | I12: =H12*E12 | J12: =F12-H12 | K12: =IF(F12>0,J12/F12,0)
A14: Per tenant per month, blended
A15: Revenue per tenant (ARPA) | B15: =SUM(G5:G12)
A16: Revenue per tenant per year | B16: =$B$15*12
A17: Revenue per tenant with no overage | B17: =$B$15-G7-G9
A18: Cost per tenant | B18: =SUM(I5:I12)
A19: Gross profit per tenant | B19: =$B$15-$B$18
A20: Gross margin | B20: =IF($B$15>0,$B$19/$B$15,0)
A21: Gross margin with no overage | B21: =IF($B$17>0,($B$17-$B$18)/$B$17,0)
A23: Used by the forecast
A24: Add-on revenue per tenant, blended | B24: =G6+G8+G10+G11
A25: Overage and resale revenue per tenant, blended | B25: =G7+G9+G12
A26: Cost per tenant, blended, without hosting and client site | B26: =$B$18-I5
A27: One-time fees per new tenant | B27: =Assumptions!$C$31+Assumptions!$C$34*Assumptions!$C$28
A28: One-time cost per new tenant | B28: =Assumptions!$C$34*UnitEconomics!$D$40
A30: Margin by add-on, overage folded in (per tenant that takes it)
A31: Add-on | B31: Revenue | C31: Cost | D31: Gross profit | E31: Gross margin | F31: Gross margin with no overage
A32: Platform | B32: =F5 | C32: =H5 | D32: =B32-C32 | E32: =IF(B32>0,D32/B32,0) | F32: =IF(F5>0,(F5-C32)/(F5),0)
A33: Dialer | B33: =F6+Assumptions!$C$25*F7 | C33: =H6 | D33: =B33-C33 | E33: =IF(B33>0,D33/B33,0) | F33: =IF(F6>0,(F6-C33)/(F6),0)
A34: SMS | B34: =F8+Assumptions!$C$25*F9 | C34: =H8 | D34: =B34-C34 | E34: =IF(B34>0,D34/B34,0) | F34: =IF(F8>0,(F8-C34)/(F8),0)
A35: Compliance | B35: =F10 | C35: =H10 | D35: =B35-C35 | E35: =IF(B35>0,D35/B35,0) | F35: =IF(F10>0,(F10-C35)/(F10),0)
A36: AI SMS | B36: =F11 | C36: =H11 | D36: =B36-C36 | E36: =IF(B36>0,D36/B36,0) | F36: =IF(F11>0,(F11-C36)/(F11),0)
A38: Bundles (1 = in the bundle)
A39: Item | B39: Core | C39: Growth | D39: Complete
A40: Platform | B40: 1 | C40: 1 | D40: 1
A41: Dialer, all seats | B41: 0 | C41: 1 | D41: 1
A42: SMS | B42: 0 | C42: 1 | D42: 1
A43: Compliance | B43: 0 | C43: 0 | D43: 1
A44: AI SMS | B44: 0 | C44: 0 | D44: 1
A45: Price per month | B45: =(B40*$F$5+B41*$F$6+B42*$F$8+B43*$F$10+B44*$F$11)*(1-Assumptions!$C$32) | C45: =(C40*$F$5+C41*$F$6+C42*$F$8+C43*$F$10+C44*$F$11)*(1-Assumptions!$C$32) | D45: =(D40*$F$5+D41*$F$6+D42*$F$8+D43*$F$10+D44*$F$11)*(1-Assumptions!$C$32)
A46: Overage per month at base usage | B46: =Assumptions!$C$25*(B41*$F$7+B42*$F$9) | C46: =Assumptions!$C$25*(C41*$F$7+C42*$F$9) | D46: =Assumptions!$C$25*(D41*$F$7+D42*$F$9)
A47: Cost per month | B47: =B40*$H$5+B41*$H$6+B42*$H$8+B43*$H$10+B44*$H$11 | C47: =C40*$H$5+C41*$H$6+C42*$H$8+C43*$H$10+C44*$H$11 | D47: =D40*$H$5+D41*$H$6+D42*$H$8+D43*$H$10+D44*$H$11
A48: Gross margin, price only | B48: =IF(B45>0,(B45-B47)/B45,0) | C48: =IF(C45>0,(C45-C47)/C45,0) | D48: =IF(D45>0,(D45-D47)/D45,0)
A49: Gross margin with overage | B49: =IF(B45+B46>0,(B45+B46-B47)/(B45+B46),0) | C49: =IF(C45+C46>0,(C45+C46-C47)/(C45+C46),0) | D49: =IF(D45+D46>0,(D45+D46-D47)/(D45+D46),0)

Sheet Hosting
A1: Hosting: Forge and AWS today, Azure at scale
A2: The switch is host_mode on the Assumptions sheet: 1 Forge and AWS, 2 Azure, 3 Azure from a tenant count.
A5: One server, all-in | B5: $ / month | C5: =Assumptions!$C$136+Assumptions!$C$137*Assumptions!$C$138+Assumptions!$C$139 | D5: Instance, disk and public address.
A6: Azure cost that grows with each tenant | B6: $ / tenant / month | C6: =Assumptions!$C$148/10000*Assumptions!$C$147+Assumptions!$C$150*Assumptions!$C$149+Assumptions!$C$152*Assumptions!$C$151+Assumptions!$C$154/10000*Assumptions!$C$153 | D6: Key Vault operations, Blob and Table storage, Table transactions.
A7: Switch (host_mode) | C7: =Assumptions!$C$155 | D7: =CHOOSE(C7,"Forge and AWS","Azure","Azure from "&Assumptions!$C$156&" tenants")
A9: Tenants | B9: Servers | C9: Forge and AWS, $ / month | D9: Per tenant | E9: Instances | F9: Azure, $ / month | G9: Per tenant | H9: Selected, $ / month | I9: Selected per tenant | J9: Client sites, $ / month | K9: Per tenant | L9: Hosting and site per tenant
A10: 1 | B10: =ROUNDUP($A10/Assumptions!$C$141,0) | C10: =(Assumptions!$C$135*Assumptions!$C$140+Hosting!$C$5*Assumptions!$C$140+MAX(0,ROUNDUP($A10/Assumptions!$C$141,0)-1)*Hosting!$C$5) | D10: =C10/$A10 | E10: =MAX(Assumptions!$C$145,ROUNDUP($A10/Assumptions!$C$146,0)) | F10: =(MAX(Assumptions!$C$145,ROUNDUP($A10/Assumptions!$C$146,0))*Assumptions!$C$144+$A10*Hosting!$C$6) | G10: =F10/$A10 | H10: =IF(Assumptions!$C$155=1,(Assumptions!$C$135*Assumptions!$C$140+Hosting!$C$5*Assumptions!$C$140+MAX(0,ROUNDUP($A10/Assumptions!$C$141,0)-1)*Hosting!$C$5),IF(Assumptions!$C$155=2,(MAX(Assumptions!$C$145,ROUNDUP($A10/Assumptions!$C$146,0))*Assumptions!$C$144+$A10*Hosting!$C$6),IF($A10>=Assumptions!$C$156,(MAX(Assumptions!$C$145,ROUNDUP($A10/Assumptions!$C$146,0))*Assumptions!$C$144+$A10*Hosting!$C$6),(Assumptions!$C$135*Assumptions!$C$140+Hosting!$C$5*Assumptions!$C$140+MAX(0,ROUNDUP($A10/Assumptions!$C$141,0)-1)*Hosting!$C$5)))) | I10: =H10/$A10 | J10: =Assumptions!$C$159*(Assumptions!$C$160+MAX(0,$A10*Assumptions!$C$163-Assumptions!$C$161)*Assumptions!$C$162) | K10: =J10/$A10 | L10: =I10+K10
A11: 2 | B11: =ROUNDUP($A11/Assumptions!$C$141,0) | C11: =(Assumptions!$C$135*Assumptions!$C$140+Hosting!$C$5*Assumptions!$C$140+MAX(0,ROUNDUP($A11/Assumptions!$C$141,0)-1)*Hosting!$C$5) | D11: =C11/$A11 | E11: =MAX(Assumptions!$C$145,ROUNDUP($A11/Assumptions!$C$146,0)) | F11: =(MAX(Assumptions!$C$145,ROUNDUP($A11/Assumptions!$C$146,0))*Assumptions!$C$144+$A11*Hosting!$C$6) | G11: =F11/$A11 | H11: =IF(Assumptions!$C$155=1,(Assumptions!$C$135*Assumptions!$C$140+Hosting!$C$5*Assumptions!$C$140+MAX(0,ROUNDUP($A11/Assumptions!$C$141,0)-1)*Hosting!$C$5),IF(Assumptions!$C$155=2,(MAX(Assumptions!$C$145,ROUNDUP($A11/Assumptions!$C$146,0))*Assumptions!$C$144+$A11*Hosting!$C$6),IF($A11>=Assumptions!$C$156,(MAX(Assumptions!$C$145,ROUNDUP($A11/Assumptions!$C$146,0))*Assumptions!$C$144+$A11*Hosting!$C$6),(Assumptions!$C$135*Assumptions!$C$140+Hosting!$C$5*Assumptions!$C$140+MAX(0,ROUNDUP($A11/Assumptions!$C$141,0)-1)*Hosting!$C$5)))) | I11: =H11/$A11 | J11: =Assumptions!$C$159*(Assumptions!$C$160+MAX(0,$A11*Assumptions!$C$163-Assumptions!$C$161)*Assumptions!$C$162) | K11: =J11/$A11 | L11: =I11+K11
A12: 5 | B12: =ROUNDUP($A12/Assumptions!$C$141,0) | C12: =(Assumptions!$C$135*Assumptions!$C$140+Hosting!$C$5*Assumptions!$C$140+MAX(0,ROUNDUP($A12/Assumptions!$C$141,0)-1)*Hosting!$C$5) | D12: =C12/$A12 | E12: =MAX(Assumptions!$C$145,ROUNDUP($A12/Assumptions!$C$146,0)) | F12: =(MAX(Assumptions!$C$145,ROUNDUP($A12/Assumptions!$C$146,0))*Assumptions!$C$144+$A12*Hosting!$C$6) | G12: =F12/$A12 | H12: =IF(Assumptions!$C$155=1,(Assumptions!$C$135*Assumptions!$C$140+Hosting!$C$5*Assumptions!$C$140+MAX(0,ROUNDUP($A12/Assumptions!$C$141,0)-1)*Hosting!$C$5),IF(Assumptions!$C$155=2,(MAX(Assumptions!$C$145,ROUNDUP($A12/Assumptions!$C$146,0))*Assumptions!$C$144+$A12*Hosting!$C$6),IF($A12>=Assumptions!$C$156,(MAX(Assumptions!$C$145,ROUNDUP($A12/Assumptions!$C$146,0))*Assumptions!$C$144+$A12*Hosting!$C$6),(Assumptions!$C$135*Assumptions!$C$140+Hosting!$C$5*Assumptions!$C$140+MAX(0,ROUNDUP($A12/Assumptions!$C$141,0)-1)*Hosting!$C$5)))) | I12: =H12/$A12 | J12: =Assumptions!$C$159*(Assumptions!$C$160+MAX(0,$A12*Assumptions!$C$163-Assumptions!$C$161)*Assumptions!$C$162) | K12: =J12/$A12 | L12: =I12+K12
A13: 10 | B13: =ROUNDUP($A13/Assumptions!$C$141,0) | C13: =(Assumptions!$C$135*Assumptions!$C$140+Hosting!$C$5*Assumptions!$C$140+MAX(0,ROUNDUP($A13/Assumptions!$C$141,0)-1)*Hosting!$C$5) | D13: =C13/$A13 | E13: =MAX(Assumptions!$C$145,ROUNDUP($A13/Assumptions!$C$146,0)) | F13: =(MAX(Assumptions!$C$145,ROUNDUP($A13/Assumptions!$C$146,0))*Assumptions!$C$144+$A13*Hosting!$C$6) | G13: =F13/$A13 | H13: =IF(Assumptions!$C$155=1,(Assumptions!$C$135*Assumptions!$C$140+Hosting!$C$5*Assumptions!$C$140+MAX(0,ROUNDUP($A13/Assumptions!$C$141,0)-1)*Hosting!$C$5),IF(Assumptions!$C$155=2,(MAX(Assumptions!$C$145,ROUNDUP($A13/Assumptions!$C$146,0))*Assumptions!$C$144+$A13*Hosting!$C$6),IF($A13>=Assumptions!$C$156,(MAX(Assumptions!$C$145,ROUNDUP($A13/Assumptions!$C$146,0))*Assumptions!$C$144+$A13*Hosting!$C$6),(Assumptions!$C$135*Assumptions!$C$140+Hosting!$C$5*Assumptions!$C$140+MAX(0,ROUNDUP($A13/Assumptions!$C$141,0)-1)*Hosting!$C$5)))) | I13: =H13/$A13 | J13: =Assumptions!$C$159*(Assumptions!$C$160+MAX(0,$A13*Assumptions!$C$163-Assumptions!$C$161)*Assumptions!$C$162) | K13: =J13/$A13 | L13: =I13+K13
A14: 25 | B14: =ROUNDUP($A14/Assumptions!$C$141,0) | C14: =(Assumptions!$C$135*Assumptions!$C$140+Hosting!$C$5*Assumptions!$C$140+MAX(0,ROUNDUP($A14/Assumptions!$C$141,0)-1)*Hosting!$C$5) | D14: =C14/$A14 | E14: =MAX(Assumptions!$C$145,ROUNDUP($A14/Assumptions!$C$146,0)) | F14: =(MAX(Assumptions!$C$145,ROUNDUP($A14/Assumptions!$C$146,0))*Assumptions!$C$144+$A14*Hosting!$C$6) | G14: =F14/$A14 | H14: =IF(Assumptions!$C$155=1,(Assumptions!$C$135*Assumptions!$C$140+Hosting!$C$5*Assumptions!$C$140+MAX(0,ROUNDUP($A14/Assumptions!$C$141,0)-1)*Hosting!$C$5),IF(Assumptions!$C$155=2,(MAX(Assumptions!$C$145,ROUNDUP($A14/Assumptions!$C$146,0))*Assumptions!$C$144+$A14*Hosting!$C$6),IF($A14>=Assumptions!$C$156,(MAX(Assumptions!$C$145,ROUNDUP($A14/Assumptions!$C$146,0))*Assumptions!$C$144+$A14*Hosting!$C$6),(Assumptions!$C$135*Assumptions!$C$140+Hosting!$C$5*Assumptions!$C$140+MAX(0,ROUNDUP($A14/Assumptions!$C$141,0)-1)*Hosting!$C$5)))) | I14: =H14/$A14 | J14: =Assumptions!$C$159*(Assumptions!$C$160+MAX(0,$A14*Assumptions!$C$163-Assumptions!$C$161)*Assumptions!$C$162) | K14: =J14/$A14 | L14: =I14+K14
A15: 50 | B15: =ROUNDUP($A15/Assumptions!$C$141,0) | C15: =(Assumptions!$C$135*Assumptions!$C$140+Hosting!$C$5*Assumptions!$C$140+MAX(0,ROUNDUP($A15/Assumptions!$C$141,0)-1)*Hosting!$C$5) | D15: =C15/$A15 | E15: =MAX(Assumptions!$C$145,ROUNDUP($A15/Assumptions!$C$146,0)) | F15: =(MAX(Assumptions!$C$145,ROUNDUP($A15/Assumptions!$C$146,0))*Assumptions!$C$144+$A15*Hosting!$C$6) | G15: =F15/$A15 | H15: =IF(Assumptions!$C$155=1,(Assumptions!$C$135*Assumptions!$C$140+Hosting!$C$5*Assumptions!$C$140+MAX(0,ROUNDUP($A15/Assumptions!$C$141,0)-1)*Hosting!$C$5),IF(Assumptions!$C$155=2,(MAX(Assumptions!$C$145,ROUNDUP($A15/Assumptions!$C$146,0))*Assumptions!$C$144+$A15*Hosting!$C$6),IF($A15>=Assumptions!$C$156,(MAX(Assumptions!$C$145,ROUNDUP($A15/Assumptions!$C$146,0))*Assumptions!$C$144+$A15*Hosting!$C$6),(Assumptions!$C$135*Assumptions!$C$140+Hosting!$C$5*Assumptions!$C$140+MAX(0,ROUNDUP($A15/Assumptions!$C$141,0)-1)*Hosting!$C$5)))) | I15: =H15/$A15 | J15: =Assumptions!$C$159*(Assumptions!$C$160+MAX(0,$A15*Assumptions!$C$163-Assumptions!$C$161)*Assumptions!$C$162) | K15: =J15/$A15 | L15: =I15+K15
A16: 100 | B16: =ROUNDUP($A16/Assumptions!$C$141,0) | C16: =(Assumptions!$C$135*Assumptions!$C$140+Hosting!$C$5*Assumptions!$C$140+MAX(0,ROUNDUP($A16/Assumptions!$C$141,0)-1)*Hosting!$C$5) | D16: =C16/$A16 | E16: =MAX(Assumptions!$C$145,ROUNDUP($A16/Assumptions!$C$146,0)) | F16: =(MAX(Assumptions!$C$145,ROUNDUP($A16/Assumptions!$C$146,0))*Assumptions!$C$144+$A16*Hosting!$C$6) | G16: =F16/$A16 | H16: =IF(Assumptions!$C$155=1,(Assumptions!$C$135*Assumptions!$C$140+Hosting!$C$5*Assumptions!$C$140+MAX(0,ROUNDUP($A16/Assumptions!$C$141,0)-1)*Hosting!$C$5),IF(Assumptions!$C$155=2,(MAX(Assumptions!$C$145,ROUNDUP($A16/Assumptions!$C$146,0))*Assumptions!$C$144+$A16*Hosting!$C$6),IF($A16>=Assumptions!$C$156,(MAX(Assumptions!$C$145,ROUNDUP($A16/Assumptions!$C$146,0))*Assumptions!$C$144+$A16*Hosting!$C$6),(Assumptions!$C$135*Assumptions!$C$140+Hosting!$C$5*Assumptions!$C$140+MAX(0,ROUNDUP($A16/Assumptions!$C$141,0)-1)*Hosting!$C$5)))) | I16: =H16/$A16 | J16: =Assumptions!$C$159*(Assumptions!$C$160+MAX(0,$A16*Assumptions!$C$163-Assumptions!$C$161)*Assumptions!$C$162) | K16: =J16/$A16 | L16: =I16+K16
A17: 250 | B17: =ROUNDUP($A17/Assumptions!$C$141,0) | C17: =(Assumptions!$C$135*Assumptions!$C$140+Hosting!$C$5*Assumptions!$C$140+MAX(0,ROUNDUP($A17/Assumptions!$C$141,0)-1)*Hosting!$C$5) | D17: =C17/$A17 | E17: =MAX(Assumptions!$C$145,ROUNDUP($A17/Assumptions!$C$146,0)) | F17: =(MAX(Assumptions!$C$145,ROUNDUP($A17/Assumptions!$C$146,0))*Assumptions!$C$144+$A17*Hosting!$C$6) | G17: =F17/$A17 | H17: =IF(Assumptions!$C$155=1,(Assumptions!$C$135*Assumptions!$C$140+Hosting!$C$5*Assumptions!$C$140+MAX(0,ROUNDUP($A17/Assumptions!$C$141,0)-1)*Hosting!$C$5),IF(Assumptions!$C$155=2,(MAX(Assumptions!$C$145,ROUNDUP($A17/Assumptions!$C$146,0))*Assumptions!$C$144+$A17*Hosting!$C$6),IF($A17>=Assumptions!$C$156,(MAX(Assumptions!$C$145,ROUNDUP($A17/Assumptions!$C$146,0))*Assumptions!$C$144+$A17*Hosting!$C$6),(Assumptions!$C$135*Assumptions!$C$140+Hosting!$C$5*Assumptions!$C$140+MAX(0,ROUNDUP($A17/Assumptions!$C$141,0)-1)*Hosting!$C$5)))) | I17: =H17/$A17 | J17: =Assumptions!$C$159*(Assumptions!$C$160+MAX(0,$A17*Assumptions!$C$163-Assumptions!$C$161)*Assumptions!$C$162) | K17: =J17/$A17 | L17: =I17+K17
A18: 500 | B18: =ROUNDUP($A18/Assumptions!$C$141,0) | C18: =(Assumptions!$C$135*Assumptions!$C$140+Hosting!$C$5*Assumptions!$C$140+MAX(0,ROUNDUP($A18/Assumptions!$C$141,0)-1)*Hosting!$C$5) | D18: =C18/$A18 | E18: =MAX(Assumptions!$C$145,ROUNDUP($A18/Assumptions!$C$146,0)) | F18: =(MAX(Assumptions!$C$145,ROUNDUP($A18/Assumptions!$C$146,0))*Assumptions!$C$144+$A18*Hosting!$C$6) | G18: =F18/$A18 | H18: =IF(Assumptions!$C$155=1,(Assumptions!$C$135*Assumptions!$C$140+Hosting!$C$5*Assumptions!$C$140+MAX(0,ROUNDUP($A18/Assumptions!$C$141,0)-1)*Hosting!$C$5),IF(Assumptions!$C$155=2,(MAX(Assumptions!$C$145,ROUNDUP($A18/Assumptions!$C$146,0))*Assumptions!$C$144+$A18*Hosting!$C$6),IF($A18>=Assumptions!$C$156,(MAX(Assumptions!$C$145,ROUNDUP($A18/Assumptions!$C$146,0))*Assumptions!$C$144+$A18*Hosting!$C$6),(Assumptions!$C$135*Assumptions!$C$140+Hosting!$C$5*Assumptions!$C$140+MAX(0,ROUNDUP($A18/Assumptions!$C$141,0)-1)*Hosting!$C$5)))) | I18: =H18/$A18 | J18: =Assumptions!$C$159*(Assumptions!$C$160+MAX(0,$A18*Assumptions!$C$163-Assumptions!$C$161)*Assumptions!$C$162) | K18: =J18/$A18 | L18: =I18+K18

Sheet Forecast
A1: Forecast: 24 months, three scenarios
A2: Tenants ramp to a share of the addressable firms at month 24. Revenue and cost per tenant come from Tiers.
A4: Scenario | B4: Share of firms at month 24 | C4: Addressable firms | D4: Tenants, month 12 | E4: MRR, month 12 | F4: Tenants, month 24 | G4: MRR, month 24 | H4: ARR, month 24 | I4: Gross margin, month 24 | J4: One-time fees, 24 months | K4: Revenue, 24 months
A5: Low | B5: =Assumptions!$C$13 | C5: =Assumptions!$C$12 | D5: =B24 | E5: =G24 | F5: =B36 | G5: =G36 | H5: =H36 | I5: =N36 | J5: =SUM(I13:I36) | K5: =O36
A6: Base | B6: =Assumptions!$C$14 | C6: =Assumptions!$C$12 | D6: =B52 | E6: =G52 | F6: =B64 | G6: =G64 | H6: =H64 | I6: =N64 | J6: =SUM(I41:I64) | K6: =O64
A7: High | B7: =Assumptions!$C$15 | C7: =Assumptions!$C$12 | D7: =B80 | E7: =G80 | F7: =B92 | G7: =G92 | H7: =H92 | I7: =N92 | J7: =SUM(I69:I92) | K7: =O92
A9: Market case is mkt_case on the Assumptions sheet. Gross margin is tool cost only.
A11: Low scenario
A12: Month | B12: Active tenants | C12: New tenants | D12: Platform MRR | E12: Add-on MRR | F12: Overage and resale MRR | G12: Total MRR | H12: ARR run rate | I12: One-time fees | J12: Cost: usage | K12: Cost: hosting, sites and lead lines | L12: Cost: one-time | M12: Gross profit | N12: Gross margin | O12: Cumulative revenue
A13: 1 | B13: =MAX(Assumptions!$C$17,ROUND(Assumptions!$C$12*Assumptions!$C$13*(A13/24)^Assumptions!$C$16,0)) | C13: =MAX(0,B13-Assumptions!$C$17+ROUND(Assumptions!$C$18*Assumptions!$C$17,0)) | D13: =B13*Assumptions!$C$21 | E13: =B13*Tiers!$B$24 | F13: =B13*Tiers!$B$25 | G13: =D13+E13+F13 | H13: =G13*12 | I13: =C13*Tiers!$B$27 | J13: =B13*Tiers!$B$26 | K13: =IF(Assumptions!$C$155=1,(Assumptions!$C$135*Assumptions!$C$140+Hosting!$C$5*Assumptions!$C$140+MAX(0,ROUNDUP(B13/Assumptions!$C$141,0)-1)*Hosting!$C$5),IF(Assumptions!$C$155=2,(MAX(Assumptions!$C$145,ROUNDUP(B13/Assumptions!$C$146,0))*Assumptions!$C$144+B13*Hosting!$C$6),IF(B13>=Assumptions!$C$156,(MAX(Assumptions!$C$145,ROUNDUP(B13/Assumptions!$C$146,0))*Assumptions!$C$144+B13*Hosting!$C$6),(Assumptions!$C$135*Assumptions!$C$140+Hosting!$C$5*Assumptions!$C$140+MAX(0,ROUNDUP(B13/Assumptions!$C$141,0)-1)*Hosting!$C$5))))+Assumptions!$C$159*(Assumptions!$C$160+MAX(0,B13*Assumptions!$C$163-Assumptions!$C$161)*Assumptions!$C$162)+Assumptions!$C$164*Assumptions!$C$165+B13*(Assumptions!$C$168+Assumptions!$C$169) | L13: =C13*Tiers!$B$28 | M13: =G13+I13-J13-K13-L13 | N13: =IF(G13+I13>0,M13/(G13+I13),0) | O13: =G13+I13
A14: 2 | B14: =MAX(Assumptions!$C$17,ROUND(Assumptions!$C$12*Assumptions!$C$13*(A14/24)^Assumptions!$C$16,0)) | C14: =MAX(0,B14-B13+ROUND(Assumptions!$C$18*B13,0)) | D14: =B14*Assumptions!$C$21 | E14: =B14*Tiers!$B$24 | F14: =B14*Tiers!$B$25 | G14: =D14+E14+F14 | H14: =G14*12 | I14: =C14*Tiers!$B$27 | J14: =B14*Tiers!$B$26 | K14: =IF(Assumptions!$C$155=1,(Assumptions!$C$135*Assumptions!$C$140+Hosting!$C$5*Assumptions!$C$140+MAX(0,ROUNDUP(B14/Assumptions!$C$141,0)-1)*Hosting!$C$5),IF(Assumptions!$C$155=2,(MAX(Assumptions!$C$145,ROUNDUP(B14/Assumptions!$C$146,0))*Assumptions!$C$144+B14*Hosting!$C$6),IF(B14>=Assumptions!$C$156,(MAX(Assumptions!$C$145,ROUNDUP(B14/Assumptions!$C$146,0))*Assumptions!$C$144+B14*Hosting!$C$6),(Assumptions!$C$135*Assumptions!$C$140+Hosting!$C$5*Assumptions!$C$140+MAX(0,ROUNDUP(B14/Assumptions!$C$141,0)-1)*Hosting!$C$5))))+Assumptions!$C$159*(Assumptions!$C$160+MAX(0,B14*Assumptions!$C$163-Assumptions!$C$161)*Assumptions!$C$162)+Assumptions!$C$164*Assumptions!$C$165+B14*(Assumptions!$C$168+Assumptions!$C$169) | L14: =C14*Tiers!$B$28 | M14: =G14+I14-J14-K14-L14 | N14: =IF(G14+I14>0,M14/(G14+I14),0) | O14: =O13+G14+I14
A15: 3 | B15: =MAX(Assumptions!$C$17,ROUND(Assumptions!$C$12*Assumptions!$C$13*(A15/24)^Assumptions!$C$16,0)) | C15: =MAX(0,B15-B14+ROUND(Assumptions!$C$18*B14,0)) | D15: =B15*Assumptions!$C$21 | E15: =B15*Tiers!$B$24 | F15: =B15*Tiers!$B$25 | G15: =D15+E15+F15 | H15: =G15*12 | I15: =C15*Tiers!$B$27 | J15: =B15*Tiers!$B$26 | K15: =IF(Assumptions!$C$155=1,(Assumptions!$C$135*Assumptions!$C$140+Hosting!$C$5*Assumptions!$C$140+MAX(0,ROUNDUP(B15/Assumptions!$C$141,0)-1)*Hosting!$C$5),IF(Assumptions!$C$155=2,(MAX(Assumptions!$C$145,ROUNDUP(B15/Assumptions!$C$146,0))*Assumptions!$C$144+B15*Hosting!$C$6),IF(B15>=Assumptions!$C$156,(MAX(Assumptions!$C$145,ROUNDUP(B15/Assumptions!$C$146,0))*Assumptions!$C$144+B15*Hosting!$C$6),(Assumptions!$C$135*Assumptions!$C$140+Hosting!$C$5*Assumptions!$C$140+MAX(0,ROUNDUP(B15/Assumptions!$C$141,0)-1)*Hosting!$C$5))))+Assumptions!$C$159*(Assumptions!$C$160+MAX(0,B15*Assumptions!$C$163-Assumptions!$C$161)*Assumptions!$C$162)+Assumptions!$C$164*Assumptions!$C$165+B15*(Assumptions!$C$168+Assumptions!$C$169) | L15: =C15*Tiers!$B$28 | M15: =G15+I15-J15-K15-L15 | N15: =IF(G15+I15>0,M15/(G15+I15),0) | O15: =O14+G15+I15
A16: 4 | B16: =MAX(Assumptions!$C$17,ROUND(Assumptions!$C$12*Assumptions!$C$13*(A16/24)^Assumptions!$C$16,0)) | C16: =MAX(0,B16-B15+ROUND(Assumptions!$C$18*B15,0)) | D16: =B16*Assumptions!$C$21 | E16: =B16*Tiers!$B$24 | F16: =B16*Tiers!$B$25 | G16: =D16+E16+F16 | H16: =G16*12 | I16: =C16*Tiers!$B$27 | J16: =B16*Tiers!$B$26 | K16: =IF(Assumptions!$C$155=1,(Assumptions!$C$135*Assumptions!$C$140+Hosting!$C$5*Assumptions!$C$140+MAX(0,ROUNDUP(B16/Assumptions!$C$141,0)-1)*Hosting!$C$5),IF(Assumptions!$C$155=2,(MAX(Assumptions!$C$145,ROUNDUP(B16/Assumptions!$C$146,0))*Assumptions!$C$144+B16*Hosting!$C$6),IF(B16>=Assumptions!$C$156,(MAX(Assumptions!$C$145,ROUNDUP(B16/Assumptions!$C$146,0))*Assumptions!$C$144+B16*Hosting!$C$6),(Assumptions!$C$135*Assumptions!$C$140+Hosting!$C$5*Assumptions!$C$140+MAX(0,ROUNDUP(B16/Assumptions!$C$141,0)-1)*Hosting!$C$5))))+Assumptions!$C$159*(Assumptions!$C$160+MAX(0,B16*Assumptions!$C$163-Assumptions!$C$161)*Assumptions!$C$162)+Assumptions!$C$164*Assumptions!$C$165+B16*(Assumptions!$C$168+Assumptions!$C$169) | L16: =C16*Tiers!$B$28 | M16: =G16+I16-J16-K16-L16 | N16: =IF(G16+I16>0,M16/(G16+I16),0) | O16: =O15+G16+I16
A17: 5 | B17: =MAX(Assumptions!$C$17,ROUND(Assumptions!$C$12*Assumptions!$C$13*(A17/24)^Assumptions!$C$16,0)) | C17: =MAX(0,B17-B16+ROUND(Assumptions!$C$18*B16,0)) | D17: =B17*Assumptions!$C$21 | E17: =B17*Tiers!$B$24 | F17: =B17*Tiers!$B$25 | G17: =D17+E17+F17 | H17: =G17*12 | I17: =C17*Tiers!$B$27 | J17: =B17*Tiers!$B$26 | K17: =IF(Assumptions!$C$155=1,(Assumptions!$C$135*Assumptions!$C$140+Hosting!$C$5*Assumptions!$C$140+MAX(0,ROUNDUP(B17/Assumptions!$C$141,0)-1)*Hosting!$C$5),IF(Assumptions!$C$155=2,(MAX(Assumptions!$C$145,ROUNDUP(B17/Assumptions!$C$146,0))*Assumptions!$C$144+B17*Hosting!$C$6),IF(B17>=Assumptions!$C$156,(MAX(Assumptions!$C$145,ROUNDUP(B17/Assumptions!$C$146,0))*Assumptions!$C$144+B17*Hosting!$C$6),(Assumptions!$C$135*Assumptions!$C$140+Hosting!$C$5*Assumptions!$C$140+MAX(0,ROUNDUP(B17/Assumptions!$C$141,0)-1)*Hosting!$C$5))))+Assumptions!$C$159*(Assumptions!$C$160+MAX(0,B17*Assumptions!$C$163-Assumptions!$C$161)*Assumptions!$C$162)+Assumptions!$C$164*Assumptions!$C$165+B17*(Assumptions!$C$168+Assumptions!$C$169) | L17: =C17*Tiers!$B$28 | M17: =G17+I17-J17-K17-L17 | N17: =IF(G17+I17>0,M17/(G17+I17),0) | O17: =O16+G17+I17
A18: 6 | B18: =MAX(Assumptions!$C$17,ROUND(Assumptions!$C$12*Assumptions!$C$13*(A18/24)^Assumptions!$C$16,0)) | C18: =MAX(0,B18-B17+ROUND(Assumptions!$C$18*B17,0)) | D18: =B18*Assumptions!$C$21 | E18: =B18*Tiers!$B$24 | F18: =B18*Tiers!$B$25 | G18: =D18+E18+F18 | H18: =G18*12 | I18: =C18*Tiers!$B$27 | J18: =B18*Tiers!$B$26 | K18: =IF(Assumptions!$C$155=1,(Assumptions!$C$135*Assumptions!$C$140+Hosting!$C$5*Assumptions!$C$140+MAX(0,ROUNDUP(B18/Assumptions!$C$141,0)-1)*Hosting!$C$5),IF(Assumptions!$C$155=2,(MAX(Assumptions!$C$145,ROUNDUP(B18/Assumptions!$C$146,0))*Assumptions!$C$144+B18*Hosting!$C$6),IF(B18>=Assumptions!$C$156,(MAX(Assumptions!$C$145,ROUNDUP(B18/Assumptions!$C$146,0))*Assumptions!$C$144+B18*Hosting!$C$6),(Assumptions!$C$135*Assumptions!$C$140+Hosting!$C$5*Assumptions!$C$140+MAX(0,ROUNDUP(B18/Assumptions!$C$141,0)-1)*Hosting!$C$5))))+Assumptions!$C$159*(Assumptions!$C$160+MAX(0,B18*Assumptions!$C$163-Assumptions!$C$161)*Assumptions!$C$162)+Assumptions!$C$164*Assumptions!$C$165+B18*(Assumptions!$C$168+Assumptions!$C$169) | L18: =C18*Tiers!$B$28 | M18: =G18+I18-J18-K18-L18 | N18: =IF(G18+I18>0,M18/(G18+I18),0) | O18: =O17+G18+I18
A19: 7 | B19: =MAX(Assumptions!$C$17,ROUND(Assumptions!$C$12*Assumptions!$C$13*(A19/24)^Assumptions!$C$16,0)) | C19: =MAX(0,B19-B18+ROUND(Assumptions!$C$18*B18,0)) | D19: =B19*Assumptions!$C$21 | E19: =B19*Tiers!$B$24 | F19: =B19*Tiers!$B$25 | G19: =D19+E19+F19 | H19: =G19*12 | I19: =C19*Tiers!$B$27 | J19: =B19*Tiers!$B$26 | K19: =IF(Assumptions!$C$155=1,(Assumptions!$C$135*Assumptions!$C$140+Hosting!$C$5*Assumptions!$C$140+MAX(0,ROUNDUP(B19/Assumptions!$C$141,0)-1)*Hosting!$C$5),IF(Assumptions!$C$155=2,(MAX(Assumptions!$C$145,ROUNDUP(B19/Assumptions!$C$146,0))*Assumptions!$C$144+B19*Hosting!$C$6),IF(B19>=Assumptions!$C$156,(MAX(Assumptions!$C$145,ROUNDUP(B19/Assumptions!$C$146,0))*Assumptions!$C$144+B19*Hosting!$C$6),(Assumptions!$C$135*Assumptions!$C$140+Hosting!$C$5*Assumptions!$C$140+MAX(0,ROUNDUP(B19/Assumptions!$C$141,0)-1)*Hosting!$C$5))))+Assumptions!$C$159*(Assumptions!$C$160+MAX(0,B19*Assumptions!$C$163-Assumptions!$C$161)*Assumptions!$C$162)+Assumptions!$C$164*Assumptions!$C$165+B19*(Assumptions!$C$168+Assumptions!$C$169) | L19: =C19*Tiers!$B$28 | M19: =G19+I19-J19-K19-L19 | N19: =IF(G19+I19>0,M19/(G19+I19),0) | O19: =O18+G19+I19
A20: 8 | B20: =MAX(Assumptions!$C$17,ROUND(Assumptions!$C$12*Assumptions!$C$13*(A20/24)^Assumptions!$C$16,0)) | C20: =MAX(0,B20-B19+ROUND(Assumptions!$C$18*B19,0)) | D20: =B20*Assumptions!$C$21 | E20: =B20*Tiers!$B$24 | F20: =B20*Tiers!$B$25 | G20: =D20+E20+F20 | H20: =G20*12 | I20: =C20*Tiers!$B$27 | J20: =B20*Tiers!$B$26 | K20: =IF(Assumptions!$C$155=1,(Assumptions!$C$135*Assumptions!$C$140+Hosting!$C$5*Assumptions!$C$140+MAX(0,ROUNDUP(B20/Assumptions!$C$141,0)-1)*Hosting!$C$5),IF(Assumptions!$C$155=2,(MAX(Assumptions!$C$145,ROUNDUP(B20/Assumptions!$C$146,0))*Assumptions!$C$144+B20*Hosting!$C$6),IF(B20>=Assumptions!$C$156,(MAX(Assumptions!$C$145,ROUNDUP(B20/Assumptions!$C$146,0))*Assumptions!$C$144+B20*Hosting!$C$6),(Assumptions!$C$135*Assumptions!$C$140+Hosting!$C$5*Assumptions!$C$140+MAX(0,ROUNDUP(B20/Assumptions!$C$141,0)-1)*Hosting!$C$5))))+Assumptions!$C$159*(Assumptions!$C$160+MAX(0,B20*Assumptions!$C$163-Assumptions!$C$161)*Assumptions!$C$162)+Assumptions!$C$164*Assumptions!$C$165+B20*(Assumptions!$C$168+Assumptions!$C$169) | L20: =C20*Tiers!$B$28 | M20: =G20+I20-J20-K20-L20 | N20: =IF(G20+I20>0,M20/(G20+I20),0) | O20: =O19+G20+I20
A21: 9 | B21: =MAX(Assumptions!$C$17,ROUND(Assumptions!$C$12*Assumptions!$C$13*(A21/24)^Assumptions!$C$16,0)) | C21: =MAX(0,B21-B20+ROUND(Assumptions!$C$18*B20,0)) | D21: =B21*Assumptions!$C$21 | E21: =B21*Tiers!$B$24 | F21: =B21*Tiers!$B$25 | G21: =D21+E21+F21 | H21: =G21*12 | I21: =C21*Tiers!$B$27 | J21: =B21*Tiers!$B$26 | K21: =IF(Assumptions!$C$155=1,(Assumptions!$C$135*Assumptions!$C$140+Hosting!$C$5*Assumptions!$C$140+MAX(0,ROUNDUP(B21/Assumptions!$C$141,0)-1)*Hosting!$C$5),IF(Assumptions!$C$155=2,(MAX(Assumptions!$C$145,ROUNDUP(B21/Assumptions!$C$146,0))*Assumptions!$C$144+B21*Hosting!$C$6),IF(B21>=Assumptions!$C$156,(MAX(Assumptions!$C$145,ROUNDUP(B21/Assumptions!$C$146,0))*Assumptions!$C$144+B21*Hosting!$C$6),(Assumptions!$C$135*Assumptions!$C$140+Hosting!$C$5*Assumptions!$C$140+MAX(0,ROUNDUP(B21/Assumptions!$C$141,0)-1)*Hosting!$C$5))))+Assumptions!$C$159*(Assumptions!$C$160+MAX(0,B21*Assumptions!$C$163-Assumptions!$C$161)*Assumptions!$C$162)+Assumptions!$C$164*Assumptions!$C$165+B21*(Assumptions!$C$168+Assumptions!$C$169) | L21: =C21*Tiers!$B$28 | M21: =G21+I21-J21-K21-L21 | N21: =IF(G21+I21>0,M21/(G21+I21),0) | O21: =O20+G21+I21
A22: 10 | B22: =MAX(Assumptions!$C$17,ROUND(Assumptions!$C$12*Assumptions!$C$13*(A22/24)^Assumptions!$C$16,0)) | C22: =MAX(0,B22-B21+ROUND(Assumptions!$C$18*B21,0)) | D22: =B22*Assumptions!$C$21 | E22: =B22*Tiers!$B$24 | F22: =B22*Tiers!$B$25 | G22: =D22+E22+F22 | H22: =G22*12 | I22: =C22*Tiers!$B$27 | J22: =B22*Tiers!$B$26 | K22: =IF(Assumptions!$C$155=1,(Assumptions!$C$135*Assumptions!$C$140+Hosting!$C$5*Assumptions!$C$140+MAX(0,ROUNDUP(B22/Assumptions!$C$141,0)-1)*Hosting!$C$5),IF(Assumptions!$C$155=2,(MAX(Assumptions!$C$145,ROUNDUP(B22/Assumptions!$C$146,0))*Assumptions!$C$144+B22*Hosting!$C$6),IF(B22>=Assumptions!$C$156,(MAX(Assumptions!$C$145,ROUNDUP(B22/Assumptions!$C$146,0))*Assumptions!$C$144+B22*Hosting!$C$6),(Assumptions!$C$135*Assumptions!$C$140+Hosting!$C$5*Assumptions!$C$140+MAX(0,ROUNDUP(B22/Assumptions!$C$141,0)-1)*Hosting!$C$5))))+Assumptions!$C$159*(Assumptions!$C$160+MAX(0,B22*Assumptions!$C$163-Assumptions!$C$161)*Assumptions!$C$162)+Assumptions!$C$164*Assumptions!$C$165+B22*(Assumptions!$C$168+Assumptions!$C$169) | L22: =C22*Tiers!$B$28 | M22: =G22+I22-J22-K22-L22 | N22: =IF(G22+I22>0,M22/(G22+I22),0) | O22: =O21+G22+I22
A23: 11 | B23: =MAX(Assumptions!$C$17,ROUND(Assumptions!$C$12*Assumptions!$C$13*(A23/24)^Assumptions!$C$16,0)) | C23: =MAX(0,B23-B22+ROUND(Assumptions!$C$18*B22,0)) | D23: =B23*Assumptions!$C$21 | E23: =B23*Tiers!$B$24 | F23: =B23*Tiers!$B$25 | G23: =D23+E23+F23 | H23: =G23*12 | I23: =C23*Tiers!$B$27 | J23: =B23*Tiers!$B$26 | K23: =IF(Assumptions!$C$155=1,(Assumptions!$C$135*Assumptions!$C$140+Hosting!$C$5*Assumptions!$C$140+MAX(0,ROUNDUP(B23/Assumptions!$C$141,0)-1)*Hosting!$C$5),IF(Assumptions!$C$155=2,(MAX(Assumptions!$C$145,ROUNDUP(B23/Assumptions!$C$146,0))*Assumptions!$C$144+B23*Hosting!$C$6),IF(B23>=Assumptions!$C$156,(MAX(Assumptions!$C$145,ROUNDUP(B23/Assumptions!$C$146,0))*Assumptions!$C$144+B23*Hosting!$C$6),(Assumptions!$C$135*Assumptions!$C$140+Hosting!$C$5*Assumptions!$C$140+MAX(0,ROUNDUP(B23/Assumptions!$C$141,0)-1)*Hosting!$C$5))))+Assumptions!$C$159*(Assumptions!$C$160+MAX(0,B23*Assumptions!$C$163-Assumptions!$C$161)*Assumptions!$C$162)+Assumptions!$C$164*Assumptions!$C$165+B23*(Assumptions!$C$168+Assumptions!$C$169) | L23: =C23*Tiers!$B$28 | M23: =G23+I23-J23-K23-L23 | N23: =IF(G23+I23>0,M23/(G23+I23),0) | O23: =O22+G23+I23
A24: 12 | B24: =MAX(Assumptions!$C$17,ROUND(Assumptions!$C$12*Assumptions!$C$13*(A24/24)^Assumptions!$C$16,0)) | C24: =MAX(0,B24-B23+ROUND(Assumptions!$C$18*B23,0)) | D24: =B24*Assumptions!$C$21 | E24: =B24*Tiers!$B$24 | F24: =B24*Tiers!$B$25 | G24: =D24+E24+F24 | H24: =G24*12 | I24: =C24*Tiers!$B$27 | J24: =B24*Tiers!$B$26 | K24: =IF(Assumptions!$C$155=1,(Assumptions!$C$135*Assumptions!$C$140+Hosting!$C$5*Assumptions!$C$140+MAX(0,ROUNDUP(B24/Assumptions!$C$141,0)-1)*Hosting!$C$5),IF(Assumptions!$C$155=2,(MAX(Assumptions!$C$145,ROUNDUP(B24/Assumptions!$C$146,0))*Assumptions!$C$144+B24*Hosting!$C$6),IF(B24>=Assumptions!$C$156,(MAX(Assumptions!$C$145,ROUNDUP(B24/Assumptions!$C$146,0))*Assumptions!$C$144+B24*Hosting!$C$6),(Assumptions!$C$135*Assumptions!$C$140+Hosting!$C$5*Assumptions!$C$140+MAX(0,ROUNDUP(B24/Assumptions!$C$141,0)-1)*Hosting!$C$5))))+Assumptions!$C$159*(Assumptions!$C$160+MAX(0,B24*Assumptions!$C$163-Assumptions!$C$161)*Assumptions!$C$162)+Assumptions!$C$164*Assumptions!$C$165+B24*(Assumptions!$C$168+Assumptions!$C$169) | L24: =C24*Tiers!$B$28 | M24: =G24+I24-J24-K24-L24 | N24: =IF(G24+I24>0,M24/(G24+I24),0) | O24: =O23+G24+I24
A25: 13 | B25: =MAX(Assumptions!$C$17,ROUND(Assumptions!$C$12*Assumptions!$C$13*(A25/24)^Assumptions!$C$16,0)) | C25: =MAX(0,B25-B24+ROUND(Assumptions!$C$18*B24,0)) | D25: =B25*Assumptions!$C$21 | E25: =B25*Tiers!$B$24 | F25: =B25*Tiers!$B$25 | G25: =D25+E25+F25 | H25: =G25*12 | I25: =C25*Tiers!$B$27 | J25: =B25*Tiers!$B$26 | K25: =IF(Assumptions!$C$155=1,(Assumptions!$C$135*Assumptions!$C$140+Hosting!$C$5*Assumptions!$C$140+MAX(0,ROUNDUP(B25/Assumptions!$C$141,0)-1)*Hosting!$C$5),IF(Assumptions!$C$155=2,(MAX(Assumptions!$C$145,ROUNDUP(B25/Assumptions!$C$146,0))*Assumptions!$C$144+B25*Hosting!$C$6),IF(B25>=Assumptions!$C$156,(MAX(Assumptions!$C$145,ROUNDUP(B25/Assumptions!$C$146,0))*Assumptions!$C$144+B25*Hosting!$C$6),(Assumptions!$C$135*Assumptions!$C$140+Hosting!$C$5*Assumptions!$C$140+MAX(0,ROUNDUP(B25/Assumptions!$C$141,0)-1)*Hosting!$C$5))))+Assumptions!$C$159*(Assumptions!$C$160+MAX(0,B25*Assumptions!$C$163-Assumptions!$C$161)*Assumptions!$C$162)+Assumptions!$C$164*Assumptions!$C$165+B25*(Assumptions!$C$168+Assumptions!$C$169) | L25: =C25*Tiers!$B$28 | M25: =G25+I25-J25-K25-L25 | N25: =IF(G25+I25>0,M25/(G25+I25),0) | O25: =O24+G25+I25
... A36: 24 | B36: =MAX(Assumptions!$C$17,ROUND(Assumptions!$C$12*Assumptions!$C$13*(A36/24)^Assumptions!$C$16,0)) | C36: =MAX(0,B36-B35+ROUND(Assumptions!$C$18*B35,0)) | D36: =B36*Assumptions!$C$21 | E36: =B36*Tiers!$B$24 | F36: =B36*Tiers!$B$25 | G36: =D36+E36+F36 | H36: =G36*12 | I36: =C36*Tiers!$B$27 | J36: =B36*Tiers!$B$26 | K36: =IF(Assumptions!$C$155=1,(Assumptions!$C$135*Assumptions!$C$140+Hosting!$C$5*Assumptions!$C$140+MAX(0,ROUNDUP(B36/Assumptions!$C$141,0)-1)*Hosting!$C$5),IF(Assumptions!$C$155=2,(MAX(Assumptions!$C$145,ROUNDUP(B36/Assumptions!$C$146,0))*Assumptions!$C$144+B36*Hosting!$C$6),IF(B36>=Assumptions!$C$156,(MAX(Assumptions!$C$145,ROUNDUP(B36/Assumptions!$C$146,0))*Assumptions!$C$144+B36*Hosting!$C$6),(Assumptions!$C$135*Assumptions!$C$140+Hosting!$C$5*Assumptions!$C$140+MAX(0,ROUNDUP(B36/Assumptions!$C$141,0)-1)*Hosting!$C$5))))+Assumptions!$C$159*(Assumptions!$C$160+MAX(0,B36*Assumptions!$C$163-Assumptions!$C$161)*Assumptions!$C$162)+Assumptions!$C$164*Assumptions!$C$165+B36*(Assumptions!$C$168+Assumptions!$C$169) | L36: =C36*Tiers!$B$28 | M36: =G36+I36-J36-K36-L36 | N36: =IF(G36+I36>0,M36/(G36+I36),0) | O36: =O35+G36+I36
A39: Base scenario
A40: Month | B40: Active tenants | C40: New tenants | D40: Platform MRR | E40: Add-on MRR | F40: Overage and resale MRR | G40: Total MRR | H40: ARR run rate | I40: One-time fees | J40: Cost: usage | K40: Cost: hosting, sites and lead lines | L40: Cost: one-time | M40: Gross profit | N40: Gross margin | O40: Cumulative revenue
A41: 1 | B41: =MAX(Assumptions!$C$17,ROUND(Assumptions!$C$12*Assumptions!$C$14*(A41/24)^Assumptions!$C$16,0)) | C41: =MAX(0,B41-Assumptions!$C$17+ROUND(Assumptions!$C$18*Assumptions!$C$17,0)) | D41: =B41*Assumptions!$C$21 | E41: =B41*Tiers!$B$24 | F41: =B41*Tiers!$B$25 | G41: =D41+E41+F41 | H41: =G41*12 | I41: =C41*Tiers!$B$27 | J41: =B41*Tiers!$B$26 | K41: =IF(Assumptions!$C$155=1,(Assumptions!$C$135*Assumptions!$C$140+Hosting!$C$5*Assumptions!$C$140+MAX(0,ROUNDUP(B41/Assumptions!$C$141,0)-1)*Hosting!$C$5),IF(Assumptions!$C$155=2,(MAX(Assumptions!$C$145,ROUNDUP(B41/Assumptions!$C$146,0))*Assumptions!$C$144+B41*Hosting!$C$6),IF(B41>=Assumptions!$C$156,(MAX(Assumptions!$C$145,ROUNDUP(B41/Assumptions!$C$146,0))*Assumptions!$C$144+B41*Hosting!$C$6),(Assumptions!$C$135*Assumptions!$C$140+Hosting!$C$5*Assumptions!$C$140+MAX(0,ROUNDUP(B41/Assumptions!$C$141,0)-1)*Hosting!$C$5))))+Assumptions!$C$159*(Assumptions!$C$160+MAX(0,B41*Assumptions!$C$163-Assumptions!$C$161)*Assumptions!$C$162)+Assumptions!$C$164*Assumptions!$C$165+B41*(Assumptions!$C$168+Assumptions!$C$169) | L41: =C41*Tiers!$B$28 | M41: =G41+I41-J41-K41-L41 | N41: =IF(G41+I41>0,M41/(G41+I41),0) | O41: =G41+I41
A42: 2 | B42: =MAX(Assumptions!$C$17,ROUND(Assumptions!$C$12*Assumptions!$C$14*(A42/24)^Assumptions!$C$16,0)) | C42: =MAX(0,B42-B41+ROUND(Assumptions!$C$18*B41,0)) | D42: =B42*Assumptions!$C$21 | E42: =B42*Tiers!$B$24 | F42: =B42*Tiers!$B$25 | G42: =D42+E42+F42 | H42: =G42*12 | I42: =C42*Tiers!$B$27 | J42: =B42*Tiers!$B$26 | K42: =IF(Assumptions!$C$155=1,(Assumptions!$C$135*Assumptions!$C$140+Hosting!$C$5*Assumptions!$C$140+MAX(0,ROUNDUP(B42/Assumptions!$C$141,0)-1)*Hosting!$C$5),IF(Assumptions!$C$155=2,(MAX(Assumptions!$C$145,ROUNDUP(B42/Assumptions!$C$146,0))*Assumptions!$C$144+B42*Hosting!$C$6),IF(B42>=Assumptions!$C$156,(MAX(Assumptions!$C$145,ROUNDUP(B42/Assumptions!$C$146,0))*Assumptions!$C$144+B42*Hosting!$C$6),(Assumptions!$C$135*Assumptions!$C$140+Hosting!$C$5*Assumptions!$C$140+MAX(0,ROUNDUP(B42/Assumptions!$C$141,0)-1)*Hosting!$C$5))))+Assumptions!$C$159*(Assumptions!$C$160+MAX(0,B42*Assumptions!$C$163-Assumptions!$C$161)*Assumptions!$C$162)+Assumptions!$C$164*Assumptions!$C$165+B42*(Assumptions!$C$168+Assumptions!$C$169) | L42: =C42*Tiers!$B$28 | M42: =G42+I42-J42-K42-L42 | N42: =IF(G42+I42>0,M42/(G42+I42),0) | O42: =O41+G42+I42
A43: 3 | B43: =MAX(Assumptions!$C$17,ROUND(Assumptions!$C$12*Assumptions!$C$14*(A43/24)^Assumptions!$C$16,0)) | C43: =MAX(0,B43-B42+ROUND(Assumptions!$C$18*B42,0)) | D43: =B43*Assumptions!$C$21 | E43: =B43*Tiers!$B$24 | F43: =B43*Tiers!$B$25 | G43: =D43+E43+F43 | H43: =G43*12 | I43: =C43*Tiers!$B$27 | J43: =B43*Tiers!$B$26 | K43: =IF(Assumptions!$C$155=1,(Assumptions!$C$135*Assumptions!$C$140+Hosting!$C$5*Assumptions!$C$140+MAX(0,ROUNDUP(B43/Assumptions!$C$141,0)-1)*Hosting!$C$5),IF(Assumptions!$C$155=2,(MAX(Assumptions!$C$145,ROUNDUP(B43/Assumptions!$C$146,0))*Assumptions!$C$144+B43*Hosting!$C$6),IF(B43>=Assumptions!$C$156,(MAX(Assumptions!$C$145,ROUNDUP(B43/Assumptions!$C$146,0))*Assumptions!$C$144+B43*Hosting!$C$6),(Assumptions!$C$135*Assumptions!$C$140+Hosting!$C$5*Assumptions!$C$140+MAX(0,ROUNDUP(B43/Assumptions!$C$141,0)-1)*Hosting!$C$5))))+Assumptions!$C$159*(Assumptions!$C$160+MAX(0,B43*Assumptions!$C$163-Assumptions!$C$161)*Assumptions!$C$162)+Assumptions!$C$164*Assumptions!$C$165+B43*(Assumptions!$C$168+Assumptions!$C$169) | L43: =C43*Tiers!$B$28 | M43: =G43+I43-J43-K43-L43 | N43: =IF(G43+I43>0,M43/(G43+I43),0) | O43: =O42+G43+I43
A44: 4 | B44: =MAX(Assumptions!$C$17,ROUND(Assumptions!$C$12*Assumptions!$C$14*(A44/24)^Assumptions!$C$16,0)) | C44: =MAX(0,B44-B43+ROUND(Assumptions!$C$18*B43,0)) | D44: =B44*Assumptions!$C$21 | E44: =B44*Tiers!$B$24 | F44: =B44*Tiers!$B$25 | G44: =D44+E44+F44 | H44: =G44*12 | I44: =C44*Tiers!$B$27 | J44: =B44*Tiers!$B$26 | K44: =IF(Assumptions!$C$155=1,(Assumptions!$C$135*Assumptions!$C$140+Hosting!$C$5*Assumptions!$C$140+MAX(0,ROUNDUP(B44/Assumptions!$C$141,0)-1)*Hosting!$C$5),IF(Assumptions!$C$155=2,(MAX(Assumptions!$C$145,ROUNDUP(B44/Assumptions!$C$146,0))*Assumptions!$C$144+B44*Hosting!$C$6),IF(B44>=Assumptions!$C$156,(MAX(Assumptions!$C$145,ROUNDUP(B44/Assumptions!$C$146,0))*Assumptions!$C$144+B44*Hosting!$C$6),(Assumptions!$C$135*Assumptions!$C$140+Hosting!$C$5*Assumptions!$C$140+MAX(0,ROUNDUP(B44/Assumptions!$C$141,0)-1)*Hosting!$C$5))))+Assumptions!$C$159*(Assumptions!$C$160+MAX(0,B44*Assumptions!$C$163-Assumptions!$C$161)*Assumptions!$C$162)+Assumptions!$C$164*Assumptions!$C$165+B44*(Assumptions!$C$168+Assumptions!$C$169) | L44: =C44*Tiers!$B$28 | M44: =G44+I44-J44-K44-L44 | N44: =IF(G44+I44>0,M44/(G44+I44),0) | O44: =O43+G44+I44
A45: 5 | B45: =MAX(Assumptions!$C$17,ROUND(Assumptions!$C$12*Assumptions!$C$14*(A45/24)^Assumptions!$C$16,0)) | C45: =MAX(0,B45-B44+ROUND(Assumptions!$C$18*B44,0)) | D45: =B45*Assumptions!$C$21 | E45: =B45*Tiers!$B$24 | F45: =B45*Tiers!$B$25 | G45: =D45+E45+F45 | H45: =G45*12 | I45: =C45*Tiers!$B$27 | J45: =B45*Tiers!$B$26 | K45: =IF(Assumptions!$C$155=1,(Assumptions!$C$135*Assumptions!$C$140+Hosting!$C$5*Assumptions!$C$140+MAX(0,ROUNDUP(B45/Assumptions!$C$141,0)-1)*Hosting!$C$5),IF(Assumptions!$C$155=2,(MAX(Assumptions!$C$145,ROUNDUP(B45/Assumptions!$C$146,0))*Assumptions!$C$144+B45*Hosting!$C$6),IF(B45>=Assumptions!$C$156,(MAX(Assumptions!$C$145,ROUNDUP(B45/Assumptions!$C$146,0))*Assumptions!$C$144+B45*Hosting!$C$6),(Assumptions!$C$135*Assumptions!$C$140+Hosting!$C$5*Assumptions!$C$140+MAX(0,ROUNDUP(B45/Assumptions!$C$141,0)-1)*Hosting!$C$5))))+Assumptions!$C$159*(Assumptions!$C$160+MAX(0,B45*Assumptions!$C$163-Assumptions!$C$161)*Assumptions!$C$162)+Assumptions!$C$164*Assumptions!$C$165+B45*(Assumptions!$C$168+Assumptions!$C$169) | L45: =C45*Tiers!$B$28 | M45: =G45+I45-J45-K45-L45 | N45: =IF(G45+I45>0,M45/(G45+I45),0) | O45: =O44+G45+I45
A46: 6 | B46: =MAX(Assumptions!$C$17,ROUND(Assumptions!$C$12*Assumptions!$C$14*(A46/24)^Assumptions!$C$16,0)) | C46: =MAX(0,B46-B45+ROUND(Assumptions!$C$18*B45,0)) | D46: =B46*Assumptions!$C$21 | E46: =B46*Tiers!$B$24 | F46: =B46*Tiers!$B$25 | G46: =D46+E46+F46 | H46: =G46*12 | I46: =C46*Tiers!$B$27 | J46: =B46*Tiers!$B$26 | K46: =IF(Assumptions!$C$155=1,(Assumptions!$C$135*Assumptions!$C$140+Hosting!$C$5*Assumptions!$C$140+MAX(0,ROUNDUP(B46/Assumptions!$C$141,0)-1)*Hosting!$C$5),IF(Assumptions!$C$155=2,(MAX(Assumptions!$C$145,ROUNDUP(B46/Assumptions!$C$146,0))*Assumptions!$C$144+B46*Hosting!$C$6),IF(B46>=Assumptions!$C$156,(MAX(Assumptions!$C$145,ROUNDUP(B46/Assumptions!$C$146,0))*Assumptions!$C$144+B46*Hosting!$C$6),(Assumptions!$C$135*Assumptions!$C$140+Hosting!$C$5*Assumptions!$C$140+MAX(0,ROUNDUP(B46/Assumptions!$C$141,0)-1)*Hosting!$C$5))))+Assumptions!$C$159*(Assumptions!$C$160+MAX(0,B46*Assumptions!$C$163-Assumptions!$C$161)*Assumptions!$C$162)+Assumptions!$C$164*Assumptions!$C$165+B46*(Assumptions!$C$168+Assumptions!$C$169) | L46: =C46*Tiers!$B$28 | M46: =G46+I46-J46-K46-L46 | N46: =IF(G46+I46>0,M46/(G46+I46),0) | O46: =O45+G46+I46
A47: 7 | B47: =MAX(Assumptions!$C$17,ROUND(Assumptions!$C$12*Assumptions!$C$14*(A47/24)^Assumptions!$C$16,0)) | C47: =MAX(0,B47-B46+ROUND(Assumptions!$C$18*B46,0)) | D47: =B47*Assumptions!$C$21 | E47: =B47*Tiers!$B$24 | F47: =B47*Tiers!$B$25 | G47: =D47+E47+F47 | H47: =G47*12 | I47: =C47*Tiers!$B$27 | J47: =B47*Tiers!$B$26 | K47: =IF(Assumptions!$C$155=1,(Assumptions!$C$135*Assumptions!$C$140+Hosting!$C$5*Assumptions!$C$140+MAX(0,ROUNDUP(B47/Assumptions!$C$141,0)-1)*Hosting!$C$5),IF(Assumptions!$C$155=2,(MAX(Assumptions!$C$145,ROUNDUP(B47/Assumptions!$C$146,0))*Assumptions!$C$144+B47*Hosting!$C$6),IF(B47>=Assumptions!$C$156,(MAX(Assumptions!$C$145,ROUNDUP(B47/Assumptions!$C$146,0))*Assumptions!$C$144+B47*Hosting!$C$6),(Assumptions!$C$135*Assumptions!$C$140+Hosting!$C$5*Assumptions!$C$140+MAX(0,ROUNDUP(B47/Assumptions!$C$141,0)-1)*Hosting!$C$5))))+Assumptions!$C$159*(Assumptions!$C$160+MAX(0,B47*Assumptions!$C$163-Assumptions!$C$161)*Assumptions!$C$162)+Assumptions!$C$164*Assumptions!$C$165+B47*(Assumptions!$C$168+Assumptions!$C$169) | L47: =C47*Tiers!$B$28 | M47: =G47+I47-J47-K47-L47 | N47: =IF(G47+I47>0,M47/(G47+I47),0) | O47: =O46+G47+I47
A48: 8 | B48: =MAX(Assumptions!$C$17,ROUND(Assumptions!$C$12*Assumptions!$C$14*(A48/24)^Assumptions!$C$16,0)) | C48: =MAX(0,B48-B47+ROUND(Assumptions!$C$18*B47,0)) | D48: =B48*Assumptions!$C$21 | E48: =B48*Tiers!$B$24 | F48: =B48*Tiers!$B$25 | G48: =D48+E48+F48 | H48: =G48*12 | I48: =C48*Tiers!$B$27 | J48: =B48*Tiers!$B$26 | K48: =IF(Assumptions!$C$155=1,(Assumptions!$C$135*Assumptions!$C$140+Hosting!$C$5*Assumptions!$C$140+MAX(0,ROUNDUP(B48/Assumptions!$C$141,0)-1)*Hosting!$C$5),IF(Assumptions!$C$155=2,(MAX(Assumptions!$C$145,ROUNDUP(B48/Assumptions!$C$146,0))*Assumptions!$C$144+B48*Hosting!$C$6),IF(B48>=Assumptions!$C$156,(MAX(Assumptions!$C$145,ROUNDUP(B48/Assumptions!$C$146,0))*Assumptions!$C$144+B48*Hosting!$C$6),(Assumptions!$C$135*Assumptions!$C$140+Hosting!$C$5*Assumptions!$C$140+MAX(0,ROUNDUP(B48/Assumptions!$C$141,0)-1)*Hosting!$C$5))))+Assumptions!$C$159*(Assumptions!$C$160+MAX(0,B48*Assumptions!$C$163-Assumptions!$C$161)*Assumptions!$C$162)+Assumptions!$C$164*Assumptions!$C$165+B48*(Assumptions!$C$168+Assumptions!$C$169) | L48: =C48*Tiers!$B$28 | M48: =G48+I48-J48-K48-L48 | N48: =IF(G48+I48>0,M48/(G48+I48),0) | O48: =O47+G48+I48
A49: 9 | B49: =MAX(Assumptions!$C$17,ROUND(Assumptions!$C$12*Assumptions!$C$14*(A49/24)^Assumptions!$C$16,0)) | C49: =MAX(0,B49-B48+ROUND(Assumptions!$C$18*B48,0)) | D49: =B49*Assumptions!$C$21 | E49: =B49*Tiers!$B$24 | F49: =B49*Tiers!$B$25 | G49: =D49+E49+F49 | H49: =G49*12 | I49: =C49*Tiers!$B$27 | J49: =B49*Tiers!$B$26 | K49: =IF(Assumptions!$C$155=1,(Assumptions!$C$135*Assumptions!$C$140+Hosting!$C$5*Assumptions!$C$140+MAX(0,ROUNDUP(B49/Assumptions!$C$141,0)-1)*Hosting!$C$5),IF(Assumptions!$C$155=2,(MAX(Assumptions!$C$145,ROUNDUP(B49/Assumptions!$C$146,0))*Assumptions!$C$144+B49*Hosting!$C$6),IF(B49>=Assumptions!$C$156,(MAX(Assumptions!$C$145,ROUNDUP(B49/Assumptions!$C$146,0))*Assumptions!$C$144+B49*Hosting!$C$6),(Assumptions!$C$135*Assumptions!$C$140+Hosting!$C$5*Assumptions!$C$140+MAX(0,ROUNDUP(B49/Assumptions!$C$141,0)-1)*Hosting!$C$5))))+Assumptions!$C$159*(Assumptions!$C$160+MAX(0,B49*Assumptions!$C$163-Assumptions!$C$161)*Assumptions!$C$162)+Assumptions!$C$164*Assumptions!$C$165+B49*(Assumptions!$C$168+Assumptions!$C$169) | L49: =C49*Tiers!$B$28 | M49: =G49+I49-J49-K49-L49 | N49: =IF(G49+I49>0,M49/(G49+I49),0) | O49: =O48+G49+I49
A50: 10 | B50: =MAX(Assumptions!$C$17,ROUND(Assumptions!$C$12*Assumptions!$C$14*(A50/24)^Assumptions!$C$16,0)) | C50: =MAX(0,B50-B49+ROUND(Assumptions!$C$18*B49,0)) | D50: =B50*Assumptions!$C$21 | E50: =B50*Tiers!$B$24 | F50: =B50*Tiers!$B$25 | G50: =D50+E50+F50 | H50: =G50*12 | I50: =C50*Tiers!$B$27 | J50: =B50*Tiers!$B$26 | K50: =IF(Assumptions!$C$155=1,(Assumptions!$C$135*Assumptions!$C$140+Hosting!$C$5*Assumptions!$C$140+MAX(0,ROUNDUP(B50/Assumptions!$C$141,0)-1)*Hosting!$C$5),IF(Assumptions!$C$155=2,(MAX(Assumptions!$C$145,ROUNDUP(B50/Assumptions!$C$146,0))*Assumptions!$C$144+B50*Hosting!$C$6),IF(B50>=Assumptions!$C$156,(MAX(Assumptions!$C$145,ROUNDUP(B50/Assumptions!$C$146,0))*Assumptions!$C$144+B50*Hosting!$C$6),(Assumptions!$C$135*Assumptions!$C$140+Hosting!$C$5*Assumptions!$C$140+MAX(0,ROUNDUP(B50/Assumptions!$C$141,0)-1)*Hosting!$C$5))))+Assumptions!$C$159*(Assumptions!$C$160+MAX(0,B50*Assumptions!$C$163-Assumptions!$C$161)*Assumptions!$C$162)+Assumptions!$C$164*Assumptions!$C$165+B50*(Assumptions!$C$168+Assumptions!$C$169) | L50: =C50*Tiers!$B$28 | M50: =G50+I50-J50-K50-L50 | N50: =IF(G50+I50>0,M50/(G50+I50),0) | O50: =O49+G50+I50
A51: 11 | B51: =MAX(Assumptions!$C$17,ROUND(Assumptions!$C$12*Assumptions!$C$14*(A51/24)^Assumptions!$C$16,0)) | C51: =MAX(0,B51-B50+ROUND(Assumptions!$C$18*B50,0)) | D51: =B51*Assumptions!$C$21 | E51: =B51*Tiers!$B$24 | F51: =B51*Tiers!$B$25 | G51: =D51+E51+F51 | H51: =G51*12 | I51: =C51*Tiers!$B$27 | J51: =B51*Tiers!$B$26 | K51: =IF(Assumptions!$C$155=1,(Assumptions!$C$135*Assumptions!$C$140+Hosting!$C$5*Assumptions!$C$140+MAX(0,ROUNDUP(B51/Assumptions!$C$141,0)-1)*Hosting!$C$5),IF(Assumptions!$C$155=2,(MAX(Assumptions!$C$145,ROUNDUP(B51/Assumptions!$C$146,0))*Assumptions!$C$144+B51*Hosting!$C$6),IF(B51>=Assumptions!$C$156,(MAX(Assumptions!$C$145,ROUNDUP(B51/Assumptions!$C$146,0))*Assumptions!$C$144+B51*Hosting!$C$6),(Assumptions!$C$135*Assumptions!$C$140+Hosting!$C$5*Assumptions!$C$140+MAX(0,ROUNDUP(B51/Assumptions!$C$141,0)-1)*Hosting!$C$5))))+Assumptions!$C$159*(Assumptions!$C$160+MAX(0,B51*Assumptions!$C$163-Assumptions!$C$161)*Assumptions!$C$162)+Assumptions!$C$164*Assumptions!$C$165+B51*(Assumptions!$C$168+Assumptions!$C$169) | L51: =C51*Tiers!$B$28 | M51: =G51+I51-J51-K51-L51 | N51: =IF(G51+I51>0,M51/(G51+I51),0) | O51: =O50+G51+I51
A52: 12 | B52: =MAX(Assumptions!$C$17,ROUND(Assumptions!$C$12*Assumptions!$C$14*(A52/24)^Assumptions!$C$16,0)) | C52: =MAX(0,B52-B51+ROUND(Assumptions!$C$18*B51,0)) | D52: =B52*Assumptions!$C$21 | E52: =B52*Tiers!$B$24 | F52: =B52*Tiers!$B$25 | G52: =D52+E52+F52 | H52: =G52*12 | I52: =C52*Tiers!$B$27 | J52: =B52*Tiers!$B$26 | K52: =IF(Assumptions!$C$155=1,(Assumptions!$C$135*Assumptions!$C$140+Hosting!$C$5*Assumptions!$C$140+MAX(0,ROUNDUP(B52/Assumptions!$C$141,0)-1)*Hosting!$C$5),IF(Assumptions!$C$155=2,(MAX(Assumptions!$C$145,ROUNDUP(B52/Assumptions!$C$146,0))*Assumptions!$C$144+B52*Hosting!$C$6),IF(B52>=Assumptions!$C$156,(MAX(Assumptions!$C$145,ROUNDUP(B52/Assumptions!$C$146,0))*Assumptions!$C$144+B52*Hosting!$C$6),(Assumptions!$C$135*Assumptions!$C$140+Hosting!$C$5*Assumptions!$C$140+MAX(0,ROUNDUP(B52/Assumptions!$C$141,0)-1)*Hosting!$C$5))))+Assumptions!$C$159*(Assumptions!$C$160+MAX(0,B52*Assumptions!$C$163-Assumptions!$C$161)*Assumptions!$C$162)+Assumptions!$C$164*Assumptions!$C$165+B52*(Assumptions!$C$168+Assumptions!$C$169) | L52: =C52*Tiers!$B$28 | M52: =G52+I52-J52-K52-L52 | N52: =IF(G52+I52>0,M52/(G52+I52),0) | O52: =O51+G52+I52
A53: 13 | B53: =MAX(Assumptions!$C$17,ROUND(Assumptions!$C$12*Assumptions!$C$14*(A53/24)^Assumptions!$C$16,0)) | C53: =MAX(0,B53-B52+ROUND(Assumptions!$C$18*B52,0)) | D53: =B53*Assumptions!$C$21 | E53: =B53*Tiers!$B$24 | F53: =B53*Tiers!$B$25 | G53: =D53+E53+F53 | H53: =G53*12 | I53: =C53*Tiers!$B$27 | J53: =B53*Tiers!$B$26 | K53: =IF(Assumptions!$C$155=1,(Assumptions!$C$135*Assumptions!$C$140+Hosting!$C$5*Assumptions!$C$140+MAX(0,ROUNDUP(B53/Assumptions!$C$141,0)-1)*Hosting!$C$5),IF(Assumptions!$C$155=2,(MAX(Assumptions!$C$145,ROUNDUP(B53/Assumptions!$C$146,0))*Assumptions!$C$144+B53*Hosting!$C$6),IF(B53>=Assumptions!$C$156,(MAX(Assumptions!$C$145,ROUNDUP(B53/Assumptions!$C$146,0))*Assumptions!$C$144+B53*Hosting!$C$6),(Assumptions!$C$135*Assumptions!$C$140+Hosting!$C$5*Assumptions!$C$140+MAX(0,ROUNDUP(B53/Assumptions!$C$141,0)-1)*Hosting!$C$5))))+Assumptions!$C$159*(Assumptions!$C$160+MAX(0,B53*Assumptions!$C$163-Assumptions!$C$161)*Assumptions!$C$162)+Assumptions!$C$164*Assumptions!$C$165+B53*(Assumptions!$C$168+Assumptions!$C$169) | L53: =C53*Tiers!$B$28 | M53: =G53+I53-J53-K53-L53 | N53: =IF(G53+I53>0,M53/(G53+I53),0) | O53: =O52+G53+I53
... A64: 24 | B64: =MAX(Assumptions!$C$17,ROUND(Assumptions!$C$12*Assumptions!$C$14*(A64/24)^Assumptions!$C$16,0)) | C64: =MAX(0,B64-B63+ROUND(Assumptions!$C$18*B63,0)) | D64: =B64*Assumptions!$C$21 | E64: =B64*Tiers!$B$24 | F64: =B64*Tiers!$B$25 | G64: =D64+E64+F64 | H64: =G64*12 | I64: =C64*Tiers!$B$27 | J64: =B64*Tiers!$B$26 | K64: =IF(Assumptions!$C$155=1,(Assumptions!$C$135*Assumptions!$C$140+Hosting!$C$5*Assumptions!$C$140+MAX(0,ROUNDUP(B64/Assumptions!$C$141,0)-1)*Hosting!$C$5),IF(Assumptions!$C$155=2,(MAX(Assumptions!$C$145,ROUNDUP(B64/Assumptions!$C$146,0))*Assumptions!$C$144+B64*Hosting!$C$6),IF(B64>=Assumptions!$C$156,(MAX(Assumptions!$C$145,ROUNDUP(B64/Assumptions!$C$146,0))*Assumptions!$C$144+B64*Hosting!$C$6),(Assumptions!$C$135*Assumptions!$C$140+Hosting!$C$5*Assumptions!$C$140+MAX(0,ROUNDUP(B64/Assumptions!$C$141,0)-1)*Hosting!$C$5))))+Assumptions!$C$159*(Assumptions!$C$160+MAX(0,B64*Assumptions!$C$163-Assumptions!$C$161)*Assumptions!$C$162)+Assumptions!$C$164*Assumptions!$C$165+B64*(Assumptions!$C$168+Assumptions!$C$169) | L64: =C64*Tiers!$B$28 | M64: =G64+I64-J64-K64-L64 | N64: =IF(G64+I64>0,M64/(G64+I64),0) | O64: =O63+G64+I64
A67: High scenario
A68: Month | B68: Active tenants | C68: New tenants | D68: Platform MRR | E68: Add-on MRR | F68: Overage and resale MRR | G68: Total MRR | H68: ARR run rate | I68: One-time fees | J68: Cost: usage | K68: Cost: hosting, sites and lead lines | L68: Cost: one-time | M68: Gross profit | N68: Gross margin | O68: Cumulative revenue
A69: 1 | B69: =MAX(Assumptions!$C$17,ROUND(Assumptions!$C$12*Assumptions!$C$15*(A69/24)^Assumptions!$C$16,0)) | C69: =MAX(0,B69-Assumptions!$C$17+ROUND(Assumptions!$C$18*Assumptions!$C$17,0)) | D69: =B69*Assumptions!$C$21 | E69: =B69*Tiers!$B$24 | F69: =B69*Tiers!$B$25 | G69: =D69+E69+F69 | H69: =G69*12 | I69: =C69*Tiers!$B$27 | J69: =B69*Tiers!$B$26 | K69: =IF(Assumptions!$C$155=1,(Assumptions!$C$135*Assumptions!$C$140+Hosting!$C$5*Assumptions!$C$140+MAX(0,ROUNDUP(B69/Assumptions!$C$141,0)-1)*Hosting!$C$5),IF(Assumptions!$C$155=2,(MAX(Assumptions!$C$145,ROUNDUP(B69/Assumptions!$C$146,0))*Assumptions!$C$144+B69*Hosting!$C$6),IF(B69>=Assumptions!$C$156,(MAX(Assumptions!$C$145,ROUNDUP(B69/Assumptions!$C$146,0))*Assumptions!$C$144+B69*Hosting!$C$6),(Assumptions!$C$135*Assumptions!$C$140+Hosting!$C$5*Assumptions!$C$140+MAX(0,ROUNDUP(B69/Assumptions!$C$141,0)-1)*Hosting!$C$5))))+Assumptions!$C$159*(Assumptions!$C$160+MAX(0,B69*Assumptions!$C$163-Assumptions!$C$161)*Assumptions!$C$162)+Assumptions!$C$164*Assumptions!$C$165+B69*(Assumptions!$C$168+Assumptions!$C$169) | L69: =C69*Tiers!$B$28 | M69: =G69+I69-J69-K69-L69 | N69: =IF(G69+I69>0,M69/(G69+I69),0) | O69: =G69+I69
A70: 2 | B70: =MAX(Assumptions!$C$17,ROUND(Assumptions!$C$12*Assumptions!$C$15*(A70/24)^Assumptions!$C$16,0)) | C70: =MAX(0,B70-B69+ROUND(Assumptions!$C$18*B69,0)) | D70: =B70*Assumptions!$C$21 | E70: =B70*Tiers!$B$24 | F70: =B70*Tiers!$B$25 | G70: =D70+E70+F70 | H70: =G70*12 | I70: =C70*Tiers!$B$27 | J70: =B70*Tiers!$B$26 | K70: =IF(Assumptions!$C$155=1,(Assumptions!$C$135*Assumptions!$C$140+Hosting!$C$5*Assumptions!$C$140+MAX(0,ROUNDUP(B70/Assumptions!$C$141,0)-1)*Hosting!$C$5),IF(Assumptions!$C$155=2,(MAX(Assumptions!$C$145,ROUNDUP(B70/Assumptions!$C$146,0))*Assumptions!$C$144+B70*Hosting!$C$6),IF(B70>=Assumptions!$C$156,(MAX(Assumptions!$C$145,ROUNDUP(B70/Assumptions!$C$146,0))*Assumptions!$C$144+B70*Hosting!$C$6),(Assumptions!$C$135*Assumptions!$C$140+Hosting!$C$5*Assumptions!$C$140+MAX(0,ROUNDUP(B70/Assumptions!$C$141,0)-1)*Hosting!$C$5))))+Assumptions!$C$159*(Assumptions!$C$160+MAX(0,B70*Assumptions!$C$163-Assumptions!$C$161)*Assumptions!$C$162)+Assumptions!$C$164*Assumptions!$C$165+B70*(Assumptions!$C$168+Assumptions!$C$169) | L70: =C70*Tiers!$B$28 | M70: =G70+I70-J70-K70-L70 | N70: =IF(G70+I70>0,M70/(G70+I70),0) | O70: =O69+G70+I70
A71: 3 | B71: =MAX(Assumptions!$C$17,ROUND(Assumptions!$C$12*Assumptions!$C$15*(A71/24)^Assumptions!$C$16,0)) | C71: =MAX(0,B71-B70+ROUND(Assumptions!$C$18*B70,0)) | D71: =B71*Assumptions!$C$21 | E71: =B71*Tiers!$B$24 | F71: =B71*Tiers!$B$25 | G71: =D71+E71+F71 | H71: =G71*12 | I71: =C71*Tiers!$B$27 | J71: =B71*Tiers!$B$26 | K71: =IF(Assumptions!$C$155=1,(Assumptions!$C$135*Assumptions!$C$140+Hosting!$C$5*Assumptions!$C$140+MAX(0,ROUNDUP(B71/Assumptions!$C$141,0)-1)*Hosting!$C$5),IF(Assumptions!$C$155=2,(MAX(Assumptions!$C$145,ROUNDUP(B71/Assumptions!$C$146,0))*Assumptions!$C$144+B71*Hosting!$C$6),IF(B71>=Assumptions!$C$156,(MAX(Assumptions!$C$145,ROUNDUP(B71/Assumptions!$C$146,0))*Assumptions!$C$144+B71*Hosting!$C$6),(Assumptions!$C$135*Assumptions!$C$140+Hosting!$C$5*Assumptions!$C$140+MAX(0,ROUNDUP(B71/Assumptions!$C$141,0)-1)*Hosting!$C$5))))+Assumptions!$C$159*(Assumptions!$C$160+MAX(0,B71*Assumptions!$C$163-Assumptions!$C$161)*Assumptions!$C$162)+Assumptions!$C$164*Assumptions!$C$165+B71*(Assumptions!$C$168+Assumptions!$C$169) | L71: =C71*Tiers!$B$28 | M71: =G71+I71-J71-K71-L71 | N71: =IF(G71+I71>0,M71/(G71+I71),0) | O71: =O70+G71+I71
A72: 4 | B72: =MAX(Assumptions!$C$17,ROUND(Assumptions!$C$12*Assumptions!$C$15*(A72/24)^Assumptions!$C$16,0)) | C72: =MAX(0,B72-B71+ROUND(Assumptions!$C$18*B71,0)) | D72: =B72*Assumptions!$C$21 | E72: =B72*Tiers!$B$24 | F72: =B72*Tiers!$B$25 | G72: =D72+E72+F72 | H72: =G72*12 | I72: =C72*Tiers!$B$27 | J72: =B72*Tiers!$B$26 | K72: =IF(Assumptions!$C$155=1,(Assumptions!$C$135*Assumptions!$C$140+Hosting!$C$5*Assumptions!$C$140+MAX(0,ROUNDUP(B72/Assumptions!$C$141,0)-1)*Hosting!$C$5),IF(Assumptions!$C$155=2,(MAX(Assumptions!$C$145,ROUNDUP(B72/Assumptions!$C$146,0))*Assumptions!$C$144+B72*Hosting!$C$6),IF(B72>=Assumptions!$C$156,(MAX(Assumptions!$C$145,ROUNDUP(B72/Assumptions!$C$146,0))*Assumptions!$C$144+B72*Hosting!$C$6),(Assumptions!$C$135*Assumptions!$C$140+Hosting!$C$5*Assumptions!$C$140+MAX(0,ROUNDUP(B72/Assumptions!$C$141,0)-1)*Hosting!$C$5))))+Assumptions!$C$159*(Assumptions!$C$160+MAX(0,B72*Assumptions!$C$163-Assumptions!$C$161)*Assumptions!$C$162)+Assumptions!$C$164*Assumptions!$C$165+B72*(Assumptions!$C$168+Assumptions!$C$169) | L72: =C72*Tiers!$B$28 | M72: =G72+I72-J72-K72-L72 | N72: =IF(G72+I72>0,M72/(G72+I72),0) | O72: =O71+G72+I72
A73: 5 | B73: =MAX(Assumptions!$C$17,ROUND(Assumptions!$C$12*Assumptions!$C$15*(A73/24)^Assumptions!$C$16,0)) | C73: =MAX(0,B73-B72+ROUND(Assumptions!$C$18*B72,0)) | D73: =B73*Assumptions!$C$21 | E73: =B73*Tiers!$B$24 | F73: =B73*Tiers!$B$25 | G73: =D73+E73+F73 | H73: =G73*12 | I73: =C73*Tiers!$B$27 | J73: =B73*Tiers!$B$26 | K73: =IF(Assumptions!$C$155=1,(Assumptions!$C$135*Assumptions!$C$140+Hosting!$C$5*Assumptions!$C$140+MAX(0,ROUNDUP(B73/Assumptions!$C$141,0)-1)*Hosting!$C$5),IF(Assumptions!$C$155=2,(MAX(Assumptions!$C$145,ROUNDUP(B73/Assumptions!$C$146,0))*Assumptions!$C$144+B73*Hosting!$C$6),IF(B73>=Assumptions!$C$156,(MAX(Assumptions!$C$145,ROUNDUP(B73/Assumptions!$C$146,0))*Assumptions!$C$144+B73*Hosting!$C$6),(Assumptions!$C$135*Assumptions!$C$140+Hosting!$C$5*Assumptions!$C$140+MAX(0,ROUNDUP(B73/Assumptions!$C$141,0)-1)*Hosting!$C$5))))+Assumptions!$C$159*(Assumptions!$C$160+MAX(0,B73*Assumptions!$C$163-Assumptions!$C$161)*Assumptions!$C$162)+Assumptions!$C$164*Assumptions!$C$165+B73*(Assumptions!$C$168+Assumptions!$C$169) | L73: =C73*Tiers!$B$28 | M73: =G73+I73-J73-K73-L73 | N73: =IF(G73+I73>0,M73/(G73+I73),0) | O73: =O72+G73+I73
A74: 6 | B74: =MAX(Assumptions!$C$17,ROUND(Assumptions!$C$12*Assumptions!$C$15*(A74/24)^Assumptions!$C$16,0)) | C74: =MAX(0,B74-B73+ROUND(Assumptions!$C$18*B73,0)) | D74: =B74*Assumptions!$C$21 | E74: =B74*Tiers!$B$24 | F74: =B74*Tiers!$B$25 | G74: =D74+E74+F74 | H74: =G74*12 | I74: =C74*Tiers!$B$27 | J74: =B74*Tiers!$B$26 | K74: =IF(Assumptions!$C$155=1,(Assumptions!$C$135*Assumptions!$C$140+Hosting!$C$5*Assumptions!$C$140+MAX(0,ROUNDUP(B74/Assumptions!$C$141,0)-1)*Hosting!$C$5),IF(Assumptions!$C$155=2,(MAX(Assumptions!$C$145,ROUNDUP(B74/Assumptions!$C$146,0))*Assumptions!$C$144+B74*Hosting!$C$6),IF(B74>=Assumptions!$C$156,(MAX(Assumptions!$C$145,ROUNDUP(B74/Assumptions!$C$146,0))*Assumptions!$C$144+B74*Hosting!$C$6),(Assumptions!$C$135*Assumptions!$C$140+Hosting!$C$5*Assumptions!$C$140+MAX(0,ROUNDUP(B74/Assumptions!$C$141,0)-1)*Hosting!$C$5))))+Assumptions!$C$159*(Assumptions!$C$160+MAX(0,B74*Assumptions!$C$163-Assumptions!$C$161)*Assumptions!$C$162)+Assumptions!$C$164*Assumptions!$C$165+B74*(Assumptions!$C$168+Assumptions!$C$169) | L74: =C74*Tiers!$B$28 | M74: =G74+I74-J74-K74-L74 | N74: =IF(G74+I74>0,M74/(G74+I74),0) | O74: =O73+G74+I74
A75: 7 | B75: =MAX(Assumptions!$C$17,ROUND(Assumptions!$C$12*Assumptions!$C$15*(A75/24)^Assumptions!$C$16,0)) | C75: =MAX(0,B75-B74+ROUND(Assumptions!$C$18*B74,0)) | D75: =B75*Assumptions!$C$21 | E75: =B75*Tiers!$B$24 | F75: =B75*Tiers!$B$25 | G75: =D75+E75+F75 | H75: =G75*12 | I75: =C75*Tiers!$B$27 | J75: =B75*Tiers!$B$26 | K75: =IF(Assumptions!$C$155=1,(Assumptions!$C$135*Assumptions!$C$140+Hosting!$C$5*Assumptions!$C$140+MAX(0,ROUNDUP(B75/Assumptions!$C$141,0)-1)*Hosting!$C$5),IF(Assumptions!$C$155=2,(MAX(Assumptions!$C$145,ROUNDUP(B75/Assumptions!$C$146,0))*Assumptions!$C$144+B75*Hosting!$C$6),IF(B75>=Assumptions!$C$156,(MAX(Assumptions!$C$145,ROUNDUP(B75/Assumptions!$C$146,0))*Assumptions!$C$144+B75*Hosting!$C$6),(Assumptions!$C$135*Assumptions!$C$140+Hosting!$C$5*Assumptions!$C$140+MAX(0,ROUNDUP(B75/Assumptions!$C$141,0)-1)*Hosting!$C$5))))+Assumptions!$C$159*(Assumptions!$C$160+MAX(0,B75*Assumptions!$C$163-Assumptions!$C$161)*Assumptions!$C$162)+Assumptions!$C$164*Assumptions!$C$165+B75*(Assumptions!$C$168+Assumptions!$C$169) | L75: =C75*Tiers!$B$28 | M75: =G75+I75-J75-K75-L75 | N75: =IF(G75+I75>0,M75/(G75+I75),0) | O75: =O74+G75+I75
A76: 8 | B76: =MAX(Assumptions!$C$17,ROUND(Assumptions!$C$12*Assumptions!$C$15*(A76/24)^Assumptions!$C$16,0)) | C76: =MAX(0,B76-B75+ROUND(Assumptions!$C$18*B75,0)) | D76: =B76*Assumptions!$C$21 | E76: =B76*Tiers!$B$24 | F76: =B76*Tiers!$B$25 | G76: =D76+E76+F76 | H76: =G76*12 | I76: =C76*Tiers!$B$27 | J76: =B76*Tiers!$B$26 | K76: =IF(Assumptions!$C$155=1,(Assumptions!$C$135*Assumptions!$C$140+Hosting!$C$5*Assumptions!$C$140+MAX(0,ROUNDUP(B76/Assumptions!$C$141,0)-1)*Hosting!$C$5),IF(Assumptions!$C$155=2,(MAX(Assumptions!$C$145,ROUNDUP(B76/Assumptions!$C$146,0))*Assumptions!$C$144+B76*Hosting!$C$6),IF(B76>=Assumptions!$C$156,(MAX(Assumptions!$C$145,ROUNDUP(B76/Assumptions!$C$146,0))*Assumptions!$C$144+B76*Hosting!$C$6),(Assumptions!$C$135*Assumptions!$C$140+Hosting!$C$5*Assumptions!$C$140+MAX(0,ROUNDUP(B76/Assumptions!$C$141,0)-1)*Hosting!$C$5))))+Assumptions!$C$159*(Assumptions!$C$160+MAX(0,B76*Assumptions!$C$163-Assumptions!$C$161)*Assumptions!$C$162)+Assumptions!$C$164*Assumptions!$C$165+B76*(Assumptions!$C$168+Assumptions!$C$169) | L76: =C76*Tiers!$B$28 | M76: =G76+I76-J76-K76-L76 | N76: =IF(G76+I76>0,M76/(G76+I76),0) | O76: =O75+G76+I76
A77: 9 | B77: =MAX(Assumptions!$C$17,ROUND(Assumptions!$C$12*Assumptions!$C$15*(A77/24)^Assumptions!$C$16,0)) | C77: =MAX(0,B77-B76+ROUND(Assumptions!$C$18*B76,0)) | D77: =B77*Assumptions!$C$21 | E77: =B77*Tiers!$B$24 | F77: =B77*Tiers!$B$25 | G77: =D77+E77+F77 | H77: =G77*12 | I77: =C77*Tiers!$B$27 | J77: =B77*Tiers!$B$26 | K77: =IF(Assumptions!$C$155=1,(Assumptions!$C$135*Assumptions!$C$140+Hosting!$C$5*Assumptions!$C$140+MAX(0,ROUNDUP(B77/Assumptions!$C$141,0)-1)*Hosting!$C$5),IF(Assumptions!$C$155=2,(MAX(Assumptions!$C$145,ROUNDUP(B77/Assumptions!$C$146,0))*Assumptions!$C$144+B77*Hosting!$C$6),IF(B77>=Assumptions!$C$156,(MAX(Assumptions!$C$145,ROUNDUP(B77/Assumptions!$C$146,0))*Assumptions!$C$144+B77*Hosting!$C$6),(Assumptions!$C$135*Assumptions!$C$140+Hosting!$C$5*Assumptions!$C$140+MAX(0,ROUNDUP(B77/Assumptions!$C$141,0)-1)*Hosting!$C$5))))+Assumptions!$C$159*(Assumptions!$C$160+MAX(0,B77*Assumptions!$C$163-Assumptions!$C$161)*Assumptions!$C$162)+Assumptions!$C$164*Assumptions!$C$165+B77*(Assumptions!$C$168+Assumptions!$C$169) | L77: =C77*Tiers!$B$28 | M77: =G77+I77-J77-K77-L77 | N77: =IF(G77+I77>0,M77/(G77+I77),0) | O77: =O76+G77+I77
A78: 10 | B78: =MAX(Assumptions!$C$17,ROUND(Assumptions!$C$12*Assumptions!$C$15*(A78/24)^Assumptions!$C$16,0)) | C78: =MAX(0,B78-B77+ROUND(Assumptions!$C$18*B77,0)) | D78: =B78*Assumptions!$C$21 | E78: =B78*Tiers!$B$24 | F78: =B78*Tiers!$B$25 | G78: =D78+E78+F78 | H78: =G78*12 | I78: =C78*Tiers!$B$27 | J78: =B78*Tiers!$B$26 | K78: =IF(Assumptions!$C$155=1,(Assumptions!$C$135*Assumptions!$C$140+Hosting!$C$5*Assumptions!$C$140+MAX(0,ROUNDUP(B78/Assumptions!$C$141,0)-1)*Hosting!$C$5),IF(Assumptions!$C$155=2,(MAX(Assumptions!$C$145,ROUNDUP(B78/Assumptions!$C$146,0))*Assumptions!$C$144+B78*Hosting!$C$6),IF(B78>=Assumptions!$C$156,(MAX(Assumptions!$C$145,ROUNDUP(B78/Assumptions!$C$146,0))*Assumptions!$C$144+B78*Hosting!$C$6),(Assumptions!$C$135*Assumptions!$C$140+Hosting!$C$5*Assumptions!$C$140+MAX(0,ROUNDUP(B78/Assumptions!$C$141,0)-1)*Hosting!$C$5))))+Assumptions!$C$159*(Assumptions!$C$160+MAX(0,B78*Assumptions!$C$163-Assumptions!$C$161)*Assumptions!$C$162)+Assumptions!$C$164*Assumptions!$C$165+B78*(Assumptions!$C$168+Assumptions!$C$169) | L78: =C78*Tiers!$B$28 | M78: =G78+I78-J78-K78-L78 | N78: =IF(G78+I78>0,M78/(G78+I78),0) | O78: =O77+G78+I78
A79: 11 | B79: =MAX(Assumptions!$C$17,ROUND(Assumptions!$C$12*Assumptions!$C$15*(A79/24)^Assumptions!$C$16,0)) | C79: =MAX(0,B79-B78+ROUND(Assumptions!$C$18*B78,0)) | D79: =B79*Assumptions!$C$21 | E79: =B79*Tiers!$B$24 | F79: =B79*Tiers!$B$25 | G79: =D79+E79+F79 | H79: =G79*12 | I79: =C79*Tiers!$B$27 | J79: =B79*Tiers!$B$26 | K79: =IF(Assumptions!$C$155=1,(Assumptions!$C$135*Assumptions!$C$140+Hosting!$C$5*Assumptions!$C$140+MAX(0,ROUNDUP(B79/Assumptions!$C$141,0)-1)*Hosting!$C$5),IF(Assumptions!$C$155=2,(MAX(Assumptions!$C$145,ROUNDUP(B79/Assumptions!$C$146,0))*Assumptions!$C$144+B79*Hosting!$C$6),IF(B79>=Assumptions!$C$156,(MAX(Assumptions!$C$145,ROUNDUP(B79/Assumptions!$C$146,0))*Assumptions!$C$144+B79*Hosting!$C$6),(Assumptions!$C$135*Assumptions!$C$140+Hosting!$C$5*Assumptions!$C$140+MAX(0,ROUNDUP(B79/Assumptions!$C$141,0)-1)*Hosting!$C$5))))+Assumptions!$C$159*(Assumptions!$C$160+MAX(0,B79*Assumptions!$C$163-Assumptions!$C$161)*Assumptions!$C$162)+Assumptions!$C$164*Assumptions!$C$165+B79*(Assumptions!$C$168+Assumptions!$C$169) | L79: =C79*Tiers!$B$28 | M79: =G79+I79-J79-K79-L79 | N79: =IF(G79+I79>0,M79/(G79+I79),0) | O79: =O78+G79+I79
A80: 12 | B80: =MAX(Assumptions!$C$17,ROUND(Assumptions!$C$12*Assumptions!$C$15*(A80/24)^Assumptions!$C$16,0)) | C80: =MAX(0,B80-B79+ROUND(Assumptions!$C$18*B79,0)) | D80: =B80*Assumptions!$C$21 | E80: =B80*Tiers!$B$24 | F80: =B80*Tiers!$B$25 | G80: =D80+E80+F80 | H80: =G80*12 | I80: =C80*Tiers!$B$27 | J80: =B80*Tiers!$B$26 | K80: =IF(Assumptions!$C$155=1,(Assumptions!$C$135*Assumptions!$C$140+Hosting!$C$5*Assumptions!$C$140+MAX(0,ROUNDUP(B80/Assumptions!$C$141,0)-1)*Hosting!$C$5),IF(Assumptions!$C$155=2,(MAX(Assumptions!$C$145,ROUNDUP(B80/Assumptions!$C$146,0))*Assumptions!$C$144+B80*Hosting!$C$6),IF(B80>=Assumptions!$C$156,(MAX(Assumptions!$C$145,ROUNDUP(B80/Assumptions!$C$146,0))*Assumptions!$C$144+B80*Hosting!$C$6),(Assumptions!$C$135*Assumptions!$C$140+Hosting!$C$5*Assumptions!$C$140+MAX(0,ROUNDUP(B80/Assumptions!$C$141,0)-1)*Hosting!$C$5))))+Assumptions!$C$159*(Assumptions!$C$160+MAX(0,B80*Assumptions!$C$163-Assumptions!$C$161)*Assumptions!$C$162)+Assumptions!$C$164*Assumptions!$C$165+B80*(Assumptions!$C$168+Assumptions!$C$169) | L80: =C80*Tiers!$B$28 | M80: =G80+I80-J80-K80-L80 | N80: =IF(G80+I80>0,M80/(G80+I80),0) | O80: =O79+G80+I80
A81: 13 | B81: =MAX(Assumptions!$C$17,ROUND(Assumptions!$C$12*Assumptions!$C$15*(A81/24)^Assumptions!$C$16,0)) | C81: =MAX(0,B81-B80+ROUND(Assumptions!$C$18*B80,0)) | D81: =B81*Assumptions!$C$21 | E81: =B81*Tiers!$B$24 | F81: =B81*Tiers!$B$25 | G81: =D81+E81+F81 | H81: =G81*12 | I81: =C81*Tiers!$B$27 | J81: =B81*Tiers!$B$26 | K81: =IF(Assumptions!$C$155=1,(Assumptions!$C$135*Assumptions!$C$140+Hosting!$C$5*Assumptions!$C$140+MAX(0,ROUNDUP(B81/Assumptions!$C$141,0)-1)*Hosting!$C$5),IF(Assumptions!$C$155=2,(MAX(Assumptions!$C$145,ROUNDUP(B81/Assumptions!$C$146,0))*Assumptions!$C$144+B81*Hosting!$C$6),IF(B81>=Assumptions!$C$156,(MAX(Assumptions!$C$145,ROUNDUP(B81/Assumptions!$C$146,0))*Assumptions!$C$144+B81*Hosting!$C$6),(Assumptions!$C$135*Assumptions!$C$140+Hosting!$C$5*Assumptions!$C$140+MAX(0,ROUNDUP(B81/Assumptions!$C$141,0)-1)*Hosting!$C$5))))+Assumptions!$C$159*(Assumptions!$C$160+MAX(0,B81*Assumptions!$C$163-Assumptions!$C$161)*Assumptions!$C$162)+Assumptions!$C$164*Assumptions!$C$165+B81*(Assumptions!$C$168+Assumptions!$C$169) | L81: =C81*Tiers!$B$28 | M81: =G81+I81-J81-K81-L81 | N81: =IF(G81+I81>0,M81/(G81+I81),0) | O81: =O80+G81+I81
... A92: 24 | B92: =MAX(Assumptions!$C$17,ROUND(Assumptions!$C$12*Assumptions!$C$15*(A92/24)^Assumptions!$C$16,0)) | C92: =MAX(0,B92-B91+ROUND(Assumptions!$C$18*B91,0)) | D92: =B92*Assumptions!$C$21 | E92: =B92*Tiers!$B$24 | F92: =B92*Tiers!$B$25 | G92: =D92+E92+F92 | H92: =G92*12 | I92: =C92*Tiers!$B$27 | J92: =B92*Tiers!$B$26 | K92: =IF(Assumptions!$C$155=1,(Assumptions!$C$135*Assumptions!$C$140+Hosting!$C$5*Assumptions!$C$140+MAX(0,ROUNDUP(B92/Assumptions!$C$141,0)-1)*Hosting!$C$5),IF(Assumptions!$C$155=2,(MAX(Assumptions!$C$145,ROUNDUP(B92/Assumptions!$C$146,0))*Assumptions!$C$144+B92*Hosting!$C$6),IF(B92>=Assumptions!$C$156,(MAX(Assumptions!$C$145,ROUNDUP(B92/Assumptions!$C$146,0))*Assumptions!$C$144+B92*Hosting!$C$6),(Assumptions!$C$135*Assumptions!$C$140+Hosting!$C$5*Assumptions!$C$140+MAX(0,ROUNDUP(B92/Assumptions!$C$141,0)-1)*Hosting!$C$5))))+Assumptions!$C$159*(Assumptions!$C$160+MAX(0,B92*Assumptions!$C$163-Assumptions!$C$161)*Assumptions!$C$162)+Assumptions!$C$164*Assumptions!$C$165+B92*(Assumptions!$C$168+Assumptions!$C$169) | L92: =C92*Tiers!$B$28 | M92: =G92+I92-J92-K92-L92 | N92: =IF(G92+I92>0,M92/(G92+I92),0) | O92: =O91+G92+I92

Sheet Sensitivity
A1: Sensitivity
A2: One driver changes at a time; everything else stays at base. Blue test values can be overwritten.
A4: Check: the formula used below, at base, against Tiers | B4: =(Assumptions!$C$21+Assumptions!$C$33*Assumptions!$C$41*(Assumptions!$C$22+Assumptions!$C$25*MAX(0,UnitEconomics!$D$12-Assumptions!$C$23)*UnitEconomics!$D$31)+Assumptions!$C$34*(Assumptions!$C$26+Assumptions!$C$25*MAX(0,UnitEconomics!$D$15-Assumptions!$C$27)*UnitEconomics!$D$39)+Assumptions!$C$35*Assumptions!$C$29+Assumptions!$C$36*Assumptions!$C$30+Assumptions!$C$37*(Assumptions!$C$116*Assumptions!$C$41+Assumptions!$C$123*Assumptions!$C$41*(1-Assumptions!$C$33))) | C4: =Tiers!$B$15 | D4: =(UnitEconomics!$D$71+Assumptions!$C$33*(Assumptions!$C$41*UnitEconomics!$D$12*UnitEconomics!$D$27+(Assumptions!$C$41*Assumptions!$C$42+Assumptions!$C$43)*Assumptions!$C$98)+Assumptions!$C$34*(UnitEconomics!$D$15*UnitEconomics!$D$38+UnitEconomics!$D$35+UnitEconomics!$D$36)+Assumptions!$C$35*UnitEconomics!$D$74+Assumptions!$C$36*UnitEconomics!$D$75) | E4: =Tiers!$B$18
A6: Phone minutes per dialer seat per month
A7: Phone minutes per dialer seat per month | B7: Revenue per tenant per month | C7: Cost per tenant per month | D7: Gross margin | E7: ARR at month 24, base scenario
A8: 600 | B8: =(Assumptions!$C$21+Assumptions!$C$33*Assumptions!$C$41*(Assumptions!$C$22+Assumptions!$C$25*MAX(0,$A8-Assumptions!$C$23)*UnitEconomics!$D$31)+Assumptions!$C$34*(Assumptions!$C$26+Assumptions!$C$25*MAX(0,UnitEconomics!$D$15-Assumptions!$C$27)*UnitEconomics!$D$39)+Assumptions!$C$35*Assumptions!$C$29+Assumptions!$C$36*Assumptions!$C$30+Assumptions!$C$37*(Assumptions!$C$116*Assumptions!$C$41+Assumptions!$C$123*Assumptions!$C$41*(1-Assumptions!$C$33))) | C8: =(UnitEconomics!$D$71+Assumptions!$C$33*(Assumptions!$C$41*$A8*UnitEconomics!$D$27+(Assumptions!$C$41*Assumptions!$C$42+Assumptions!$C$43)*Assumptions!$C$98)+Assumptions!$C$34*(UnitEconomics!$D$15*UnitEconomics!$D$38+UnitEconomics!$D$35+UnitEconomics!$D$36)+Assumptions!$C$35*UnitEconomics!$D$74+Assumptions!$C$36*UnitEconomics!$D$75) | D8: =IF(B8>0,(B8-C8)/B8,0) | E8: =Forecast!$F$6*B8*12
A9: 1000 | B9: =(Assumptions!$C$21+Assumptions!$C$33*Assumptions!$C$41*(Assumptions!$C$22+Assumptions!$C$25*MAX(0,$A9-Assumptions!$C$23)*UnitEconomics!$D$31)+Assumptions!$C$34*(Assumptions!$C$26+Assumptions!$C$25*MAX(0,UnitEconomics!$D$15-Assumptions!$C$27)*UnitEconomics!$D$39)+Assumptions!$C$35*Assumptions!$C$29+Assumptions!$C$36*Assumptions!$C$30+Assumptions!$C$37*(Assumptions!$C$116*Assumptions!$C$41+Assumptions!$C$123*Assumptions!$C$41*(1-Assumptions!$C$33))) | C9: =(UnitEconomics!$D$71+Assumptions!$C$33*(Assumptions!$C$41*$A9*UnitEconomics!$D$27+(Assumptions!$C$41*Assumptions!$C$42+Assumptions!$C$43)*Assumptions!$C$98)+Assumptions!$C$34*(UnitEconomics!$D$15*UnitEconomics!$D$38+UnitEconomics!$D$35+UnitEconomics!$D$36)+Assumptions!$C$35*UnitEconomics!$D$74+Assumptions!$C$36*UnitEconomics!$D$75) | D9: =IF(B9>0,(B9-C9)/B9,0) | E9: =Forecast!$F$6*B9*12
A10: 1200 | B10: =(Assumptions!$C$21+Assumptions!$C$33*Assumptions!$C$41*(Assumptions!$C$22+Assumptions!$C$25*MAX(0,$A10-Assumptions!$C$23)*UnitEconomics!$D$31)+Assumptions!$C$34*(Assumptions!$C$26+Assumptions!$C$25*MAX(0,UnitEconomics!$D$15-Assumptions!$C$27)*UnitEconomics!$D$39)+Assumptions!$C$35*Assumptions!$C$29+Assumptions!$C$36*Assumptions!$C$30+Assumptions!$C$37*(Assumptions!$C$116*Assumptions!$C$41+Assumptions!$C$123*Assumptions!$C$41*(1-Assumptions!$C$33))) | C10: =(UnitEconomics!$D$71+Assumptions!$C$33*(Assumptions!$C$41*$A10*UnitEconomics!$D$27+(Assumptions!$C$41*Assumptions!$C$42+Assumptions!$C$43)*Assumptions!$C$98)+Assumptions!$C$34*(UnitEconomics!$D$15*UnitEconomics!$D$38+UnitEconomics!$D$35+UnitEconomics!$D$36)+Assumptions!$C$35*UnitEconomics!$D$74+Assumptions!$C$36*UnitEconomics!$D$75) | D10: =IF(B10>0,(B10-C10)/B10,0) | E10: =Forecast!$F$6*B10*12
A11: 1500 | B11: =(Assumptions!$C$21+Assumptions!$C$33*Assumptions!$C$41*(Assumptions!$C$22+Assumptions!$C$25*MAX(0,$A11-Assumptions!$C$23)*UnitEconomics!$D$31)+Assumptions!$C$34*(Assumptions!$C$26+Assumptions!$C$25*MAX(0,UnitEconomics!$D$15-Assumptions!$C$27)*UnitEconomics!$D$39)+Assumptions!$C$35*Assumptions!$C$29+Assumptions!$C$36*Assumptions!$C$30+Assumptions!$C$37*(Assumptions!$C$116*Assumptions!$C$41+Assumptions!$C$123*Assumptions!$C$41*(1-Assumptions!$C$33))) | C11: =(UnitEconomics!$D$71+Assumptions!$C$33*(Assumptions!$C$41*$A11*UnitEconomics!$D$27+(Assumptions!$C$41*Assumptions!$C$42+Assumptions!$C$43)*Assumptions!$C$98)+Assumptions!$C$34*(UnitEconomics!$D$15*UnitEconomics!$D$38+UnitEconomics!$D$35+UnitEconomics!$D$36)+Assumptions!$C$35*UnitEconomics!$D$74+Assumptions!$C$36*UnitEconomics!$D$75) | D11: =IF(B11>0,(B11-C11)/B11,0) | E11: =Forecast!$F$6*B11*12
A12: 2000 | B12: =(Assumptions!$C$21+Assumptions!$C$33*Assumptions!$C$41*(Assumptions!$C$22+Assumptions!$C$25*MAX(0,$A12-Assumptions!$C$23)*UnitEconomics!$D$31)+Assumptions!$C$34*(Assumptions!$C$26+Assumptions!$C$25*MAX(0,UnitEconomics!$D$15-Assumptions!$C$27)*UnitEconomics!$D$39)+Assumptions!$C$35*Assumptions!$C$29+Assumptions!$C$36*Assumptions!$C$30+Assumptions!$C$37*(Assumptions!$C$116*Assumptions!$C$41+Assumptions!$C$123*Assumptions!$C$41*(1-Assumptions!$C$33))) | C12: =(UnitEconomics!$D$71+Assumptions!$C$33*(Assumptions!$C$41*$A12*UnitEconomics!$D$27+(Assumptions!$C$41*Assumptions!$C$42+Assumptions!$C$43)*Assumptions!$C$98)+Assumptions!$C$34*(UnitEconomics!$D$15*UnitEconomics!$D$38+UnitEconomics!$D$35+UnitEconomics!$D$36)+Assumptions!$C$35*UnitEconomics!$D$74+Assumptions!$C$36*UnitEconomics!$D$75) | D12: =IF(B12>0,(B12-C12)/B12,0) | E12: =Forecast!$F$6*B12*12
A13: 2500 | B13: =(Assumptions!$C$21+Assumptions!$C$33*Assumptions!$C$41*(Assumptions!$C$22+Assumptions!$C$25*MAX(0,$A13-Assumptions!$C$23)*UnitEconomics!$D$31)+Assumptions!$C$34*(Assumptions!$C$26+Assumptions!$C$25*MAX(0,UnitEconomics!$D$15-Assumptions!$C$27)*UnitEconomics!$D$39)+Assumptions!$C$35*Assumptions!$C$29+Assumptions!$C$36*Assumptions!$C$30+Assumptions!$C$37*(Assumptions!$C$116*Assumptions!$C$41+Assumptions!$C$123*Assumptions!$C$41*(1-Assumptions!$C$33))) | C13: =(UnitEconomics!$D$71+Assumptions!$C$33*(Assumptions!$C$41*$A13*UnitEconomics!$D$27+(Assumptions!$C$41*Assumptions!$C$42+Assumptions!$C$43)*Assumptions!$C$98)+Assumptions!$C$34*(UnitEconomics!$D$15*UnitEconomics!$D$38+UnitEconomics!$D$35+UnitEconomics!$D$36)+Assumptions!$C$35*UnitEconomics!$D$74+Assumptions!$C$36*UnitEconomics!$D$75) | D13: =IF(B13>0,(B13-C13)/B13,0) | E13: =Forecast!$F$6*B13*12
A14: 3000 | B14: =(Assumptions!$C$21+Assumptions!$C$33*Assumptions!$C$41*(Assumptions!$C$22+Assumptions!$C$25*MAX(0,$A14-Assumptions!$C$23)*UnitEconomics!$D$31)+Assumptions!$C$34*(Assumptions!$C$26+Assumptions!$C$25*MAX(0,UnitEconomics!$D$15-Assumptions!$C$27)*UnitEconomics!$D$39)+Assumptions!$C$35*Assumptions!$C$29+Assumptions!$C$36*Assumptions!$C$30+Assumptions!$C$37*(Assumptions!$C$116*Assumptions!$C$41+Assumptions!$C$123*Assumptions!$C$41*(1-Assumptions!$C$33))) | C14: =(UnitEconomics!$D$71+Assumptions!$C$33*(Assumptions!$C$41*$A14*UnitEconomics!$D$27+(Assumptions!$C$41*Assumptions!$C$42+Assumptions!$C$43)*Assumptions!$C$98)+Assumptions!$C$34*(UnitEconomics!$D$15*UnitEconomics!$D$38+UnitEconomics!$D$35+UnitEconomics!$D$36)+Assumptions!$C$35*UnitEconomics!$D$74+Assumptions!$C$36*UnitEconomics!$D$75) | D14: =IF(B14>0,(B14-C14)/B14,0) | E14: =Forecast!$F$6*B14*12
A15: 4000 | B15: =(Assumptions!$C$21+Assumptions!$C$33*Assumptions!$C$41*(Assumptions!$C$22+Assumptions!$C$25*MAX(0,$A15-Assumptions!$C$23)*UnitEconomics!$D$31)+Assumptions!$C$34*(Assumptions!$C$26+Assumptions!$C$25*MAX(0,UnitEconomics!$D$15-Assumptions!$C$27)*UnitEconomics!$D$39)+Assumptions!$C$35*Assumptions!$C$29+Assumptions!$C$36*Assumptions!$C$30+Assumptions!$C$37*(Assumptions!$C$116*Assumptions!$C$41+Assumptions!$C$123*Assumptions!$C$41*(1-Assumptions!$C$33))) | C15: =(UnitEconomics!$D$71+Assumptions!$C$33*(Assumptions!$C$41*$A15*UnitEconomics!$D$27+(Assumptions!$C$41*Assumptions!$C$42+Assumptions!$C$43)*Assumptions!$C$98)+Assumptions!$C$34*(UnitEconomics!$D$15*UnitEconomics!$D$38+UnitEconomics!$D$35+UnitEconomics!$D$36)+Assumptions!$C$35*UnitEconomics!$D$74+Assumptions!$C$36*UnitEconomics!$D$75) | D15: =IF(B15>0,(B15-C15)/B15,0) | E15: =Forecast!$F$6*B15*12
A17: Seats per tenant
A18: Seats per tenant | B18: Revenue per tenant per month | C18: Cost per tenant per month | D18: Gross margin | E18: ARR at month 24, base scenario
A19: 2 | B19: =(Assumptions!$C$21+Assumptions!$C$33*$A19*(Assumptions!$C$22+Assumptions!$C$25*MAX(0,UnitEconomics!$D$12-Assumptions!$C$23)*UnitEconomics!$D$31)+Assumptions!$C$34*(Assumptions!$C$26+Assumptions!$C$25*MAX(0,UnitEconomics!$D$15-Assumptions!$C$27)*UnitEconomics!$D$39)+Assumptions!$C$35*Assumptions!$C$29+Assumptions!$C$36*Assumptions!$C$30+Assumptions!$C$37*(Assumptions!$C$116*$A19+Assumptions!$C$123*$A19*(1-Assumptions!$C$33))) | C19: =(UnitEconomics!$D$71+Assumptions!$C$33*($A19*UnitEconomics!$D$12*UnitEconomics!$D$27+($A19*Assumptions!$C$42+Assumptions!$C$43)*Assumptions!$C$98)+Assumptions!$C$34*(UnitEconomics!$D$15*UnitEconomics!$D$38+UnitEconomics!$D$35+UnitEconomics!$D$36)+Assumptions!$C$35*UnitEconomics!$D$74+Assumptions!$C$36*UnitEconomics!$D$75) | D19: =IF(B19>0,(B19-C19)/B19,0) | E19: =Forecast!$F$6*B19*12
A20: 3 | B20: =(Assumptions!$C$21+Assumptions!$C$33*$A20*(Assumptions!$C$22+Assumptions!$C$25*MAX(0,UnitEconomics!$D$12-Assumptions!$C$23)*UnitEconomics!$D$31)+Assumptions!$C$34*(Assumptions!$C$26+Assumptions!$C$25*MAX(0,UnitEconomics!$D$15-Assumptions!$C$27)*UnitEconomics!$D$39)+Assumptions!$C$35*Assumptions!$C$29+Assumptions!$C$36*Assumptions!$C$30+Assumptions!$C$37*(Assumptions!$C$116*$A20+Assumptions!$C$123*$A20*(1-Assumptions!$C$33))) | C20: =(UnitEconomics!$D$71+Assumptions!$C$33*($A20*UnitEconomics!$D$12*UnitEconomics!$D$27+($A20*Assumptions!$C$42+Assumptions!$C$43)*Assumptions!$C$98)+Assumptions!$C$34*(UnitEconomics!$D$15*UnitEconomics!$D$38+UnitEconomics!$D$35+UnitEconomics!$D$36)+Assumptions!$C$35*UnitEconomics!$D$74+Assumptions!$C$36*UnitEconomics!$D$75) | D20: =IF(B20>0,(B20-C20)/B20,0) | E20: =Forecast!$F$6*B20*12
A21: 4 | B21: =(Assumptions!$C$21+Assumptions!$C$33*$A21*(Assumptions!$C$22+Assumptions!$C$25*MAX(0,UnitEconomics!$D$12-Assumptions!$C$23)*UnitEconomics!$D$31)+Assumptions!$C$34*(Assumptions!$C$26+Assumptions!$C$25*MAX(0,UnitEconomics!$D$15-Assumptions!$C$27)*UnitEconomics!$D$39)+Assumptions!$C$35*Assumptions!$C$29+Assumptions!$C$36*Assumptions!$C$30+Assumptions!$C$37*(Assumptions!$C$116*$A21+Assumptions!$C$123*$A21*(1-Assumptions!$C$33))) | C21: =(UnitEconomics!$D$71+Assumptions!$C$33*($A21*UnitEconomics!$D$12*UnitEconomics!$D$27+($A21*Assumptions!$C$42+Assumptions!$C$43)*Assumptions!$C$98)+Assumptions!$C$34*(UnitEconomics!$D$15*UnitEconomics!$D$38+UnitEconomics!$D$35+UnitEconomics!$D$36)+Assumptions!$C$35*UnitEconomics!$D$74+Assumptions!$C$36*UnitEconomics!$D$75) | D21: =IF(B21>0,(B21-C21)/B21,0) | E21: =Forecast!$F$6*B21*12
A22: 6 | B22: =(Assumptions!$C$21+Assumptions!$C$33*$A22*(Assumptions!$C$22+Assumptions!$C$25*MAX(0,UnitEconomics!$D$12-Assumptions!$C$23)*UnitEconomics!$D$31)+Assumptions!$C$34*(Assumptions!$C$26+Assumptions!$C$25*MAX(0,UnitEconomics!$D$15-Assumptions!$C$27)*UnitEconomics!$D$39)+Assumptions!$C$35*Assumptions!$C$29+Assumptions!$C$36*Assumptions!$C$30+Assumptions!$C$37*(Assumptions!$C$116*$A22+Assumptions!$C$123*$A22*(1-Assumptions!$C$33))) | C22: =(UnitEconomics!$D$71+Assumptions!$C$33*($A22*UnitEconomics!$D$12*UnitEconomics!$D$27+($A22*Assumptions!$C$42+Assumptions!$C$43)*Assumptions!$C$98)+Assumptions!$C$34*(UnitEconomics!$D$15*UnitEconomics!$D$38+UnitEconomics!$D$35+UnitEconomics!$D$36)+Assumptions!$C$35*UnitEconomics!$D$74+Assumptions!$C$36*UnitEconomics!$D$75) | D22: =IF(B22>0,(B22-C22)/B22,0) | E22: =Forecast!$F$6*B22*12
A23: 8 | B23: =(Assumptions!$C$21+Assumptions!$C$33*$A23*(Assumptions!$C$22+Assumptions!$C$25*MAX(0,UnitEconomics!$D$12-Assumptions!$C$23)*UnitEconomics!$D$31)+Assumptions!$C$34*(Assumptions!$C$26+Assumptions!$C$25*MAX(0,UnitEconomics!$D$15-Assumptions!$C$27)*UnitEconomics!$D$39)+Assumptions!$C$35*Assumptions!$C$29+Assumptions!$C$36*Assumptions!$C$30+Assumptions!$C$37*(Assumptions!$C$116*$A23+Assumptions!$C$123*$A23*(1-Assumptions!$C$33))) | C23: =(UnitEconomics!$D$71+Assumptions!$C$33*($A23*UnitEconomics!$D$12*UnitEconomics!$D$27+($A23*Assumptions!$C$42+Assumptions!$C$43)*Assumptions!$C$98)+Assumptions!$C$34*(UnitEconomics!$D$15*UnitEconomics!$D$38+UnitEconomics!$D$35+UnitEconomics!$D$36)+Assumptions!$C$35*UnitEconomics!$D$74+Assumptions!$C$36*UnitEconomics!$D$75) | D23: =IF(B23>0,(B23-C23)/B23,0) | E23: =Forecast!$F$6*B23*12
A24: 12 | B24: =(Assumptions!$C$21+Assumptions!$C$33*$A24*(Assumptions!$C$22+Assumptions!$C$25*MAX(0,UnitEconomics!$D$12-Assumptions!$C$23)*UnitEconomics!$D$31)+Assumptions!$C$34*(Assumptions!$C$26+Assumptions!$C$25*MAX(0,UnitEconomics!$D$15-Assumptions!$C$27)*UnitEconomics!$D$39)+Assumptions!$C$35*Assumptions!$C$29+Assumptions!$C$36*Assumptions!$C$30+Assumptions!$C$37*(Assumptions!$C$116*$A24+Assumptions!$C$123*$A24*(1-Assumptions!$C$33))) | C24: =(UnitEconomics!$D$71+Assumptions!$C$33*($A24*UnitEconomics!$D$12*UnitEconomics!$D$27+($A24*Assumptions!$C$42+Assumptions!$C$43)*Assumptions!$C$98)+Assumptions!$C$34*(UnitEconomics!$D$15*UnitEconomics!$D$38+UnitEconomics!$D$35+UnitEconomics!$D$36)+Assumptions!$C$35*UnitEconomics!$D$74+Assumptions!$C$36*UnitEconomics!$D$75) | D24: =IF(B24>0,(B24-C24)/B24,0) | E24: =Forecast!$F$6*B24*12
A26: Outbound SMS segments per tenant per month
A27: Outbound SMS segments per tenant per month | B27: Revenue per tenant per month | C27: Cost per tenant per month | D27: Gross margin | E27: ARR at month 24, base scenario
A28: 500 | B28: =(Assumptions!$C$21+Assumptions!$C$33*Assumptions!$C$41*(Assumptions!$C$22+Assumptions!$C$25*MAX(0,UnitEconomics!$D$12-Assumptions!$C$23)*UnitEconomics!$D$31)+Assumptions!$C$34*(Assumptions!$C$26+Assumptions!$C$25*MAX(0,$A28-Assumptions!$C$27)*UnitEconomics!$D$39)+Assumptions!$C$35*Assumptions!$C$29+Assumptions!$C$36*Assumptions!$C$30+Assumptions!$C$37*(Assumptions!$C$116*Assumptions!$C$41+Assumptions!$C$123*Assumptions!$C$41*(1-Assumptions!$C$33))) | C28: =(UnitEconomics!$D$71+Assumptions!$C$33*(Assumptions!$C$41*UnitEconomics!$D$12*UnitEconomics!$D$27+(Assumptions!$C$41*Assumptions!$C$42+Assumptions!$C$43)*Assumptions!$C$98)+Assumptions!$C$34*($A28*UnitEconomics!$D$38+UnitEconomics!$D$35+UnitEconomics!$D$36)+Assumptions!$C$35*UnitEconomics!$D$74+Assumptions!$C$36*UnitEconomics!$D$75) | D28: =IF(B28>0,(B28-C28)/B28,0) | E28: =Forecast!$F$6*B28*12
A29: 1000 | B29: =(Assumptions!$C$21+Assumptions!$C$33*Assumptions!$C$41*(Assumptions!$C$22+Assumptions!$C$25*MAX(0,UnitEconomics!$D$12-Assumptions!$C$23)*UnitEconomics!$D$31)+Assumptions!$C$34*(Assumptions!$C$26+Assumptions!$C$25*MAX(0,$A29-Assumptions!$C$27)*UnitEconomics!$D$39)+Assumptions!$C$35*Assumptions!$C$29+Assumptions!$C$36*Assumptions!$C$30+Assumptions!$C$37*(Assumptions!$C$116*Assumptions!$C$41+Assumptions!$C$123*Assumptions!$C$41*(1-Assumptions!$C$33))) | C29: =(UnitEconomics!$D$71+Assumptions!$C$33*(Assumptions!$C$41*UnitEconomics!$D$12*UnitEconomics!$D$27+(Assumptions!$C$41*Assumptions!$C$42+Assumptions!$C$43)*Assumptions!$C$98)+Assumptions!$C$34*($A29*UnitEconomics!$D$38+UnitEconomics!$D$35+UnitEconomics!$D$36)+Assumptions!$C$35*UnitEconomics!$D$74+Assumptions!$C$36*UnitEconomics!$D$75) | D29: =IF(B29>0,(B29-C29)/B29,0) | E29: =Forecast!$F$6*B29*12
A30: 2500 | B30: =(Assumptions!$C$21+Assumptions!$C$33*Assumptions!$C$41*(Assumptions!$C$22+Assumptions!$C$25*MAX(0,UnitEconomics!$D$12-Assumptions!$C$23)*UnitEconomics!$D$31)+Assumptions!$C$34*(Assumptions!$C$26+Assumptions!$C$25*MAX(0,$A30-Assumptions!$C$27)*UnitEconomics!$D$39)+Assumptions!$C$35*Assumptions!$C$29+Assumptions!$C$36*Assumptions!$C$30+Assumptions!$C$37*(Assumptions!$C$116*Assumptions!$C$41+Assumptions!$C$123*Assumptions!$C$41*(1-Assumptions!$C$33))) | C30: =(UnitEconomics!$D$71+Assumptions!$C$33*(Assumptions!$C$41*UnitEconomics!$D$12*UnitEconomics!$D$27+(Assumptions!$C$41*Assumptions!$C$42+Assumptions!$C$43)*Assumptions!$C$98)+Assumptions!$C$34*($A30*UnitEconomics!$D$38+UnitEconomics!$D$35+UnitEconomics!$D$36)+Assumptions!$C$35*UnitEconomics!$D$74+Assumptions!$C$36*UnitEconomics!$D$75) | D30: =IF(B30>0,(B30-C30)/B30,0) | E30: =Forecast!$F$6*B30*12
A31: 5000 | B31: =(Assumptions!$C$21+Assumptions!$C$33*Assumptions!$C$41*(Assumptions!$C$22+Assumptions!$C$25*MAX(0,UnitEconomics!$D$12-Assumptions!$C$23)*UnitEconomics!$D$31)+Assumptions!$C$34*(Assumptions!$C$26+Assumptions!$C$25*MAX(0,$A31-Assumptions!$C$27)*UnitEconomics!$D$39)+Assumptions!$C$35*Assumptions!$C$29+Assumptions!$C$36*Assumptions!$C$30+Assumptions!$C$37*(Assumptions!$C$116*Assumptions!$C$41+Assumptions!$C$123*Assumptions!$C$41*(1-Assumptions!$C$33))) | C31: =(UnitEconomics!$D$71+Assumptions!$C$33*(Assumptions!$C$41*UnitEconomics!$D$12*UnitEconomics!$D$27+(Assumptions!$C$41*Assumptions!$C$42+Assumptions!$C$43)*Assumptions!$C$98)+Assumptions!$C$34*($A31*UnitEconomics!$D$38+UnitEconomics!$D$35+UnitEconomics!$D$36)+Assumptions!$C$35*UnitEconomics!$D$74+Assumptions!$C$36*UnitEconomics!$D$75) | D31: =IF(B31>0,(B31-C31)/B31,0) | E31: =Forecast!$F$6*B31*12
A32: 7500 | B32: =(Assumptions!$C$21+Assumptions!$C$33*Assumptions!$C$41*(Assumptions!$C$22+Assumptions!$C$25*MAX(0,UnitEconomics!$D$12-Assumptions!$C$23)*UnitEconomics!$D$31)+Assumptions!$C$34*(Assumptions!$C$26+Assumptions!$C$25*MAX(0,$A32-Assumptions!$C$27)*UnitEconomics!$D$39)+Assumptions!$C$35*Assumptions!$C$29+Assumptions!$C$36*Assumptions!$C$30+Assumptions!$C$37*(Assumptions!$C$116*Assumptions!$C$41+Assumptions!$C$123*Assumptions!$C$41*(1-Assumptions!$C$33))) | C32: =(UnitEconomics!$D$71+Assumptions!$C$33*(Assumptions!$C$41*UnitEconomics!$D$12*UnitEconomics!$D$27+(Assumptions!$C$41*Assumptions!$C$42+Assumptions!$C$43)*Assumptions!$C$98)+Assumptions!$C$34*($A32*UnitEconomics!$D$38+UnitEconomics!$D$35+UnitEconomics!$D$36)+Assumptions!$C$35*UnitEconomics!$D$74+Assumptions!$C$36*UnitEconomics!$D$75) | D32: =IF(B32>0,(B32-C32)/B32,0) | E32: =Forecast!$F$6*B32*12
A33: 10000 | B33: =(Assumptions!$C$21+Assumptions!$C$33*Assumptions!$C$41*(Assumptions!$C$22+Assumptions!$C$25*MAX(0,UnitEconomics!$D$12-Assumptions!$C$23)*UnitEconomics!$D$31)+Assumptions!$C$34*(Assumptions!$C$26+Assumptions!$C$25*MAX(0,$A33-Assumptions!$C$27)*UnitEconomics!$D$39)+Assumptions!$C$35*Assumptions!$C$29+Assumptions!$C$36*Assumptions!$C$30+Assumptions!$C$37*(Assumptions!$C$116*Assumptions!$C$41+Assumptions!$C$123*Assumptions!$C$41*(1-Assumptions!$C$33))) | C33: =(UnitEconomics!$D$71+Assumptions!$C$33*(Assumptions!$C$41*UnitEconomics!$D$12*UnitEconomics!$D$27+(Assumptions!$C$41*Assumptions!$C$42+Assumptions!$C$43)*Assumptions!$C$98)+Assumptions!$C$34*($A33*UnitEconomics!$D$38+UnitEconomics!$D$35+UnitEconomics!$D$36)+Assumptions!$C$35*UnitEconomics!$D$74+Assumptions!$C$36*UnitEconomics!$D$75) | D33: =IF(B33>0,(B33-C33)/B33,0) | E33: =Forecast!$F$6*B33*12
A34: 20000 | B34: =(Assumptions!$C$21+Assumptions!$C$33*Assumptions!$C$41*(Assumptions!$C$22+Assumptions!$C$25*MAX(0,UnitEconomics!$D$12-Assumptions!$C$23)*UnitEconomics!$D$31)+Assumptions!$C$34*(Assumptions!$C$26+Assumptions!$C$25*MAX(0,$A34-Assumptions!$C$27)*UnitEconomics!$D$39)+Assumptions!$C$35*Assumptions!$C$29+Assumptions!$C$36*Assumptions!$C$30+Assumptions!$C$37*(Assumptions!$C$116*Assumptions!$C$41+Assumptions!$C$123*Assumptions!$C$41*(1-Assumptions!$C$33))) | C34: =(UnitEconomics!$D$71+Assumptions!$C$33*(Assumptions!$C$41*UnitEconomics!$D$12*UnitEconomics!$D$27+(Assumptions!$C$41*Assumptions!$C$42+Assumptions!$C$43)*Assumptions!$C$98)+Assumptions!$C$34*($A34*UnitEconomics!$D$38+UnitEconomics!$D$35+UnitEconomics!$D$36)+Assumptions!$C$35*UnitEconomics!$D$74+Assumptions!$C$36*UnitEconomics!$D$75) | D34: =IF(B34>0,(B34-C34)/B34,0) | E34: =Forecast!$F$6*B34*12
A36: Dialer attach rate
A37: Dialer attach rate | B37: Revenue per tenant per month | C37: Cost per tenant per month | D37: Gross margin | E37: ARR at month 24, base scenario
A38: 0.2 | B38: =(Assumptions!$C$21+$A38*Assumptions!$C$41*(Assumptions!$C$22+Assumptions!$C$25*MAX(0,UnitEconomics!$D$12-Assumptions!$C$23)*UnitEconomics!$D$31)+Assumptions!$C$34*(Assumptions!$C$26+Assumptions!$C$25*MAX(0,UnitEconomics!$D$15-Assumptions!$C$27)*UnitEconomics!$D$39)+Assumptions!$C$35*Assumptions!$C$29+Assumptions!$C$36*Assumptions!$C$30+Assumptions!$C$37*(Assumptions!$C$116*Assumptions!$C$41+Assumptions!$C$123*Assumptions!$C$41*(1-$A38))) | C38: =(UnitEconomics!$D$71+$A38*(Assumptions!$C$41*UnitEconomics!$D$12*UnitEconomics!$D$27+(Assumptions!$C$41*Assumptions!$C$42+Assumptions!$C$43)*Assumptions!$C$98)+Assumptions!$C$34*(UnitEconomics!$D$15*UnitEconomics!$D$38+UnitEconomics!$D$35+UnitEconomics!$D$36)+Assumptions!$C$35*UnitEconomics!$D$74+Assumptions!$C$36*UnitEconomics!$D$75) | D38: =IF(B38>0,(B38-C38)/B38,0) | E38: =Forecast!$F$6*B38*12
A39: 0.4 | B39: =(Assumptions!$C$21+$A39*Assumptions!$C$41*(Assumptions!$C$22+Assumptions!$C$25*MAX(0,UnitEconomics!$D$12-Assumptions!$C$23)*UnitEconomics!$D$31)+Assumptions!$C$34*(Assumptions!$C$26+Assumptions!$C$25*MAX(0,UnitEconomics!$D$15-Assumptions!$C$27)*UnitEconomics!$D$39)+Assumptions!$C$35*Assumptions!$C$29+Assumptions!$C$36*Assumptions!$C$30+Assumptions!$C$37*(Assumptions!$C$116*Assumptions!$C$41+Assumptions!$C$123*Assumptions!$C$41*(1-$A39))) | C39: =(UnitEconomics!$D$71+$A39*(Assumptions!$C$41*UnitEconomics!$D$12*UnitEconomics!$D$27+(Assumptions!$C$41*Assumptions!$C$42+Assumptions!$C$43)*Assumptions!$C$98)+Assumptions!$C$34*(UnitEconomics!$D$15*UnitEconomics!$D$38+UnitEconomics!$D$35+UnitEconomics!$D$36)+Assumptions!$C$35*UnitEconomics!$D$74+Assumptions!$C$36*UnitEconomics!$D$75) | D39: =IF(B39>0,(B39-C39)/B39,0) | E39: =Forecast!$F$6*B39*12
A40: 0.6 | B40: =(Assumptions!$C$21+$A40*Assumptions!$C$41*(Assumptions!$C$22+Assumptions!$C$25*MAX(0,UnitEconomics!$D$12-Assumptions!$C$23)*UnitEconomics!$D$31)+Assumptions!$C$34*(Assumptions!$C$26+Assumptions!$C$25*MAX(0,UnitEconomics!$D$15-Assumptions!$C$27)*UnitEconomics!$D$39)+Assumptions!$C$35*Assumptions!$C$29+Assumptions!$C$36*Assumptions!$C$30+Assumptions!$C$37*(Assumptions!$C$116*Assumptions!$C$41+Assumptions!$C$123*Assumptions!$C$41*(1-$A40))) | C40: =(UnitEconomics!$D$71+$A40*(Assumptions!$C$41*UnitEconomics!$D$12*UnitEconomics!$D$27+(Assumptions!$C$41*Assumptions!$C$42+Assumptions!$C$43)*Assumptions!$C$98)+Assumptions!$C$34*(UnitEconomics!$D$15*UnitEconomics!$D$38+UnitEconomics!$D$35+UnitEconomics!$D$36)+Assumptions!$C$35*UnitEconomics!$D$74+Assumptions!$C$36*UnitEconomics!$D$75) | D40: =IF(B40>0,(B40-C40)/B40,0) | E40: =Forecast!$F$6*B40*12
A41: 0.8 | B41: =(Assumptions!$C$21+$A41*Assumptions!$C$41*(Assumptions!$C$22+Assumptions!$C$25*MAX(0,UnitEconomics!$D$12-Assumptions!$C$23)*UnitEconomics!$D$31)+Assumptions!$C$34*(Assumptions!$C$26+Assumptions!$C$25*MAX(0,UnitEconomics!$D$15-Assumptions!$C$27)*UnitEconomics!$D$39)+Assumptions!$C$35*Assumptions!$C$29+Assumptions!$C$36*Assumptions!$C$30+Assumptions!$C$37*(Assumptions!$C$116*Assumptions!$C$41+Assumptions!$C$123*Assumptions!$C$41*(1-$A41))) | C41: =(UnitEconomics!$D$71+$A41*(Assumptions!$C$41*UnitEconomics!$D$12*UnitEconomics!$D$27+(Assumptions!$C$41*Assumptions!$C$42+Assumptions!$C$43)*Assumptions!$C$98)+Assumptions!$C$34*(UnitEconomics!$D$15*UnitEconomics!$D$38+UnitEconomics!$D$35+UnitEconomics!$D$36)+Assumptions!$C$35*UnitEconomics!$D$74+Assumptions!$C$36*UnitEconomics!$D$75) | D41: =IF(B41>0,(B41-C41)/B41,0) | E41: =Forecast!$F$6*B41*12
A42: 1 | B42: =(Assumptions!$C$21+$A42*Assumptions!$C$41*(Assumptions!$C$22+Assumptions!$C$25*MAX(0,UnitEconomics!$D$12-Assumptions!$C$23)*UnitEconomics!$D$31)+Assumptions!$C$34*(Assumptions!$C$26+Assumptions!$C$25*MAX(0,UnitEconomics!$D$15-Assumptions!$C$27)*UnitEconomics!$D$39)+Assumptions!$C$35*Assumptions!$C$29+Assumptions!$C$36*Assumptions!$C$30+Assumptions!$C$37*(Assumptions!$C$116*Assumptions!$C$41+Assumptions!$C$123*Assumptions!$C$41*(1-$A42))) | C42: =(UnitEconomics!$D$71+$A42*(Assumptions!$C$41*UnitEconomics!$D$12*UnitEconomics!$D$27+(Assumptions!$C$41*Assumptions!$C$42+Assumptions!$C$43)*Assumptions!$C$98)+Assumptions!$C$34*(UnitEconomics!$D$15*UnitEconomics!$D$38+UnitEconomics!$D$35+UnitEconomics!$D$36)+Assumptions!$C$35*UnitEconomics!$D$74+Assumptions!$C$36*UnitEconomics!$D$75) | D42: =IF(B42>0,(B42-C42)/B42,0) | E42: =Forecast!$F$6*B42*12
A44: SMS attach rate
A45: SMS attach rate | B45: Revenue per tenant per month | C45: Cost per tenant per month | D45: Gross margin | E45: ARR at month 24, base scenario
A46: 0.2 | B46: =(Assumptions!$C$21+Assumptions!$C$33*Assumptions!$C$41*(Assumptions!$C$22+Assumptions!$C$25*MAX(0,UnitEconomics!$D$12-Assumptions!$C$23)*UnitEconomics!$D$31)+$A46*(Assumptions!$C$26+Assumptions!$C$25*MAX(0,UnitEconomics!$D$15-Assumptions!$C$27)*UnitEconomics!$D$39)+Assumptions!$C$35*Assumptions!$C$29+Assumptions!$C$36*Assumptions!$C$30+Assumptions!$C$37*(Assumptions!$C$116*Assumptions!$C$41+Assumptions!$C$123*Assumptions!$C$41*(1-Assumptions!$C$33))) | C46: =(UnitEconomics!$D$71+Assumptions!$C$33*(Assumptions!$C$41*UnitEconomics!$D$12*UnitEconomics!$D$27+(Assumptions!$C$41*Assumptions!$C$42+Assumptions!$C$43)*Assumptions!$C$98)+$A46*(UnitEconomics!$D$15*UnitEconomics!$D$38+UnitEconomics!$D$35+UnitEconomics!$D$36)+Assumptions!$C$35*UnitEconomics!$D$74+Assumptions!$C$36*UnitEconomics!$D$75) | D46: =IF(B46>0,(B46-C46)/B46,0) | E46: =Forecast!$F$6*B46*12
A47: 0.35 | B47: =(Assumptions!$C$21+Assumptions!$C$33*Assumptions!$C$41*(Assumptions!$C$22+Assumptions!$C$25*MAX(0,UnitEconomics!$D$12-Assumptions!$C$23)*UnitEconomics!$D$31)+$A47*(Assumptions!$C$26+Assumptions!$C$25*MAX(0,UnitEconomics!$D$15-Assumptions!$C$27)*UnitEconomics!$D$39)+Assumptions!$C$35*Assumptions!$C$29+Assumptions!$C$36*Assumptions!$C$30+Assumptions!$C$37*(Assumptions!$C$116*Assumptions!$C$41+Assumptions!$C$123*Assumptions!$C$41*(1-Assumptions!$C$33))) | C47: =(UnitEconomics!$D$71+Assumptions!$C$33*(Assumptions!$C$41*UnitEconomics!$D$12*UnitEconomics!$D$27+(Assumptions!$C$41*Assumptions!$C$42+Assumptions!$C$43)*Assumptions!$C$98)+$A47*(UnitEconomics!$D$15*UnitEconomics!$D$38+UnitEconomics!$D$35+UnitEconomics!$D$36)+Assumptions!$C$35*UnitEconomics!$D$74+Assumptions!$C$36*UnitEconomics!$D$75) | D47: =IF(B47>0,(B47-C47)/B47,0) | E47: =Forecast!$F$6*B47*12
A48: 0.5 | B48: =(Assumptions!$C$21+Assumptions!$C$33*Assumptions!$C$41*(Assumptions!$C$22+Assumptions!$C$25*MAX(0,UnitEconomics!$D$12-Assumptions!$C$23)*UnitEconomics!$D$31)+$A48*(Assumptions!$C$26+Assumptions!$C$25*MAX(0,UnitEconomics!$D$15-Assumptions!$C$27)*UnitEconomics!$D$39)+Assumptions!$C$35*Assumptions!$C$29+Assumptions!$C$36*Assumptions!$C$30+Assumptions!$C$37*(Assumptions!$C$116*Assumptions!$C$41+Assumptions!$C$123*Assumptions!$C$41*(1-Assumptions!$C$33))) | C48: =(UnitEconomics!$D$71+Assumptions!$C$33*(Assumptions!$C$41*UnitEconomics!$D$12*UnitEconomics!$D$27+(Assumptions!$C$41*Assumptions!$C$42+Assumptions!$C$43)*Assumptions!$C$98)+$A48*(UnitEconomics!$D$15*UnitEconomics!$D$38+UnitEconomics!$D$35+UnitEconomics!$D$36)+Assumptions!$C$35*UnitEconomics!$D$74+Assumptions!$C$36*UnitEconomics!$D$75) | D48: =IF(B48>0,(B48-C48)/B48,0) | E48: =Forecast!$F$6*B48*12
A49: 0.65 | B49: =(Assumptions!$C$21+Assumptions!$C$33*Assumptions!$C$41*(Assumptions!$C$22+Assumptions!$C$25*MAX(0,UnitEconomics!$D$12-Assumptions!$C$23)*UnitEconomics!$D$31)+$A49*(Assumptions!$C$26+Assumptions!$C$25*MAX(0,UnitEconomics!$D$15-Assumptions!$C$27)*UnitEconomics!$D$39)+Assumptions!$C$35*Assumptions!$C$29+Assumptions!$C$36*Assumptions!$C$30+Assumptions!$C$37*(Assumptions!$C$116*Assumptions!$C$41+Assumptions!$C$123*Assumptions!$C$41*(1-Assumptions!$C$33))) | C49: =(UnitEconomics!$D$71+Assumptions!$C$33*(Assumptions!$C$41*UnitEconomics!$D$12*UnitEconomics!$D$27+(Assumptions!$C$41*Assumptions!$C$42+Assumptions!$C$43)*Assumptions!$C$98)+$A49*(UnitEconomics!$D$15*UnitEconomics!$D$38+UnitEconomics!$D$35+UnitEconomics!$D$36)+Assumptions!$C$35*UnitEconomics!$D$74+Assumptions!$C$36*UnitEconomics!$D$75) | D49: =IF(B49>0,(B49-C49)/B49,0) | E49: =Forecast!$F$6*B49*12
A50: 0.8 | B50: =(Assumptions!$C$21+Assumptions!$C$33*Assumptions!$C$41*(Assumptions!$C$22+Assumptions!$C$25*MAX(0,UnitEconomics!$D$12-Assumptions!$C$23)*UnitEconomics!$D$31)+$A50*(Assumptions!$C$26+Assumptions!$C$25*MAX(0,UnitEconomics!$D$15-Assumptions!$C$27)*UnitEconomics!$D$39)+Assumptions!$C$35*Assumptions!$C$29+Assumptions!$C$36*Assumptions!$C$30+Assumptions!$C$37*(Assumptions!$C$116*Assumptions!$C$41+Assumptions!$C$123*Assumptions!$C$41*(1-Assumptions!$C$33))) | C50: =(UnitEconomics!$D$71+Assumptions!$C$33*(Assumptions!$C$41*UnitEconomics!$D$12*UnitEconomics!$D$27+(Assumptions!$C$41*Assumptions!$C$42+Assumptions!$C$43)*Assumptions!$C$98)+$A50*(UnitEconomics!$D$15*UnitEconomics!$D$38+UnitEconomics!$D$35+UnitEconomics!$D$36)+Assumptions!$C$35*UnitEconomics!$D$74+Assumptions!$C$36*UnitEconomics!$D$75) | D50: =IF(B50>0,(B50-C50)/B50,0) | E50: =Forecast!$F$6*B50*12
A52: Compliance attach rate
A53: Compliance attach rate | B53: Revenue per tenant per month | C53: Cost per tenant per month | D53: Gross margin | E53: ARR at month 24, base scenario
A54: 0.1 | B54: =(Assumptions!$C$21+Assumptions!$C$33*Assumptions!$C$41*(Assumptions!$C$22+Assumptions!$C$25*MAX(0,UnitEconomics!$D$12-Assumptions!$C$23)*UnitEconomics!$D$31)+Assumptions!$C$34*(Assumptions!$C$26+Assumptions!$C$25*MAX(0,UnitEconomics!$D$15-Assumptions!$C$27)*UnitEconomics!$D$39)+$A54*Assumptions!$C$29+Assumptions!$C$36*Assumptions!$C$30+Assumptions!$C$37*(Assumptions!$C$116*Assumptions!$C$41+Assumptions!$C$123*Assumptions!$C$41*(1-Assumptions!$C$33))) | C54: =(UnitEconomics!$D$71+Assumptions!$C$33*(Assumptions!$C$41*UnitEconomics!$D$12*UnitEconomics!$D$27+(Assumptions!$C$41*Assumptions!$C$42+Assumptions!$C$43)*Assumptions!$C$98)+Assumptions!$C$34*(UnitEconomics!$D$15*UnitEconomics!$D$38+UnitEconomics!$D$35+UnitEconomics!$D$36)+$A54*UnitEconomics!$D$74+Assumptions!$C$36*UnitEconomics!$D$75) | D54: =IF(B54>0,(B54-C54)/B54,0) | E54: =Forecast!$F$6*B54*12
A55: 0.25 | B55: =(Assumptions!$C$21+Assumptions!$C$33*Assumptions!$C$41*(Assumptions!$C$22+Assumptions!$C$25*MAX(0,UnitEconomics!$D$12-Assumptions!$C$23)*UnitEconomics!$D$31)+Assumptions!$C$34*(Assumptions!$C$26+Assumptions!$C$25*MAX(0,UnitEconomics!$D$15-Assumptions!$C$27)*UnitEconomics!$D$39)+$A55*Assumptions!$C$29+Assumptions!$C$36*Assumptions!$C$30+Assumptions!$C$37*(Assumptions!$C$116*Assumptions!$C$41+Assumptions!$C$123*Assumptions!$C$41*(1-Assumptions!$C$33))) | C55: =(UnitEconomics!$D$71+Assumptions!$C$33*(Assumptions!$C$41*UnitEconomics!$D$12*UnitEconomics!$D$27+(Assumptions!$C$41*Assumptions!$C$42+Assumptions!$C$43)*Assumptions!$C$98)+Assumptions!$C$34*(UnitEconomics!$D$15*UnitEconomics!$D$38+UnitEconomics!$D$35+UnitEconomics!$D$36)+$A55*UnitEconomics!$D$74+Assumptions!$C$36*UnitEconomics!$D$75) | D55: =IF(B55>0,(B55-C55)/B55,0) | E55: =Forecast!$F$6*B55*12
A56: 0.4 | B56: =(Assumptions!$C$21+Assumptions!$C$33*Assumptions!$C$41*(Assumptions!$C$22+Assumptions!$C$25*MAX(0,UnitEconomics!$D$12-Assumptions!$C$23)*UnitEconomics!$D$31)+Assumptions!$C$34*(Assumptions!$C$26+Assumptions!$C$25*MAX(0,UnitEconomics!$D$15-Assumptions!$C$27)*UnitEconomics!$D$39)+$A56*Assumptions!$C$29+Assumptions!$C$36*Assumptions!$C$30+Assumptions!$C$37*(Assumptions!$C$116*Assumptions!$C$41+Assumptions!$C$123*Assumptions!$C$41*(1-Assumptions!$C$33))) | C56: =(UnitEconomics!$D$71+Assumptions!$C$33*(Assumptions!$C$41*UnitEconomics!$D$12*UnitEconomics!$D$27+(Assumptions!$C$41*Assumptions!$C$42+Assumptions!$C$43)*Assumptions!$C$98)+Assumptions!$C$34*(UnitEconomics!$D$15*UnitEconomics!$D$38+UnitEconomics!$D$35+UnitEconomics!$D$36)+$A56*UnitEconomics!$D$74+Assumptions!$C$36*UnitEconomics!$D$75) | D56: =IF(B56>0,(B56-C56)/B56,0) | E56: =Forecast!$F$6*B56*12
A57: 0.6 | B57: =(Assumptions!$C$21+Assumptions!$C$33*Assumptions!$C$41*(Assumptions!$C$22+Assumptions!$C$25*MAX(0,UnitEconomics!$D$12-Assumptions!$C$23)*UnitEconomics!$D$31)+Assumptions!$C$34*(Assumptions!$C$26+Assumptions!$C$25*MAX(0,UnitEconomics!$D$15-Assumptions!$C$27)*UnitEconomics!$D$39)+$A57*Assumptions!$C$29+Assumptions!$C$36*Assumptions!$C$30+Assumptions!$C$37*(Assumptions!$C$116*Assumptions!$C$41+Assumptions!$C$123*Assumptions!$C$41*(1-Assumptions!$C$33))) | C57: =(UnitEconomics!$D$71+Assumptions!$C$33*(Assumptions!$C$41*UnitEconomics!$D$12*UnitEconomics!$D$27+(Assumptions!$C$41*Assumptions!$C$42+Assumptions!$C$43)*Assumptions!$C$98)+Assumptions!$C$34*(UnitEconomics!$D$15*UnitEconomics!$D$38+UnitEconomics!$D$35+UnitEconomics!$D$36)+$A57*UnitEconomics!$D$74+Assumptions!$C$36*UnitEconomics!$D$75) | D57: =IF(B57>0,(B57-C57)/B57,0) | E57: =Forecast!$F$6*B57*12
A58: 0.8 | B58: =(Assumptions!$C$21+Assumptions!$C$33*Assumptions!$C$41*(Assumptions!$C$22+Assumptions!$C$25*MAX(0,UnitEconomics!$D$12-Assumptions!$C$23)*UnitEconomics!$D$31)+Assumptions!$C$34*(Assumptions!$C$26+Assumptions!$C$25*MAX(0,UnitEconomics!$D$15-Assumptions!$C$27)*UnitEconomics!$D$39)+$A58*Assumptions!$C$29+Assumptions!$C$36*Assumptions!$C$30+Assumptions!$C$37*(Assumptions!$C$116*Assumptions!$C$41+Assumptions!$C$123*Assumptions!$C$41*(1-Assumptions!$C$33))) | C58: =(UnitEconomics!$D$71+Assumptions!$C$33*(Assumptions!$C$41*UnitEconomics!$D$12*UnitEconomics!$D$27+(Assumptions!$C$41*Assumptions!$C$42+Assumptions!$C$43)*Assumptions!$C$98)+Assumptions!$C$34*(UnitEconomics!$D$15*UnitEconomics!$D$38+UnitEconomics!$D$35+UnitEconomics!$D$36)+$A58*UnitEconomics!$D$74+Assumptions!$C$36*UnitEconomics!$D$75) | D58: =IF(B58>0,(B58-C58)/B58,0) | E58: =Forecast!$F$6*B58*12
A60: AI SMS attach rate
A61: AI SMS attach rate | B61: Revenue per tenant per month | C61: Cost per tenant per month | D61: Gross margin | E61: ARR at month 24, base scenario
A62: 0.05 | B62: =(Assumptions!$C$21+Assumptions!$C$33*Assumptions!$C$41*(Assumptions!$C$22+Assumptions!$C$25*MAX(0,UnitEconomics!$D$12-Assumptions!$C$23)*UnitEconomics!$D$31)+Assumptions!$C$34*(Assumptions!$C$26+Assumptions!$C$25*MAX(0,UnitEconomics!$D$15-Assumptions!$C$27)*UnitEconomics!$D$39)+Assumptions!$C$35*Assumptions!$C$29+$A62*Assumptions!$C$30+Assumptions!$C$37*(Assumptions!$C$116*Assumptions!$C$41+Assumptions!$C$123*Assumptions!$C$41*(1-Assumptions!$C$33))) | C62: =(UnitEconomics!$D$71+Assumptions!$C$33*(Assumptions!$C$41*UnitEconomics!$D$12*UnitEconomics!$D$27+(Assumptions!$C$41*Assumptions!$C$42+Assumptions!$C$43)*Assumptions!$C$98)+Assumptions!$C$34*(UnitEconomics!$D$15*UnitEconomics!$D$38+UnitEconomics!$D$35+UnitEconomics!$D$36)+Assumptions!$C$35*UnitEconomics!$D$74+$A62*UnitEconomics!$D$75) | D62: =IF(B62>0,(B62-C62)/B62,0) | E62: =Forecast!$F$6*B62*12
A63: 0.1 | B63: =(Assumptions!$C$21+Assumptions!$C$33*Assumptions!$C$41*(Assumptions!$C$22+Assumptions!$C$25*MAX(0,UnitEconomics!$D$12-Assumptions!$C$23)*UnitEconomics!$D$31)+Assumptions!$C$34*(Assumptions!$C$26+Assumptions!$C$25*MAX(0,UnitEconomics!$D$15-Assumptions!$C$27)*UnitEconomics!$D$39)+Assumptions!$C$35*Assumptions!$C$29+$A63*Assumptions!$C$30+Assumptions!$C$37*(Assumptions!$C$116*Assumptions!$C$41+Assumptions!$C$123*Assumptions!$C$41*(1-Assumptions!$C$33))) | C63: =(UnitEconomics!$D$71+Assumptions!$C$33*(Assumptions!$C$41*UnitEconomics!$D$12*UnitEconomics!$D$27+(Assumptions!$C$41*Assumptions!$C$42+Assumptions!$C$43)*Assumptions!$C$98)+Assumptions!$C$34*(UnitEconomics!$D$15*UnitEconomics!$D$38+UnitEconomics!$D$35+UnitEconomics!$D$36)+Assumptions!$C$35*UnitEconomics!$D$74+$A63*UnitEconomics!$D$75) | D63: =IF(B63>0,(B63-C63)/B63,0) | E63: =Forecast!$F$6*B63*12
A64: 0.2 | B64: =(Assumptions!$C$21+Assumptions!$C$33*Assumptions!$C$41*(Assumptions!$C$22+Assumptions!$C$25*MAX(0,UnitEconomics!$D$12-Assumptions!$C$23)*UnitEconomics!$D$31)+Assumptions!$C$34*(Assumptions!$C$26+Assumptions!$C$25*MAX(0,UnitEconomics!$D$15-Assumptions!$C$27)*UnitEconomics!$D$39)+Assumptions!$C$35*Assumptions!$C$29+$A64*Assumptions!$C$30+Assumptions!$C$37*(Assumptions!$C$116*Assumptions!$C$41+Assumptions!$C$123*Assumptions!$C$41*(1-Assumptions!$C$33))) | C64: =(UnitEconomics!$D$71+Assumptions!$C$33*(Assumptions!$C$41*UnitEconomics!$D$12*UnitEconomics!$D$27+(Assumptions!$C$41*Assumptions!$C$42+Assumptions!$C$43)*Assumptions!$C$98)+Assumptions!$C$34*(UnitEconomics!$D$15*UnitEconomics!$D$38+UnitEconomics!$D$35+UnitEconomics!$D$36)+Assumptions!$C$35*UnitEconomics!$D$74+$A64*UnitEconomics!$D$75) | D64: =IF(B64>0,(B64-C64)/B64,0) | E64: =Forecast!$F$6*B64*12
A65: 0.35 | B65: =(Assumptions!$C$21+Assumptions!$C$33*Assumptions!$C$41*(Assumptions!$C$22+Assumptions!$C$25*MAX(0,UnitEconomics!$D$12-Assumptions!$C$23)*UnitEconomics!$D$31)+Assumptions!$C$34*(Assumptions!$C$26+Assumptions!$C$25*MAX(0,UnitEconomics!$D$15-Assumptions!$C$27)*UnitEconomics!$D$39)+Assumptions!$C$35*Assumptions!$C$29+$A65*Assumptions!$C$30+Assumptions!$C$37*(Assumptions!$C$116*Assumptions!$C$41+Assumptions!$C$123*Assumptions!$C$41*(1-Assumptions!$C$33))) | C65: =(UnitEconomics!$D$71+Assumptions!$C$33*(Assumptions!$C$41*UnitEconomics!$D$12*UnitEconomics!$D$27+(Assumptions!$C$41*Assumptions!$C$42+Assumptions!$C$43)*Assumptions!$C$98)+Assumptions!$C$34*(UnitEconomics!$D$15*UnitEconomics!$D$38+UnitEconomics!$D$35+UnitEconomics!$D$36)+Assumptions!$C$35*UnitEconomics!$D$74+$A65*UnitEconomics!$D$75) | D65: =IF(B65>0,(B65-C65)/B65,0) | E65: =Forecast!$F$6*B65*12
A66: 0.5 | B66: =(Assumptions!$C$21+Assumptions!$C$33*Assumptions!$C$41*(Assumptions!$C$22+Assumptions!$C$25*MAX(0,UnitEconomics!$D$12-Assumptions!$C$23)*UnitEconomics!$D$31)+Assumptions!$C$34*(Assumptions!$C$26+Assumptions!$C$25*MAX(0,UnitEconomics!$D$15-Assumptions!$C$27)*UnitEconomics!$D$39)+Assumptions!$C$35*Assumptions!$C$29+$A66*Assumptions!$C$30+Assumptions!$C$37*(Assumptions!$C$116*Assumptions!$C$41+Assumptions!$C$123*Assumptions!$C$41*(1-Assumptions!$C$33))) | C66: =(UnitEconomics!$D$71+Assumptions!$C$33*(Assumptions!$C$41*UnitEconomics!$D$12*UnitEconomics!$D$27+(Assumptions!$C$41*Assumptions!$C$42+Assumptions!$C$43)*Assumptions!$C$98)+Assumptions!$C$34*(UnitEconomics!$D$15*UnitEconomics!$D$38+UnitEconomics!$D$35+UnitEconomics!$D$36)+Assumptions!$C$35*UnitEconomics!$D$74+$A66*UnitEconomics!$D$75) | D66: =IF(B66>0,(B66-C66)/B66,0) | E66: =Forecast!$F$6*B66*12
A68: Platform fee
A69: Platform fee | B69: Revenue per tenant per month | C69: Cost per tenant per month | D69: Gross margin | E69: ARR at month 24, base scenario
A70: 299 | B70: =($A70+Assumptions!$C$33*Assumptions!$C$41*(Assumptions!$C$22+Assumptions!$C$25*MAX(0,UnitEconomics!$D$12-Assumptions!$C$23)*UnitEconomics!$D$31)+Assumptions!$C$34*(Assumptions!$C$26+Assumptions!$C$25*MAX(0,UnitEconomics!$D$15-Assumptions!$C$27)*UnitEconomics!$D$39)+Assumptions!$C$35*Assumptions!$C$29+Assumptions!$C$36*Assumptions!$C$30+Assumptions!$C$37*(Assumptions!$C$116*Assumptions!$C$41+Assumptions!$C$123*Assumptions!$C$41*(1-Assumptions!$C$33))) | C70: =(UnitEconomics!$D$71+Assumptions!$C$33*(Assumptions!$C$41*UnitEconomics!$D$12*UnitEconomics!$D$27+(Assumptions!$C$41*Assumptions!$C$42+Assumptions!$C$43)*Assumptions!$C$98)+Assumptions!$C$34*(UnitEconomics!$D$15*UnitEconomics!$D$38+UnitEconomics!$D$35+UnitEconomics!$D$36)+Assumptions!$C$35*UnitEconomics!$D$74+Assumptions!$C$36*UnitEconomics!$D$75) | D70: =IF(B70>0,(B70-C70)/B70,0) | E70: =Forecast!$F$6*B70*12
A71: 349 | B71: =($A71+Assumptions!$C$33*Assumptions!$C$41*(Assumptions!$C$22+Assumptions!$C$25*MAX(0,UnitEconomics!$D$12-Assumptions!$C$23)*UnitEconomics!$D$31)+Assumptions!$C$34*(Assumptions!$C$26+Assumptions!$C$25*MAX(0,UnitEconomics!$D$15-Assumptions!$C$27)*UnitEconomics!$D$39)+Assumptions!$C$35*Assumptions!$C$29+Assumptions!$C$36*Assumptions!$C$30+Assumptions!$C$37*(Assumptions!$C$116*Assumptions!$C$41+Assumptions!$C$123*Assumptions!$C$41*(1-Assumptions!$C$33))) | C71: =(UnitEconomics!$D$71+Assumptions!$C$33*(Assumptions!$C$41*UnitEconomics!$D$12*UnitEconomics!$D$27+(Assumptions!$C$41*Assumptions!$C$42+Assumptions!$C$43)*Assumptions!$C$98)+Assumptions!$C$34*(UnitEconomics!$D$15*UnitEconomics!$D$38+UnitEconomics!$D$35+UnitEconomics!$D$36)+Assumptions!$C$35*UnitEconomics!$D$74+Assumptions!$C$36*UnitEconomics!$D$75) | D71: =IF(B71>0,(B71-C71)/B71,0) | E71: =Forecast!$F$6*B71*12
A72: 399 | B72: =($A72+Assumptions!$C$33*Assumptions!$C$41*(Assumptions!$C$22+Assumptions!$C$25*MAX(0,UnitEconomics!$D$12-Assumptions!$C$23)*UnitEconomics!$D$31)+Assumptions!$C$34*(Assumptions!$C$26+Assumptions!$C$25*MAX(0,UnitEconomics!$D$15-Assumptions!$C$27)*UnitEconomics!$D$39)+Assumptions!$C$35*Assumptions!$C$29+Assumptions!$C$36*Assumptions!$C$30+Assumptions!$C$37*(Assumptions!$C$116*Assumptions!$C$41+Assumptions!$C$123*Assumptions!$C$41*(1-Assumptions!$C$33))) | C72: =(UnitEconomics!$D$71+Assumptions!$C$33*(Assumptions!$C$41*UnitEconomics!$D$12*UnitEconomics!$D$27+(Assumptions!$C$41*Assumptions!$C$42+Assumptions!$C$43)*Assumptions!$C$98)+Assumptions!$C$34*(UnitEconomics!$D$15*UnitEconomics!$D$38+UnitEconomics!$D$35+UnitEconomics!$D$36)+Assumptions!$C$35*UnitEconomics!$D$74+Assumptions!$C$36*UnitEconomics!$D$75) | D72: =IF(B72>0,(B72-C72)/B72,0) | E72: =Forecast!$F$6*B72*12
A73: 449 | B73: =($A73+Assumptions!$C$33*Assumptions!$C$41*(Assumptions!$C$22+Assumptions!$C$25*MAX(0,UnitEconomics!$D$12-Assumptions!$C$23)*UnitEconomics!$D$31)+Assumptions!$C$34*(Assumptions!$C$26+Assumptions!$C$25*MAX(0,UnitEconomics!$D$15-Assumptions!$C$27)*UnitEconomics!$D$39)+Assumptions!$C$35*Assumptions!$C$29+Assumptions!$C$36*Assumptions!$C$30+Assumptions!$C$37*(Assumptions!$C$116*Assumptions!$C$41+Assumptions!$C$123*Assumptions!$C$41*(1-Assumptions!$C$33))) | C73: =(UnitEconomics!$D$71+Assumptions!$C$33*(Assumptions!$C$41*UnitEconomics!$D$12*UnitEconomics!$D$27+(Assumptions!$C$41*Assumptions!$C$42+Assumptions!$C$43)*Assumptions!$C$98)+Assumptions!$C$34*(UnitEconomics!$D$15*UnitEconomics!$D$38+UnitEconomics!$D$35+UnitEconomics!$D$36)+Assumptions!$C$35*UnitEconomics!$D$74+Assumptions!$C$36*UnitEconomics!$D$75) | D73: =IF(B73>0,(B73-C73)/B73,0) | E73: =Forecast!$F$6*B73*12
A74: 499 | B74: =($A74+Assumptions!$C$33*Assumptions!$C$41*(Assumptions!$C$22+Assumptions!$C$25*MAX(0,UnitEconomics!$D$12-Assumptions!$C$23)*UnitEconomics!$D$31)+Assumptions!$C$34*(Assumptions!$C$26+Assumptions!$C$25*MAX(0,UnitEconomics!$D$15-Assumptions!$C$27)*UnitEconomics!$D$39)+Assumptions!$C$35*Assumptions!$C$29+Assumptions!$C$36*Assumptions!$C$30+Assumptions!$C$37*(Assumptions!$C$116*Assumptions!$C$41+Assumptions!$C$123*Assumptions!$C$41*(1-Assumptions!$C$33))) | C74: =(UnitEconomics!$D$71+Assumptions!$C$33*(Assumptions!$C$41*UnitEconomics!$D$12*UnitEconomics!$D$27+(Assumptions!$C$41*Assumptions!$C$42+Assumptions!$C$43)*Assumptions!$C$98)+Assumptions!$C$34*(UnitEconomics!$D$15*UnitEconomics!$D$38+UnitEconomics!$D$35+UnitEconomics!$D$36)+Assumptions!$C$35*UnitEconomics!$D$74+Assumptions!$C$36*UnitEconomics!$D$75) | D74: =IF(B74>0,(B74-C74)/B74,0) | E74: =Forecast!$F$6*B74*12
A76: Addressable firms
A77: Addressable firms | B77: Revenue per tenant per month | C77: Cost per tenant per month | D77: Gross margin | E77: ARR at month 24, base scenario
A78: 901 | B78: =(Assumptions!$C$21+Assumptions!$C$33*Assumptions!$C$41*(Assumptions!$C$22+Assumptions!$C$25*MAX(0,UnitEconomics!$D$12-Assumptions!$C$23)*UnitEconomics!$D$31)+Assumptions!$C$34*(Assumptions!$C$26+Assumptions!$C$25*MAX(0,UnitEconomics!$D$15-Assumptions!$C$27)*UnitEconomics!$D$39)+Assumptions!$C$35*Assumptions!$C$29+Assumptions!$C$36*Assumptions!$C$30+Assumptions!$C$37*(Assumptions!$C$116*Assumptions!$C$41+Assumptions!$C$123*Assumptions!$C$41*(1-Assumptions!$C$33))) | C78: =(UnitEconomics!$D$71+Assumptions!$C$33*(Assumptions!$C$41*UnitEconomics!$D$12*UnitEconomics!$D$27+(Assumptions!$C$41*Assumptions!$C$42+Assumptions!$C$43)*Assumptions!$C$98)+Assumptions!$C$34*(UnitEconomics!$D$15*UnitEconomics!$D$38+UnitEconomics!$D$35+UnitEconomics!$D$36)+Assumptions!$C$35*UnitEconomics!$D$74+Assumptions!$C$36*UnitEconomics!$D$75) | D78: =IF(B78>0,(B78-C78)/B78,0) | E78: =MAX(Assumptions!$C$17,ROUND($A78*Assumptions!$C$14,0))*B78*12
A79: 1256 | B79: =(Assumptions!$C$21+Assumptions!$C$33*Assumptions!$C$41*(Assumptions!$C$22+Assumptions!$C$25*MAX(0,UnitEconomics!$D$12-Assumptions!$C$23)*UnitEconomics!$D$31)+Assumptions!$C$34*(Assumptions!$C$26+Assumptions!$C$25*MAX(0,UnitEconomics!$D$15-Assumptions!$C$27)*UnitEconomics!$D$39)+Assumptions!$C$35*Assumptions!$C$29+Assumptions!$C$36*Assumptions!$C$30+Assumptions!$C$37*(Assumptions!$C$116*Assumptions!$C$41+Assumptions!$C$123*Assumptions!$C$41*(1-Assumptions!$C$33))) | C79: =(UnitEconomics!$D$71+Assumptions!$C$33*(Assumptions!$C$41*UnitEconomics!$D$12*UnitEconomics!$D$27+(Assumptions!$C$41*Assumptions!$C$42+Assumptions!$C$43)*Assumptions!$C$98)+Assumptions!$C$34*(UnitEconomics!$D$15*UnitEconomics!$D$38+UnitEconomics!$D$35+UnitEconomics!$D$36)+Assumptions!$C$35*UnitEconomics!$D$74+Assumptions!$C$36*UnitEconomics!$D$75) | D79: =IF(B79>0,(B79-C79)/B79,0) | E79: =MAX(Assumptions!$C$17,ROUND($A79*Assumptions!$C$14,0))*B79*12
A80: 4664 | B80: =(Assumptions!$C$21+Assumptions!$C$33*Assumptions!$C$41*(Assumptions!$C$22+Assumptions!$C$25*MAX(0,UnitEconomics!$D$12-Assumptions!$C$23)*UnitEconomics!$D$31)+Assumptions!$C$34*(Assumptions!$C$26+Assumptions!$C$25*MAX(0,UnitEconomics!$D$15-Assumptions!$C$27)*UnitEconomics!$D$39)+Assumptions!$C$35*Assumptions!$C$29+Assumptions!$C$36*Assumptions!$C$30+Assumptions!$C$37*(Assumptions!$C$116*Assumptions!$C$41+Assumptions!$C$123*Assumptions!$C$41*(1-Assumptions!$C$33))) | C80: =(UnitEconomics!$D$71+Assumptions!$C$33*(Assumptions!$C$41*UnitEconomics!$D$12*UnitEconomics!$D$27+(Assumptions!$C$41*Assumptions!$C$42+Assumptions!$C$43)*Assumptions!$C$98)+Assumptions!$C$34*(UnitEconomics!$D$15*UnitEconomics!$D$38+UnitEconomics!$D$35+UnitEconomics!$D$36)+Assumptions!$C$35*UnitEconomics!$D$74+Assumptions!$C$36*UnitEconomics!$D$75) | D80: =IF(B80>0,(B80-C80)/B80,0) | E80: =MAX(Assumptions!$C$17,ROUND($A80*Assumptions!$C$14,0))*B80*12
A81: 9260 | B81: =(Assumptions!$C$21+Assumptions!$C$33*Assumptions!$C$41*(Assumptions!$C$22+Assumptions!$C$25*MAX(0,UnitEconomics!$D$12-Assumptions!$C$23)*UnitEconomics!$D$31)+Assumptions!$C$34*(Assumptions!$C$26+Assumptions!$C$25*MAX(0,UnitEconomics!$D$15-Assumptions!$C$27)*UnitEconomics!$D$39)+Assumptions!$C$35*Assumptions!$C$29+Assumptions!$C$36*Assumptions!$C$30+Assumptions!$C$37*(Assumptions!$C$116*Assumptions!$C$41+Assumptions!$C$123*Assumptions!$C$41*(1-Assumptions!$C$33))) | C81: =(UnitEconomics!$D$71+Assumptions!$C$33*(Assumptions!$C$41*UnitEconomics!$D$12*UnitEconomics!$D$27+(Assumptions!$C$41*Assumptions!$C$42+Assumptions!$C$43)*Assumptions!$C$98)+Assumptions!$C$34*(UnitEconomics!$D$15*UnitEconomics!$D$38+UnitEconomics!$D$35+UnitEconomics!$D$36)+Assumptions!$C$35*UnitEconomics!$D$74+Assumptions!$C$36*UnitEconomics!$D$75) | D81: =IF(B81>0,(B81-C81)/B81,0) | E81: =MAX(Assumptions!$C$17,ROUND($A81*Assumptions!$C$14,0))*B81*12
A83: Seats: texting volume is held at base, though more seats would send more. Minutes: voice cost moves in step with minutes at the base cost per minute. Hosting per tenant is held at today's tenant count.
